Workbook

Sheet PLANILLA GENERAL ABRIL 2026
A1: Índice | B1: RUT (sin puntos y con guion) | C1: ID (rut sin puntos, sin guión ni digito vertificador) | D1: APELLIDO PATERNO | E1: APELLIDO MATERNO | F1: NOMBRES | G1: CARGO | H1: INICIO DE CONTRATO | I1: D/I | J1: GENERO M/F | K1: TURNO (5x2-4x3-14x14 -art22) | L1: CC | M1: 1 | N1: 2 | O1: 3 | P1: 4 | Q1: 5 | R1: 6 | S1: 7 | T1: 8 | U1: 9 | V1: 10 | W1: 11 | X1: 12 | Y1: 13 | Z1: 14 | AA1: 15 | AB1: 16 | AC1: 17 | AD1: 18 | AE1: 19 | AF1: 20 | AG1: 21 | AH1: 22 | AI1: 23 | AJ1: 24 | AK1: 25 | AL1: 26 | AM1: 27 | AN1: 28 | AO1: 29 | AP1: 30 | AQ1: 31 | AR1: (1) | AS1: (2) | AT1: (3) | AU1: (4) | AV1: (5) | AW1: (6) | AX1: (7) | AY1: (8) | AZ1: (9) | BA1: T.D.T. | BB1: 1033-Bono Gestión Variable | BC1: 1029-Bono Compensatorio descanso | BD1: Justificación Bono 10-29 (Compensatorio descanso) | BE1: 1034-Bono Incentivo variable | BF1: Justificación Bono 1034 (Incentivo variable) | BG1: 1140-Bono Responsabilidad 2 | BH1: Justificación 1140 (Bono Responsabilidad) | BI1: 1041-Bono Terreno (Exclusivo proyecto Techint-CMDIC) | BJ1: 1031-Bono Escolaridad I/T (Uso exclusivo Area de Compensaciones) | BK1: 1092-Diferencia de haber | BL1: Justificación Bono 1092 (Diferencia de Haber) | BM1: Cantidad de feriados del mes | BN1: 1082-Bono Compens. Feriado | BO1: 1020-Aguinaldo I/T | BP1: 1140-Bono de Permanencia (Plan de Beneficios) | BQ1: Bono Seguridad BESALCO-MEL | BR1: Bono Q1 (Exclusivo Collahuasi) | BS1: Bono Q2 (Exclusivo Collahuasi) | BT1: Bono Q3 (Exclusivo Collahuasi) | BU1: Bono Q4 (Exclusivo Collahuasi) | BV1: Bono RSA (Exclusivo Collahuasi) | BW1: 1044-Asignación Colación | BX1: Justificación Asignacion Colacion | BY1: 1165-Asignación Movilización 2 | BZ1: Justificación Asignación Movilización 2 | CA1: 1172-Viatico 2 | CB1: Justificación Viatico | CC1: SALA CUNA | CD1: Justificaciión de Asignación (Detalle del beneficio) | CE1: 1032-Bono Escolaridad N/I | CF1: 1124-Asignación familiar Retroactiva | CG1: Descuento por aporte voluntario | CH1: Observaciones generales | CI1: ACUERDO MARCO ACCIONA-CODELCO | CJ1: GRATIFICACION ACUERD MARCO ACCIONA-CODELCO2 | CK1: DIAS ADICIONALES CHIQUICAMATA | CL1: BONO PARTICIPACION CHIQUI | CM1: RETENCION JUDICIAL | CN1: PRESTAMO EMPRESA | CO1: LOS HEROES | CP1: LA ARAUCANA | CQ1: SEGURO | CR1: FALP
A2: 1 | B2: 7365743-1 | C2: 7365743 | D2: BONE | E2: SANTIS | F2: CARLOS ALBERTO | G2: GERENTE GENERAL | I2: I | J2: M | K2: 5X2 | L2: 1710000001 | M2: 1 | N2: 1 | O2: 3 | P2: 3 | Q2: 3 | R2: 1 | S2: 1 | T2: 1 | U2: 1 | V2: 1 | W2: 3 | X2: 3 | Y2: 1 | Z2: 1 | AA2: 1 | AB2: 1 | AC2: 1 | AD2: 3 | AE2: 3 | AF2: 1 | AG2: 1 | AH2: 1 | AI2: 1 | AJ2: 1 | AK2: 3 | AL2: 3 | AM2: 1 | AN2: 1 | AO2: 1 | AP2: 1 | AR2: 21 | AS2: 0 | AT2: 9 | AU2: 0 | AV2: 0 | AW2: 0 | AX2: 0 | AY2: 0 | AZ2: 0 | BA2: 30 | CN2: 601803 | CO2: =VLOOKUP(C2,'LOS HEROES'!$A$2:$D$30,4,0) -> 552163 | CP2: 0 | CQ2: =VLOOKUP(C2,SEGURO!$A$2:$C$28,3,0) -> 46667 | CR2: 0
A3: 2 | B3: 9187205-6 | C3: 9187205 | D3: HERRERA | E3: VERA | F3: OSCAR CRISTIAN | G3: GERENTE DE PROYECTOS | H3: 45676 | I3: I | J3: M | K3: 4X3 | L3: 1790000088 | M3: 1 | N3: 1 | O3: 3 | P3: 3 | Q3: 3 | R3: 1 | S3: 1 | T3: 1 | U3: 1 | V3: 3 | W3: 3 | X3: 3 | Y3: 1 | Z3: 1 | AA3: 1 | AB3: 1 | AC3: 3 | AD3: 3 | AE3: 3 | AF3: 1 | AG3: 1 | AH3: 1 | AI3: 1 | AJ3: 3 | AK3: 3 | AL3: 3 | AM3: 1 | AN3: 1 | AO3: 1 | AP3: 1 | AR3: 18 | AS3: 0 | AT3: 12 | AU3: 0 | AV3: 0 | AW3: 0 | AX3: 0 | AY3: 0 | AZ3: 0 | BA3: 30 | BE3: 328000 | BF3: Bono para llegar a sueldo pactado | BM3: 0 | CP3: 0 | CQ3: 0 | CR3: 0
A4: 3 | B4: 9205219-2 | C4: 9205219 | D4: JOGLAR | E4: ZAMBRANA | F4: ADOLFO | G4: GERENTE GESTION PERSONAS | I4: I | J4: M | K4: 5X2 | L4: 1720000001 | M4: 1 | N4: 1 | O4: 3 | P4: 3 | Q4: 3 | R4: 1 | S4: 1 | T4: 1 | U4: 1 | V4: 3 | W4: 3 | X4: 3 | Y4: 1 | Z4: 1 | AA4: 1 | AB4: 1 | AC4: 3 | AD4: 3 | AE4: 3 | AF4: 1 | AG4: 1 | AH4: 1 | AI4: 1 | AJ4: 3 | AK4: 3 | AL4: 3 | AM4: 1 | AN4: 1 | AO4: 1 | AP4: 1 | AR4: 18 | AS4: 0 | AT4: 12 | AU4: 0 | AV4: 0 | AW4: 0 | AX4: 0 | AY4: 0 | AZ4: 0 | BA4: 30 | CP4: 0 | CQ4: =VLOOKUP(C4,SEGURO!$A$2:$C$28,3,0) -> 46667 | CR4: 0
A5: 4 | B5: 9430404-0 | C5: 9430404 | D5: BARRIA | E5: BARRIENTOS | F5: HARRY ISMAEL | G5: ENCARGADO TALLER MANTENCION | I5: I | J5: M | K5: 5X2 | L5: 1740000002 | M5: 1 | N5: 1 | O5: 3 | P5: 3 | Q5: 3 | R5: 9 | S5: 9 | T5: 9 | U5: 9 | V5: 9 | W5: 9 | X5: 9 | Y5: 9 | Z5: 9 | AA5: 9 | AB5: 9 | AC5: 9 | AD5: 9 | AE5: 9 | AF5: 1 | AG5: 1 | AH5: 1 | AI5: 1 | AJ5: 1 | AK5: 3 | AL5: 3 | AM5: 1 | AN5: 1 | AO5: 1 | AP5: 1 | AR5: 11 | AS5: 0 | AT5: 5 | AU5: 0 | AV5: 0 | AW5: 0 | AX5: 0 | AY5: 0 | AZ5: 14 | BA5: 30 | BY5: 40000 | CA5: 30000 | CB5: Viatico para traslado terminal buses oficina (4 am) | CO5: =VLOOKUP(C5,'LOS HEROES'!$A$2:$D$30,4,0) -> 64673 | CP5: 0 | CQ5: =VLOOKUP(C5,SEGURO!$A$2:$C$28,3,0) -> 18779 | CR5: 0
A6: 5 | B6: 9460969-0 | C6: 9460969 | D6: ARANDA | E6: CAQUEO | F6: LUIS ALFONSO | G6: EXPEDITOR | H6: 45712 | I6: I | J6: M | K6: A | L6: 1790000088 | M6: 1 | N6: 3 | O6: 3 | P6: 3 | AR6: 1 | AS6: 0 | AT6: 3 | AU6: 0 | AV6: 0 | AW6: 0 | AX6: 0 | AY6: 0 | AZ6: 0 | BA6: 4 | BC6: 193599 | BD6: Corresponde a dia pend. Cambio jornada 4x3 transición. | BE6: 33333.333 | BF6: para ajustar sueldo pactado a 1.700.000.- | BM6: 0 | BP6: 75000 | CP6: 0 | CQ6: 0 | CR6: 0
A7: 6 | B7: 9717041-K | C7: 9717041 | D7: OLIVARES | E7: DIAZ | F7: GONZALO LUIS | G7: ENCARGADO DE COMPRAS Y ABASTECIMIENTO | I7: I | J7: M | K7: 5X2 | L7: 1790000088 | M7: 1 | N7: 1 | O7: 3 | P7: 3 | Q7: 3 | R7: 1 | S7: 1 | T7: 1 | U7: 1 | V7: 1 | W7: 3 | X7: 3 | Y7: 1 | Z7: 1 | AA7: 1 | AB7: 1 | AC7: 1 | AD7: 3 | AE7: 3 | AF7: 1 | AG7: 1 | AH7: 1 | AI7: 1 | AJ7: 1 | AK7: 3 | AL7: 3 | AM7: 1 | AN7: 1 | AO7: 1 | AP7: 1 | AR7: 21 | AS7: 0 | AT7: 9 | AU7: 0 | AV7: 0 | AW7: 0 | AX7: 0 | AY7: 0 | AZ7: 0 | BA7: 30 | BW7: 110000 | CO7: =VLOOKUP(C7,'LOS HEROES'!$A$2:$D$30,4,0) -> 100429 | CP7: 0 | CQ7: 0 | CR7: 0
A8: 7 | B8: 9809267-6 | C8: 9809267 | D8: ANGEL | E8: GOMEZ | F8: SERGIO ERNESTO | G8: AYUDANTE GEOSINTETICOS | H8: 46096 | I8: D | J8: M | K8: 7X7 | L8: 1790000091 | M8: 3 | N8: 3 | O8: 3 | P8: 3 | Q8: 3 | R8: 3 | S8: 3 | T8: 2 | U8: 2 | V8: 2 | W8: 2 | X8: 2 | Y8: 2 | Z8: 2 | AA8: 3 | AB8: 3 | AC8: 3 | AD8: 3 | AE8: 3 | AF8: 3 | AG8: 3 | AH8: 2 | AI8: 2 | AJ8: 2 | AK8: 2 | AL8: 2 | AM8: 2 | AN8: 2 | AO8: 3 | AP8: 3 | AR8: 0 | AS8: 14 | AT8: 16 | AU8: 0 | AV8: 0 | AW8: 0 | AX8: 0 | AY8: 0 | AZ8: 0 | BA8: 30 | CP8: 0 | CQ8: 0 | CR8: 0
A9: 8 | B9: 9850740-k | C9: 9850740 | D9: ARAYA | E9: TELLO | F9: JABIEL NICANOR | G9: MAESTRO PRIMERA GEOSINTETICOS | H9: 45992 | I9: D | J9: M | K9: 14X14 B | L9: 1790000090 | M9: 3 | N9: 3 | O9: 3 | P9: 3 | Q9: 3 | R9: 3 | S9: 3 | T9: 2 | U9: 2 | V9: 2 | W9: 2 | X9: 2 | Y9: 2 | Z9: 2 | AA9: 2 | AB9: 2 | AC9: 2 | AD9: 2 | AE9: 2 | AF9: 2 | AG9: 2 | AH9: 3 | AI9: 3 | AJ9: 3 | AK9: 3 | AL9: 3 | AM9: 3 | AN9: 3 | AO9: 3 | AP9: 3 | AR9: 0 | AS9: 14 | AT9: 16 | AU9: 0 | AV9: 0 | AW9: 0 | AX9: 0 | AY9: 0 | AZ9: 0 | BA9: 30 | BC9: 235333 | BD9: DESCANSO PENDIENTE POR CIERRE LABORAL AL 30-04-2026 | BP9: 75000 | CI9: 473333 | CP9: 0 | CQ9: 0 | CR9: 0
A10: 9 | B10: 9912965-4 | C10: 9912965 | D10: PEREZ | E10: OSSANDON | F10: ORIEL EDUARDO | G10: SUPERVISOR CONTROL CALIDAD | I10: I | J10: M | K10: 5X2 | L10: 1740000002 | M10: 9 | N10: 9 | O10: 9 | P10: 9 | Q10: 9 | R10: 9 | S10: 1 | T10: 1 | U10: 1 | V10: 1 | W10: 3 | X10: 3 | Y10: 9 | Z10: 9 | AA10: 9 | AB10: 9 | AC10: 9 | AD10: 9 | AE10: 9 | AF10: 9 | AG10: 9 | AH10: 9 | AI10: 9 | AJ10: 9 | AK10: 9 | AL10: 9 | AM10: 9 | AN10: 9 | AO10: 9 | AP10: 9 | AR10: 4 | AS10: 0 | AT10: 2 | AU10: 0 | AV10: 0 | AW10: 0 | AX10: 0 | AY10: 0 | AZ10: 24 | BA10: 30 | BE10: 519000 | BF10: Bono complemento sueldo | CH10: CENTRO DE COSTO (SIN FAENA) | CP10: 0 | CQ10: 0 | CR10: 0
A11: 10 | B11: 10147391-0 | C11: 10147391 | D11: SEGOVIA | E11: GUERRA | F11: PEDRO ENRIQUE | G11: AYUDANTE GEOSINTETICOS | H11: 45992 | I11: D | J11: M | K11: 14X14 B | L11: 1790000090 | M11: 3 | N11: 3 | O11: 3 | P11: 3 | Q11: 3 | R11: 3 | S11: 3 | T11: 2 | U11: 2 | V11: 2 | W11: 2 | X11: 2 | Y11: 2 | Z11: 2 | AA11: 2 | AB11: 2 | AC11: 2 | AD11: 2 | AE11: 2 | AF11: 2 | AG11: 2 | AH11: 3 | AI11: 3 | AJ11: 3 | AK11: 3 | AL11: 3 | AM11: 3 | AN11: 3 | AO11: 3 | AP11: 3 | AR11: 0 | AS11: 14 | AT11: 16 | AU11: 0 | AV11: 0 | AW11: 0 | AX11: 0 | AY11: 0 | AZ11: 0 | BA11: 30 | BC11: 130833 | BD11: DESCANSO PENDIENTE POR CIERRE LABORAL AL 30-04-2026 | BP11: 75000 | CI11: 473333 | CJ11: 213354 | CP11: 0 | CQ11: 0 | CR11: 0
A12: 11 | B12: 10192082-8 | C12: 10192082 | D12: GUERRERO | E12: GOMEZ | F12: LUIS HUMBERTO | G12: AYUDANTE GEOSINTETICOS | H12: 46096 | I12: D | J12: M | K12: 7X7 | L12: 1790000091 | M12: 3 | N12: 3 | O12: 3 | P12: 3 | Q12: 3 | R12: 3 | S12: 3 | T12: 2 | U12: 2 | V12: 2 | W12: 2 | X12: 2 | Y12: 2 | Z12: 2 | AA12: 3 | AB12: 3 | AC12: 3 | AD12: 3 | AE12: 3 | AF12: 3 | AG12: 3 | AH12: 2 | AI12: 2 | AJ12: 2 | AK12: 2 | AL12: 2 | AM12: 2 | AN12: 2 | AO12: 3 | AP12: 3 | AR12: 0 | AS12: 14 | AT12: 16 | AU12: 0 | AV12: 0 | AW12: 0 | AX12: 0 | AY12: 0 | AZ12: 0 | BA12: 30 | CP12: 0 | CQ12: 0 | CR12: 0
A13: 12 | B13: 10420797-9 | C13: 10420797 | D13: IRRIBARRA | E13: PEÑA | F13: HECTOR LEONIDAS | G13: JEFE RECURSOS HUMANOS PROYECTO | H13: 45704 | I13: I | J13: M | K13: 4X3 | L13: 1790000088 | M13: 1 | N13: 1 | O13: 3 | P13: 3 | Q13: 3 | R13: 1 | S13: 1 | T13: 1 | U13: 1 | V13: 3 | W13: 3 | X13: 3 | Y13: 1 | Z13: 1 | AA13: 1 | AB13: 1 | AC13: 3 | AD13: 3 | AE13: 3 | AF13: 1 | AG13: 1 | AH13: 1 | AI13: 1 | AJ13: 3 | AK13: 3 | AL13: 3 | AM13: 1 | AN13: 1 | AO13: 1 | AP13: 1 | AR13: 18 | AS13: 0 | AT13: 12 | AU13: 0 | AV13: 0 | AW13: 0 | AX13: 0 | AY13: 0 | AZ13: 0 | BA13: 30 | BM13: 0 | BY13: 61241 | CA13: 72000 | CB13: PAGO TRASLADO ALIMENTACION DIC-ENERO-ESPAÑA A TOKY EN EFECTIVO | CM13: 211065 | CP13: 0 | CQ13: 0 | CR13: 0
A14: 13 | B14: 10603186-K | C14: 10603186 | D14: LEON | E14: OLEA | F14: JAIME ANTONIO | G14: TECNICO RECURSOS HUMANOS PROYECTO | H14: 45748 | I14: I | J14: M | K14: A | L14: 1790000088 | M14: 1 | N14: 1 | O14: 3 | P14: 3 | Q14: 3 | R14: 1 | S14: 1 | T14: 1 | U14: 1 | V14: 3 | W14: 3 | X14: 3 | Y14: 1 | Z14: 1 | AA14: 1 | AB14: 1 | AC14: 3 | AD14: 3 | AE14: 3 | AF14: 1 | AG14: 1 | AH14: 1 | AI14: 1 | AJ14: 3 | AK14: 3 | AL14: 3 | AM14: 1 | AN14: 1 | AO14: 1 | AP14: 1 | AR14: 18 | AS14: 0 | AT14: 12 | AU14: 0 | AV14: 0 | AW14: 0 | AX14: 0 | AY14: 0 | AZ14: 0 | BA14: 30 | BE14: 300000 | BF14: Realizar actividades de ADMIN. CAMPAMENTO | BM14: 0 | CM14: 209667 | CP14: 0 | CQ14: 0 | CR14: 0
A15: 14 | B15: 10675506-K | C15: 10675506 | D15: CAMPILLAI | E15: NAVARRO | F15: VICTOR JAVIER | G15: JEFE DE UNIDAD LOGISTICA | I15: I | J15: M | K15: 5X2 | L15: 1740000003 | M15: 1 | N15: 1 | O15: 3 | P15: 3 | Q15: 3 | R15: 1 | S15: 1 | T15: 1 | U15: 1 | V15: 1 | W15: 3 | X15: 3 | Y15: 1 | Z15: 1 | AA15: 1 | AB15: 1 | AC15: 1 | AD15: 3 | AE15: 3 | AF15: 1 | AG15: 1 | AH15: 1 | AI15: 1 | AJ15: 1 | AK15: 3 | AL15: 3 | AM15: 1 | AN15: 1 | AO15: 1 | AP15: 1 | AR15: 21 | AS15: 0 | AT15: 9 | AU15: 0 | AV15: 0 | AW15: 0 | AX15: 0 | AY15: 0 | AZ15: 0 | BA15: 30 | BW15: 110000 | CP15: 0 | CQ15: =VLOOKUP(C15,SEGURO!$A$2:$C$28,3,0) -> 46667 | CR15: =VLOOKUP(C15,FALP!$A$2:$C$13,3,0) -> 17600
A16: 15 | B16: 10742396-6 | C16: 10742396 | D16: ALFARO | E16: CAMPUSANO | F16: EDUARDO ENRIQUE | G16: AYUDANTE GEOSINTETICOS | H16: 46068 | I16: D | J16: M | K16: 7X7 | L16: 1790000091 | M16: 3 | N16: 3 | O16: 3 | P16: 3 | Q16: 3 | R16: 3 | S16: 3 | T16: 2 | U16: 2 | V16: 2 | W16: 2 | X16: 2 | Y16: 2 | Z16: 2 | AA16: 3 | AB16: 3 | AC16: 3 | AD16: 3 | AE16: 3 | AF16: 3 | AG16: 3 | AH16: 2 | AI16: 2 | AJ16: 2 | AK16: 2 | AL16: 2 | AM16: 2 | AN16: 2 | AO16: 3 | AP16: 3 | AR16: 0 | AS16: 14 | AT16: 16 | AU16: 0 | AV16: 0 | AW16: 0 | AX16: 0 | AY16: 0 | AZ16: 0 | BA16: 30 | CP16: 0 | CQ16: 0 | CR16: 0
A17: 16 | B17: 10957493-7 | C17: 10957493 | D17: GONZALEZ | E17: QUINZACARA | F17: LUIS ARNOLDO | G17: CAPATAZ GEOSINTETICOS | H17: 45809 | I17: D | J17: M | K17: B | L17: 1790000088 | M17: 3 | N17: 3 | O17: 3 | P17: 3 | Q17: 3 | R17: 3 | S17: 1 | T17: 1 | U17: 2 | V17: 2 | W17: 2 | X17: 2 | Y17: 2 | Z17: 2 | AA17: 2 | AB17: 2 | AC17: 2 | AD17: 2 | AE17: 2 | AF17: 2 | AG17: 2 | AH17: 3 | AI17: 3 | AJ17: 3 | AK17: 3 | AL17: 3 | AM17: 3 | AN17: 3 | AO17: 3 | AP17: 3 | AR17: 2 | AS17: 13 | AT17: 15 | AU17: 0 | AV17: 0 | AW17: 0 | AX17: 0 | AY17: 0 | AZ17: 0 | BA17: 30 | BM17: 0 | CP17: 0 | CQ17: 0 | CR17: 0
A18: 17 | B18: 11265430-5 | C18: 11265430 | D18: FAUNDEZ | E18: ORTIZ | F18: CESAR HERNAN | G18: TOPÓGRAFO - NIVELADOR | H18: 45748 | I18: I | J18: M | K18: 4x3 | L18: 1790000088 | M18: 1 | N18: 1 | O18: 3 | P18: 3 | Q18: 3 | R18: 1 | S18: 1 | T18: 1 | U18: 1 | V18: 3 | W18: 3 | X18: 3 | Y18: 1 | Z18: 1 | AA18: 1 | AB18: 1 | AC18: 3 | AD18: 3 | AE18: 3 | AF18: 1 | AG18: 1 | AH18: 1 | AI18: 1 | AJ18: 3 | AK18: 3 | AL18: 3 | AM18: 1 | AN18: 1 | AO18: 1 | AP18: 1 | AR18: 18 | AS18: 0 | AT18: 12 | AU18: 0 | AV18: 0 | AW18: 0 | AX18: 0 | AY18: 0 | AZ18: 0 | BA18: 30 | BE18: 837000 | BF18: Bono asignacion de obra | BM18: 0 | CP18: 0 | CQ18: =VLOOKUP(C18,SEGURO!$A$2:$C$28,3,0) -> 45318 | CR18: 0
A19: 18 | B19: 11387365-5 | C19: 11387365 | D19: JOHNSON | E19: SUAZO | F19: CRISTIAN BENJAMIN | G19: CONDUCTOR SERVICIO | H19: 46082 | I19: I | J19: M | K19: 14X14 B | L19: 1790000090 | M19: 3 | N19: 3 | O19: 3 | P19: 3 | Q19: 3 | R19: 3 | S19: 3 | T19: 2 | U19: 2 | V19: 2 | W19: 2 | X19: 2 | Y19: 2 | Z19: 2 | AA19: 2 | AB19: 2 | AC19: 2 | AD19: 2 | AE19: 2 | AF19: 2 | AG19: 2 | AH19: 3 | AI19: 3 | AJ19: 3 | AK19: 3 | AL19: 3 | AM19: 3 | AN19: 3 | AO19: 3 | AP19: 3 | AR19: 0 | AS19: 14 | AT19: 16 | AU19: 0 | AV19: 0 | AW19: 0 | AX19: 0 | AY19: 0 | AZ19: 0 | BA19: 30 | BC19: 215000 | BD19: DESCANSO PENDIENTE POR CIERRE LABORAL AL 30-04-2026 | BP19: 75000 | BY19: 98114 | CI19: 315556 | CP19: 0 | CQ19: 0 | CR19: 0
A20: 19 | B20: 11511458-1 | C20: 11511458 | D20: ASTUDILLO | E20: FRE | F20: JUAN LUIS | G20: MAESTRO SEGUNDA GEOSINTETICOS | H20: 45992 | I20: D | J20: M | K20: 14x14 A | L20: 1790000090 | M20: 2 | N20: 2 | O20: 8 | P20: 8 | Q20: 2 | R20: 2 | S20: 2 | T20: 3 | U20: 3 | V20: 3 | W20: 3 | X20: 3 | Y20: 3 | Z20: 3 | AA20: 3 | AB20: 3 | AC20: 3 | AD20: 3 | AE20: 3 | AF20: 3 | AG20: 3 | AR20: 0 | AS20: 5 | AT20: 14 | AU20: 0 | AV20: 0 | AW20: 0 | AX20: 0 | AY20: 2 | AZ20: 0 | BA20: 21 | BM20: 2 | BN20: 180000 | BP20: 52500 | CI20: 315555 | CO20: =VLOOKUP(C20,'LOS HEROES'!$A$2:$D$30,4,0) -> 62330 | CP20: 0 | CQ20: 0 | CR20: 0
A21: 20 | B21: 11734191-7 | C21: 11734191 | D21: TORRES | E21: LOPEZ | F21: LUIS EDUARDO | G21: OPERADOR CAMIÓN PLUMA | H21: 45756 | I21: D | J21: M | K21: A | L21: 1790000088 | M21: 1 | N21: 1 | O21: 1 | P21: 1 | Q21: 1 | R21: 1 | S21: 1 | T21: 1 | U21: 1 | V21: 1 | W21: 1 | X21: 1 | Y21: 1 | Z21: 1 | AA21: 1 | AB21: 1 | AC21: 1 | AD21: 1 | AE21: 1 | AF21: 1 | AG21: 1 | AH21: 2 | AI21: 2 | AJ21: 2 | AK21: 2 | AL21: 2 | AM21: 2 | AN21: 2 | AO21: 2 | AP21: 2 | AR21: 21 | AS21: 9 | AT21: 0 | AU21: 0 | AV21: 0 | AW21: 0 | AX21: 0 | AY21: 0 | AZ21: 0 | BA21: 30 | BM21: 0 | CP21: 0 | CQ21: 0 | CR21: 0
A22: 21 | B22: 11820207-4 | C22: 11820207 | D22: MIRANDA | E22: CACERES | F22: HECTOR ANTONIO | G22: CAPATAZ GEOSINTETICOS | H22: 46092 | I22: D | J22: M | K22: 14X14 B | L22: 1790000090 | M22: 3 | N22: 3 | O22: 3 | P22: 3 | Q22: 3 | R22: 3 | S22: 3 | T22: 2 | U22: 2 | V22: 2 | W22: 2 | X22: 2 | Y22: 2 | Z22: 2 | AA22: 2 | AB22: 2 | AC22: 2 | AD22: 2 | AE22: 2 | AF22: 2 | AG22: 2 | AH22: 3 | AI22: 3 | AJ22: 3 | AK22: 3 | AL22: 3 | AM22: 3 | AN22: 3 | AO22: 3 | AP22: 3 | AR22: 0 | AS22: 14 | AT22: 16 | AU22: 0 | AV22: 0 | AW22: 0 | AX22: 0 | AY22: 0 | AZ22: 0 | BA22: 30 | BC22: 266667 | BD22: DESCANSO PENDIENTE POR CIERRE LABORAL AL 30-04-2026 | BK22: 160000 | BL22: 1 DIA ADICIONAL POR COUCHING EN ANTOFAGASTA | BP22: 75000 | BY22: 24000 | CI22: 157778 | CP22: 0 | CQ22: 0 | CR22: 0
A23: 22 | B23: 11876153-7 | C23: 11876153 | D23: HERNANDEZ | E23: DE LA FUENTE | F23: FERNANDO HIPOLITO | G23: SUPERVISRO VISITADOR E INSTRUCTOR | I23: I | J23: M | K23: 5X2 | L23: 1790000090 | M23: 1 | N23: 1 | O23: 3 | P23: 3 | Q23: 3 | R23: 1 | S23: 3 | T23: 3 | U23: 1 | V23: 1 | W23: 1 | X23: 1 | Y23: 1 | Z23: 3 | AA23: 3 | AB23: 1 | AC23: 1 | AD23: 1 | AE23: 1 | AF23: 1 | AG23: 3 | AH23: 3 | AI23: 1 | AJ23: 1 | AK23: 1 | AL23: 1 | AM23: 1 | AN23: 1 | AO23: 1 | AP23: 1 | AR23: 21 | AS23: 0 | AT23: 9 | AU23: 0 | AV23: 0 | AW23: 0 | AX23: 0 | AY23: 0 | AZ23: 0 | BA23: 30 | BW23: 110000 | CE23: 77281 | CO23: =VLOOKUP(C23,'LOS HEROES'!$A$2:$D$30,4,0) -> 451560 | CP23: 0 | CQ23: =VLOOKUP(C23,SEGURO!$A$2:$C$28,3,0) -> 46667 | CR23: =VLOOKUP(C23,FALP!$A$2:$C$13,3,0) -> 17600
A24: 23 | B24: 11922653-8 | C24: 11922653 | D24: ANDRADE | E24: CASTRO | F24: LUIS BERNARDO | G24: ENCARGADO DE MANTENCION | I24: I | J24: M | K24: 5X2 | L24: 1790000088 | M24: 4 | N24: 4 | O24: 4 | P24: 4 | Q24: 4 | R24: 4 | S24: 1 | T24: 1 | U24: 1 | V24: 1 | W24: 3 | X24: 3 | Y24: 1 | Z24: 1 | AA24: 1 | AB24: 1 | AC24: 1 | AD24: 3 | AE24: 3 | AF24: 1 | AG24: 1 | AH24: 1 | AI24: 1 | AJ24: 1 | AK24: 3 | AL24: 3 | AM24: 1 | AN24: 1 | AO24: 1 | AP24: 1 | AR24: 18 | AS24: 0 | AT24: 6 | AU24: 6 | AV24: 0 | AW24: 0 | AX24: 0 | AY24: 0 | AZ24: 0 | BA24: 24 | CO24: =VLOOKUP(C24,'LOS HEROES'!$A$2:$D$30,4,0) -> 309350 | CP24: 0 | CQ24: =VLOOKUP(C24,SEGURO!$A$2:$C$28,3,0) -> 32725 | CR24: 0
A25: 24 | B25: 12038137-7 | C25: 12038137 | D25: CORTES | E25: LÓPEZ | F25: MARCELO ANTONIO | G25: MAESTRO SEGUNDA GEOSINTETICOS | H25: 45924 | I25: D | J25: M | K25: B | L25: 1790000088 | M25: 1 | N25: 1 | O25: 1 | P25: 1 | Q25: 1 | R25: 1 | S25: 1 | T25: 1 | U25: 1 | V25: 1 | W25: 1 | AR25: 11 | AS25: 0 | AT25: 0 | AU25: 0 | AV25: 0 | AW25: 0 | AX25: 0 | AY25: 0 | AZ25: 0 | BA25: 11 | BM25: 0 | CP25: 0 | CQ25: 0 | CR25: 0
A26: 25 | B26: 12227004-1 | C26: 12227004 | D26: NARVAEZ | E26: PEÑA | F26: ALDO IVAN | G26: SUBGERENTE TECNICO | I26: I | J26: M | K26: 5X2 | L26: 1760000001 | M26: 1 | N26: 1 | O26: 3 | P26: 3 | Q26: 3 | R26: 1 | S26: 1 | T26: 1 | U26: 1 | V26: 1 | W26: 3 | X26: 3 | Y26: 1 | Z26: 1 | AA26: 1 | AB26: 1 | AC26: 1 | AD26: 3 | AE26: 3 | AF26: 1 | AG26: 1 | AH26: 1 | AI26: 1 | AJ26: 1 | AK26: 3 | AL26: 3 | AM26: 1 | AN26: 1 | AO26: 1 | AP26: 1 | AR26: 21 | AS26: 0 | AT26: 9 | AU26: 0 | AV26: 0 | AW26: 0 | AX26: 0 | AY26: 0 | AZ26: 0 | BA26: 30 | BE26: 179000 | BF26: Bono ajuste liquido pactado | CP26: 0 | CQ26: =VLOOKUP(C26,SEGURO!$A$2:$C$28,3,0) -> 32725 | CR26: =VLOOKUP(C26,FALP!$A$2:$C$13,3,0) -> 17600
A27: 26 | B27: 12397806-4 | C27: 12397806 | D27: RAMIREZ | E27: ORTEGA | F27: JUAN SIMON | G27: MAESTRO SEGUNDA GEOSINTETICOS | H27: 46064 | I27: D | J27: M | K27: 14X14 A | L27: 1790000090 | M27: 2 | N27: 2 | O27: 8 | P27: 8 | Q27: 2 | R27: 2 | S27: 2 | T27: 3 | U27: 3 | V27: 3 | W27: 3 | X27: 3 | Y27: 3 | Z27: 3 | AA27: 3 | AB27: 3 | AC27: 3 | AD27: 3 | AE27: 3 | AF27: 3 | AG27: 3 | AR27: 0 | AS27: 5 | AT27: 14 | AU27: 0 | AV27: 0 | AW27: 0 | AX27: 0 | AY27: 2 | AZ27: 0 | BA27: 21 | BM27: 2 | BN27: 180000 | BP27: 52500 | CI27: 157778 | CP27: 0 | CQ27: 0 | CR27: 0
A28: 27 | B28: 12443848-9 | C28: 12443848 | D28: MEDALLA | E28: CASTILLO | F28: MANUEL SEGUNDO | G28: AYUDANTE GEOSINTETICOS | H28: 46096 | I28: D | J28: M | K28: 7X7 | L28: 1790000091 | M28: 3 | N28: 3 | O28: 3 | P28: 3 | Q28: 3 | R28: 3 | S28: 3 | T28: 2 | U28: 2 | V28: 2 | W28: 2 | X28: 2 | Y28: 2 | Z28: 2 | AA28: 3 | AB28: 3 | AC28: 3 | AD28: 3 | AE28: 3 | AF28: 3 | AG28: 3 | AH28: 2 | AI28: 2 | AJ28: 2 | AK28: 2 | AL28: 2 | AM28: 2 | AN28: 2 | AO28: 3 | AP28: 3 | AR28: 0 | AS28: 14 | AT28: 16 | AU28: 0 | AV28: 0 | AW28: 0 | AX28: 0 | AY28: 0 | AZ28: 0 | BA28: 30 | CP28: 0 | CQ28: 0 | CR28: 0
A29: 28 | B29: 12487485-8 | C29: 12487485 | D29: SILVA | E29: BOCK | F29: DANIELA VIVIAN | G29: JEFE UNIDAD COMPENSACIONES | I29: I | J29: F | K29: 5X2 | L29: 1720000001 | M29: 1 | N29: 1 | O29: 3 | P29: 3 | Q29: 3 | R29: 1 | S29: 1 | T29: 1 | U29: 1 | V29: 1 | W29: 3 | X29: 3 | Y29: 1 | Z29: 1 | AA29: 1 | AB29: 1 | AC29: 9 | AD29: 3 | AE29: 3 | AF29: 1 | AG29: 1 | AH29: 1 | AI29: 1 | AJ29: 1 | AK29: 3 | AL29: 3 | AM29: 1 | AN29: 1 | AO29: 1 | AP29: 1 | AR29: 20 | AS29: 0 | AT29: 9 | AU29: 0 | AV29: 0 | AW29: 0 | AX29: 0 | AY29: 0 | AZ29: 1 | BA29: 30 | CP29: 0 | CQ29: =VLOOKUP(C29,SEGURO!$A$2:$C$28,3,0) -> 18779 | CR29: =VLOOKUP(C29,FALP!$A$2:$C$13,3,0) -> 17600
A30: 29 | B30: 12543039-2 | C30: 12543039 | D30: AVILA | E30: LINEROS | F30: AUDIAS ABDENEGO | G30: AYUDANTE GEOSINTETICOS | H30: 45995 | I30: D | J30: M | K30: 14X14 B | L30: 1790000090 | M30: 3 | N30: 3 | O30: 3 | P30: 3 | Q30: 3 | R30: 3 | S30: 3 | T30: 2 | U30: 2 | V30: 2 | W30: 2 | X30: 2 | Y30: 2 | Z30: 2 | AA30: 2 | AB30: 2 | AC30: 2 | AD30: 2 | AE30: 2 | AF30: 2 | AG30: 2 | AH30: 3 | AI30: 3 | AJ30: 3 | AK30: 3 | AL30: 3 | AM30: 3 | AN30: 3 | AO30: 3 | AP30: 3 | AR30: 0 | AS30: 14 | AT30: 16 | AU30: 0 | AV30: 0 | AW30: 0 | AX30: 0 | AY30: 0 | AZ30: 0 | BA30: 30 | BC30: 130833 | BD30: DESCANSO PENDIENTE POR CIERRE LABORAL AL 30-04-2026 | BP30: 75000 | BY30: 50900 | CI30: 473333 | CJ30: 213354 | CP30: 0 | CQ30: 0 | CR30: 0
A31: 30 | B31: 12572374-8 | C31: 12572374 | D31: PEREZ | E31: CARVAJAL | F31: ALBERTO HERNAN | G31: CONDUCTOR SERVICIO | H31: 46082 | I31: I | J31: M | K31: 14X14 A | L31: 1790000090 | M31: 2 | N31: 2 | O31: 8 | P31: 8 | Q31: 2 | R31: 2 | S31: 2 | T31: 3 | U31: 3 | V31: 3 | W31: 3 | X31: 3 | Y31: 3 | Z31: 3 | AA31: 3 | AB31: 3 | AC31: 3 | AD31: 3 | AE31: 3 | AF31: 3 | AG31: 3 | AR31: 0 | AS31: 5 | AT31: 14 | AU31: 0 | AV31: 0 | AW31: 0 | AX31: 0 | AY31: 2 | AZ31: 0 | BA31: 21 | BM31: 2 | BN31: 258000 | BP31: 52500 | CI31: 157778 | CP31: 0 | CQ31: 0 | CR31: 0
A32: 31 | B32: 12612919-k | C32: 12612919 | D32: HERRERA | E32: CORTES | F32: JUVENAL HUMBERTO | G32: AYUDANTE GEOSINTETICOS | H32: 45858 | I32: D | J32: M | K32: A | L32: 1790000088 | M32: 2 | N32: 2 | O32: 8 | P32: 8 | Q32: 2 | R32: 2 | S32: 2 | T32: 3 | U32: 3 | V32: 3 | W32: 3 | X32: 3 | Y32: 3 | Z32: 3 | AA32: 3 | AB32: 3 | AC32: 3 | AD32: 3 | AE32: 3 | AF32: 3 | AG32: 3 | AH32: 2 | AI32: 2 | AJ32: 2 | AK32: 2 | AL32: 2 | AM32: 2 | AN32: 2 | AO32: 2 | AP32: 2 | AR32: 0 | AS32: 14 | AT32: 14 | AU32: 0 | AV32: 0 | AW32: 0 | AX32: 0 | AY32: 2 | AZ32: 0 | BA32: 30 | BM32: 2 | BN32: 149200 | CP32: 0 | CQ32: 0 | CR32: 0
A33: 32 | B33: 12807347-7 | C33: 12807347 | D33: CORTES | E33: MONARDES | F33: PABLO ANTONIO | G33: MAESTRO SEGUNDA GEOSINTETICOS | H33: 46003 | I33: D | J33: M | K33: 14X14 B | L33: 1790000090 | M33: 3 | N33: 3 | O33: 3 | P33: 3 | Q33: 3 | R33: 3 | S33: 3 | T33: 2 | U33: 2 | V33: 2 | W33: 2 | X33: 2 | Y33: 2 | Z33: 2 | AA33: 2 | AB33: 2 | AC33: 2 | AD33: 2 | AE33: 2 | AF33: 2 | AG33: 2 | AH33: 3 | AI33: 3 | AJ33: 3 | AK33: 3 | AL33: 3 | AM33: 3 | AN33: 3 | AO33: 3 | AP33: 3 | AR33: 0 | AS33: 14 | AT33: 16 | AU33: 0 | AV33: 0 | AW33: 0 | AX33: 0 | AY33: 0 | AZ33: 0 | BA33: 30 | BC33: 150000 | BD33: DESCANSO PENDIENTE POR CIERRE LABORAL AL 30-04-2026 | BP33: 75000 | CI33: 473333 | CP33: 0 | CQ33: 0 | CR33: 0
A34: 33 | B34: 12943659-K | C34: 12943659 | D34: SANTANDER | E34: SANTANDER | F34: CARLOS LUIS | G34: SUPERVISOR GEOSINTETICOS | H34: 45992 | I34: I | J34: M | K34: 14x14 B | L34: 1790000090 | M34: 3 | N34: 3 | O34: 3 | P34: 3 | Q34: 3 | R34: 3 | S34: 3 | T34: 2 | U34: 2 | V34: 2 | W34: 2 | X34: 2 | Y34: 2 | Z34: 2 | AA34: 2 | AB34: 2 | AC34: 2 | AD34: 2 | AE34: 2 | AF34: 2 | AG34: 2 | AH34: 3 | AI34: 3 | AJ34: 3 | AK34: 3 | AL34: 3 | AM34: 3 | AN34: 3 | AO34: 3 | AP34: 3 | AR34: 0 | AS34: 14 | AT34: 16 | AU34: 0 | AV34: 0 | AW34: 0 | AX34: 0 | AY34: 0 | AZ34: 0 | BA34: 30 | BC34: 428833 | BD34: DESCANSO PENDIENTE POR CIERRE LABORAL AL 30-04-2026 | BE34: 860000 | BF34: Bono acuerdo salarial | BK34: 257300 | BL34: 1 DIA ADICIONAL POR COUCHING EN ANTOFAGASTA | CE34: 77281 | CI34: 473333 | CO34: =VLOOKUP(C34,'LOS HEROES'!$A$2:$D$30,4,0) -> 290002 | CP34: 0 | CQ34: 0 | CR34: 0
A35: 34 | B35: 12953191-6 | C35: 12953191 | D35: ARELLANO | E35: ARRIAZA | F35: MARCO ANTONIO | G35: TECNICO RRHH PROYECTO | H35: 45971 | I35: D | J35: M | K35: 14x14 D | L35: 1790000090 | M35: 3 | N35: 3 | O35: 3 | P35: 3 | Q35: 3 | R35: 3 | S35: 3 | T35: 3 | U35: 3 | V35: 3 | W35: 3 | X35: 3 | Y35: 3 | Z35: 3 | AA35: 2 | AB35: 2 | AC35: 2 | AD35: 2 | AE35: 2 | AF35: 2 | AG35: 2 | AH35: 2 | AI35: 2 | AJ35: 2 | AK35: 2 | AL35: 2 | AM35: 2 | AN35: 2 | AO35: 3 | AP35: 3 | AR35: 0 | AS35: 14 | AT35: 16 | AU35: 0 | AV35: 0 | AW35: 0 | AX35: 0 | AY35: 0 | AZ35: 0 | BA35: 30 | BC35: 620000 | BD35: DESCANSO PENDIENTE POR CIERRE LABORAL AL 30-04-2026 | BP35: 75000 | BY35: 31000 | CI35: 473333 | CP35: 0 | CQ35: 0 | CR35: 0
A36: 35 | B36: 13012039-3 | C36: 13012039 | D36: LOBOS | E36: PIZARRO | F36: JORGE HUMBERTO | G36: JEFE CONTROL DE CALIDAD | H36: 46118 | I36: I | J36: M | K36: 5X2 | L36: 1790000088 | R36: 1 | S36: 1 | T36: 1 | U36: 1 | V36: 1 | W36: 3 | X36: 3 | Y36: 1 | Z36: 1 | AA36: 1 | AB36: 1 | AC36: 1 | AD36: 3 | AE36: 3 | AF36: 1 | AG36: 1 | AH36: 1 | AI36: 1 | AJ36: 1 | AK36: 3 | AL36: 3 | AM36: 1 | AN36: 1 | AO36: 1 | AP36: 1 | AR36: 19 | AS36: 0 | AT36: 6 | AU36: 0 | AV36: 0 | AW36: 0 | AX36: 0 | AY36: 0 | AZ36: 0 | BA36: 25 | CP36: 0 | CQ36: 0 | CR36: 0
A37: 36 | B37: 13076470-3 | C37: 13076470 | D37: REHBEIN | E37: GANTES | F37: ANTONIO ALEJANDRO | G37: JEFE DE TERRENO | H37: 45805 | I37: I | J37: M | K37: B | L37: 1790000088 | M37: 3 | N37: 3 | O37: 3 | P37: 3 | Q37: 3 | R37: 3 | S37: 3 | T37: 2 | U37: 2 | V37: 2 | W37: 2 | X37: 2 | Y37: 1 | Z37: 1 | AA37: 2 | AB37: 2 | AC37: 2 | AD37: 2 | AE37: 2 | AF37: 2 | AG37: 2 | AH37: 3 | AI37: 3 | AJ37: 3 | AK37: 3 | AL37: 3 | AM37: 3 | AN37: 3 | AO37: 3 | AP37: 3 | AR37: 2 | AS37: 12 | AT37: 16 | AU37: 0 | AV37: 0 | AW37: 0 | AX37: 0 | AY37: 0 | AZ37: 0 | BA37: 30 | BE37: 375000 | BF37: Bono ajuste salarial | BM37: 0 | CP37: 0 | CQ37: 0 | CR37: 0
A38: 37 | B38: 13172993-6 | C38: 13172993 | D38: GODOY | E38: CORTES | F38: SANDRA ROSARIO | G38: ADMINISTRATIVO OFICINA TECNICA | H38: 45839 | I38: I | J38: F | K38: 4X3 | L38: 1790000088 | M38: 1 | N38: 3 | O38: 3 | P38: 3 | AR38: 1 | AS38: 0 | AT38: 3 | AU38: 0 | AV38: 0 | AW38: 0 | AX38: 0 | AY38: 0 | AZ38: 0 | BA38: 4 | BM38: 0 | CP38: 0 | CQ38: 0 | CR38: 0
A39: 38 | B39: 13174740-3 | C39: 13174740 | D39: ROJAS | E39: GERALDO | F39: EUGENIO DAVID | G39: MAESTRO SEGUNDA GEOSINTETICOS | H39: 45846 | I39: D | J39: M | K39: B | L39: 1790000088 | M39: 3 | N39: 3 | O39: 3 | P39: 3 | Q39: 3 | R39: 3 | S39: 3 | T39: 2 | U39: 2 | V39: 2 | W39: 2 | X39: 2 | Y39: 2 | Z39: 2 | AA39: 2 | AB39: 2 | AC39: 2 | AD39: 2 | AE39: 2 | AF39: 2 | AG39: 2 | AH39: 3 | AI39: 3 | AJ39: 3 | AK39: 3 | AL39: 3 | AM39: 3 | AN39: 3 | AO39: 3 | AP39: 3 | AR39: 0 | AS39: 14 | AT39: 16 | AU39: 0 | AV39: 0 | AW39: 0 | AX39: 0 | AY39: 0 | AZ39: 0 | BA39: 30 | BM39: 0 | CP39: 0 | CQ39: 0 | CR39: 0
A40: 39 | B40: 13179077-5 | C40: 13179077 | D40: GUERRERO | E40: GARCÍA | F40: PEDRO FREDDY | G40: JEFE PREVENCION DE RIESGOS | H40: 45957 | I40: I | J40: M | K40: 4X3 | L40: 1790000090 | M40: 2 | N40: 2 | O40: 3 | P40: 3 | Q40: 3 | R40: 2 | S40: 2 | T40: 2 | U40: 2 | V40: 3 | W40: 3 | X40: 3 | Y40: 2 | Z40: 2 | AA40: 2 | AB40: 2 | AC40: 3 | AD40: 3 | AE40: 3 | AF40: 2 | AG40: 2 | AH40: 2 | AI40: 2 | AJ40: 3 | AK40: 3 | AL40: 3 | AM40: 2 | AN40: 2 | AO40: 2 | AP40: 2 | AR40: 0 | AS40: 18 | AT40: 12 | AU40: 0 | AV40: 0 | AW40: 0 | AX40: 0 | AY40: 0 | AZ40: 0 | BA40: 30 | BC40: 333600 | BD40: DIA ADICIONAL PENDIENTE POR REEMPLAZO DE APR (M. IBARRA) | BY40: 120050 | CI40: 473333 | CK40: 1000800 | CL40: 100000 | CP40: 0 | CQ40: 0 | CR40: 0
A41: 40 | B41: 13205525-4 | C41: 13205525 | D41: ORTIZ | E41: MEDEL | F41: SEBASTIAN DEL CARMEN | G41: CONDUCTOR CAMION RAMPA | H41: 44136 | I41: D | J41: M | K41: 5X2 | L41: 1790000088 | M41: 5 | N41: 5 | O41: 5 | P41: 5 | Q41: 5 | R41: 9 | S41: 9 | T41: 9 | U41: 9 | V41: 9 | W41: 9 | X41: 9 | Y41: 9 | Z41: 9 | AA41: 9 | AB41: 9 | AC41: 9 | AD41: 9 | AE41: 9 | AF41: 9 | AG41: 9 | AH41: 9 | AI41: 9 | AJ41: 9 | AK41: 9 | AL41: 9 | AM41: 9 | AN41: 9 | AO41: 9 | AP41: 9 | AR41: 0 | AS41: 0 | AT41: 0 | AU41: 0 | AV41: 5 | AW41: 0 | AX41: 0 | AY41: 0 | AZ41: 25 | BA41: 30 | CO41: =VLOOKUP(C41,'LOS HEROES'!$A$2:$D$30,4,0) -> 343828 | CP41: 0 | CQ41: 0 | CR41: 0
A42: 41 | B42: 13218666-9 | C42: 13218666 | D42: OYARCE | E42: CARVAJAL | F42: LUIS RICARDO | G42: TECNICO CONTROL CALIDAD | H42: 46092 | I42: D | J42: M | K42: 14X14 A | L42: 1790000090 | M42: 2 | N42: 2 | O42: 8 | P42: 8 | Q42: 2 | R42: 2 | S42: 2 | T42: 3 | U42: 3 | V42: 3 | W42: 3 | X42: 3 | Y42: 3 | Z42: 3 | AA42: 3 | AB42: 3 | AC42: 3 | AD42: 3 | AE42: 3 | AF42: 3 | AG42: 3 | AR42: 0 | AS42: 5 | AT42: 14 | AU42: 0 | AV42: 0 | AW42: 0 | AX42: 0 | AY42: 2 | AZ42: 0 | BA42: 21 | BM42: 2 | BN42: 282400 | BP42: 52500 | CI42: 0 | CP42: 0 | CQ42: 0 | CR42: 0
A43: 42 | B43: 13327527-4 | C43: 13327527 | D43: POBLETE | E43: GALLARDO | F43: VICTOR ANTONIO | G43: SUPERVISOR GEOSINTETICOS | H43: 46054 | I43: I | J43: M | K43: 7X7 | L43: 1790000091 | M43: 3 | N43: 3 | O43: 3 | P43: 3 | Q43: 3 | R43: 3 | S43: 3 | T43: 2 | U43: 2 | V43: 2 | W43: 2 | X43: 2 | Y43: 2 | Z43: 2 | AA43: 3 | AB43: 3 | AC43: 3 | AD43: 3 | AE43: 3 | AF43: 3 | AG43: 3 | AH43: 2 | AI43: 2 | AJ43: 2 | AK43: 2 | AL43: 2 | AM43: 2 | AN43: 2 | AO43: 3 | AP43: 3 | AR43: 0 | AS43: 14 | AT43: 16 | AU43: 0 | AV43: 0 | AW43: 0 | AX43: 0 | AY43: 0 | AZ43: 0 | BA43: 30 | BE43: 646000 | BF43: Bono asignación de obra | CP43: =VLOOKUP(C43,'LA ARAUCANA'!$A$2:$D$5,4,0) -> 154868 | CQ43: 0 | CR43: 0
A44: 43 | B44: 13330676-5 | C44: 13330676 | D44: VEGA | E44: JIMENEZ | F44: JUAN CARLOS | G44: CAPATAZ GEOSINTETICOS | H44: 46054 | I44: D | J44: M | K44: 14X14 A | L44: 1790000090 | M44: 2 | N44: 2 | O44: 8 | P44: 8 | Q44: 2 | R44: 2 | S44: 2 | T44: 3 | U44: 3 | V44: 3 | W44: 3 | X44: 3 | Y44: 3 | Z44: 3 | AA44: 3 | AB44: 3 | AC44: 3 | AD44: 3 | AE44: 3 | AF44: 3 | AG44: 3 | AR44: 0 | AS44: 5 | AT44: 14 | AU44: 0 | AV44: 0 | AW44: 0 | AX44: 0 | AY44: 2 | AZ44: 0 | BA44: 21 | BM44: 2 | BN44: 320000 | BP44: 52500 | CI44: 315555 | CP44: 0 | CQ44: 0 | CR44: 0
A45: 44 | B45: 13419327-1 | C45: 13419327 | D45: MIRANDA | E45: MERCADO | F45: MARCO ANTONIO | G45: SUPERVISOR GEOSINTETICOS | H45: 45962 | I45: I | J45: M | K45: 14x14 A | L45: 1790000090 | M45: 2 | N45: 2 | O45: 8 | P45: 8 | Q45: 2 | R45: 2 | S45: 2 | T45: 3 | U45: 3 | V45: 3 | W45: 3 | X45: 3 | Y45: 3 | Z45: 3 | AA45: 3 | AB45: 3 | AC45: 3 | AD45: 3 | AE45: 3 | AF45: 3 | AG45: 3 | AH45: 2 | AI45: 2 | AJ45: 2 | AK45: 2 | AL45: 2 | AM45: 2 | AN45: 2 | AO45: 2 | AP45: 2 | AR45: 0 | AS45: 14 | AT45: 14 | AU45: 0 | AV45: 0 | AW45: 0 | AX45: 0 | AY45: 2 | AZ45: 0 | BA45: 30 | BE45: 792000 | BF45: Bono acuerdo salarial | BM45: 2 | BN45: 512000 | CI45: 473333 | CM45: 597267 | CP45: 0 | CQ45: =VLOOKUP(C45,SEGURO!$A$2:$C$28,3,0) -> 46667 | CR45: 0
A46: 45 | B46: 13531208-8 | C46: 13531208 | D46: ARAYA | E46: REYES | F46: MARCO ANTONIO | G46: JEFE PREVENCIÓN DE RIESGOS | H46: 45689 | I46: I | J46: M | K46: 4X3 | L46: 1790000088 | M46: 1 | N46: 1 | O46: 3 | P46: 3 | Q46: 3 | R46: 1 | S46: 1 | T46: 1 | U46: 1 | V46: 3 | W46: 3 | X46: 3 | Y46: 1 | Z46: 1 | AA46: 1 | AB46: 1 | AC46: 3 | AD46: 3 | AE46: 3 | AF46: 1 | AG46: 1 | AH46: 1 | AI46: 1 | AJ46: 3 | AK46: 3 | AL46: 3 | AM46: 1 | AN46: 1 | AO46: 1 | AP46: 1 | AR46: 18 | AS46: 0 | AT46: 12 | AU46: 0 | AV46: 0 | AW46: 0 | AX46: 0 | AY46: 0 | AZ46: 0 | BA46: 30 | BE46: 1634000 | BF46: Bono para llegar a monto asignado | BM46: 0 | CE46: 77281 | CP46: 0 | CQ46: =VLOOKUP(C46,SEGURO!$A$2:$C$28,3,0) -> 46667 | CR46: =VLOOKUP(C46,FALP!$A$2:$C$13,3,0) -> 17600
A47: 46 | B47: 13534540-7 | C47: 13534540 | D47: TORO | E47: VARAS | F47: JORGE ARMANDO | G47: AYUDANTE GEOSINTETICOS | H47: 45992 | I47: D | J47: M | K47: 14x14 B | L47: 1790000090 | M47: 3 | N47: 3 | O47: 3 | P47: 3 | Q47: 3 | R47: 3 | S47: 3 | T47: 2 | U47: 2 | V47: 2 | W47: 2 | X47: 2 | Y47: 2 | Z47: 2 | AA47: 2 | AB47: 2 | AC47: 2 | AD47: 2 | AE47: 2 | AF47: 2 | AG47: 2 | AH47: 3 | AI47: 3 | AJ47: 3 | AK47: 3 | AL47: 3 | AM47: 3 | AN47: 3 | AO47: 3 | AP47: 3 | AR47: 0 | AS47: 14 | AT47: 16 | AU47: 0 | AV47: 0 | AW47: 0 | AX47: 0 | AY47: 0 | AZ47: 0 | BA47: 30 | BC47: 130833 | BD47: DESCANSO PENDIENTE POR CIERRE LABORAL AL 30-04-2026 | BP47: 75000 | CI47: 473333 | CJ47: 213354 | CP47: 0 | CQ47: 0 | CR47: 0
A48: 47 | B48: 13632515-9 | C48: 13632515 | D48: CLARK | E48: ALFARO | F48: MAURICIO ANDRES | G48: JEFE DE TERRENO | H48: 45962 | I48: D | J48: M | K48: 14x14 A | L48: 1790000090 | M48: 2 | N48: 2 | O48: 8 | P48: 8 | Q48: 2 | R48: 2 | S48: 2 | T48: 3 | U48: 3 | V48: 3 | W48: 3 | X48: 3 | Y48: 3 | Z48: 3 | AA48: 3 | AB48: 3 | AC48: 3 | AD48: 3 | AE48: 3 | AF48: 3 | AG48: 3 | AH48: 2 | AI48: 2 | AJ48: 2 | AK48: 2 | AL48: 2 | AM48: 2 | AN48: 2 | AO48: 2 | AP48: 2 | AR48: 0 | AS48: 14 | AT48: 14 | AU48: 0 | AV48: 0 | AW48: 0 | AX48: 0 | AY48: 2 | AZ48: 0 | BA48: 30 | BE48: 1877000 | BF48: Bono acuerdo salarial | BM48: 2 | BN48: 718000 | CE48: 77281 | CI48: 473333 | CK48: 3230999 | CL48: 100000 | CP48: 0 | CQ48: 0 | CR48: 0
A49: 48 | B49: 13640892-5 | C49: 13640892 | D49: CACERES | E49: MUÑOZ | F49: ANIBAL JOSE | G49: JEFE RRHH PROYECTO | H49: 45962 | I49: I | J49: M | K49: 4X3 | L49: 1790000090 | M49: 2 | N49: 2 | O49: 3 | P49: 3 | Q49: 3 | R49: 2 | S49: 2 | T49: 2 | U49: 2 | V49: 3 | W49: 3 | X49: 3 | Y49: 2 | Z49: 2 | AA49: 2 | AB49: 2 | AC49: 3 | AD49: 3 | AE49: 3 | AF49: 2 | AG49: 2 | AH49: 2 | AI49: 2 | AJ49: 3 | AK49: 3 | AL49: 3 | AM49: 2 | AN49: 2 | AO49: 2 | AP49: 2 | AR49: 0 | AS49: 18 | AT49: 12 | AU49: 0 | AV49: 0 | AW49: 0 | AX49: 0 | AY49: 0 | AZ49: 0 | BA49: 30 | BC49: 269600 | BD49: 1 DIA ADICIONAL POR TRABAJOS DE AUDITORIA Y CIERRE MES FUERA TURNO | BY49: 157655 | CI49: 473333 | CP49: 0 | CQ49: 0 | CR49: 0
A50: 49 | B50: 13702938-3 | C50: 13702938 | D50: VEGA | E50: GUERRERO | F50: VICTOR ANDRES | G50: SUPERVISOR GEOSINTETICOS | H50: 45702 | I50: I | J50: M | K50: A | L50: 1790000088 | M50: 2 | N50: 2 | O50: 8 | P50: 8 | Q50: 2 | R50: 2 | S50: 2 | T50: 3 | U50: 3 | V50: 3 | W50: 3 | X50: 3 | Y50: 3 | Z50: 3 | AA50: 3 | AB50: 3 | AC50: 3 | AD50: 3 | AE50: 3 | AF50: 3 | AG50: 3 | AH50: 2 | AI50: 2 | AJ50: 2 | AK50: 2 | AL50: 2 | AM50: 2 | AN50: 2 | AO50: 2 | AP50: 2 | AR50: 0 | AS50: 14 | AT50: 14 | AU50: 0 | AV50: 0 | AW50: 0 | AX50: 0 | AY50: 2 | AZ50: 0 | BA50: 30 | BM50: 2 | BN50: 488018 | BY50: 12000 | CP50: 0 | CQ50: =VLOOKUP(C50,SEGURO!$A$2:$C$28,3,0) -> 46667 | CR50: 0
A51: 50 | B51: 13904453-3 | C51: 13904453 | D51: TORO | E51: ANDRADE | F51: ESTEBAN | G51: GERENTE DE PLANIFICACION Y CONTROL | I51: I | J51: M | K51: 5X2 | L51: 1740000001 | M51: 1 | N51: 1 | O51: 3 | P51: 3 | Q51: 3 | R51: 1 | S51: 1 | T51: 1 | U51: 1 | V51: 1 | W51: 3 | X51: 3 | Y51: 1 | Z51: 1 | AA51: 1 | AB51: 1 | AC51: 1 | AD51: 3 | AE51: 3 | AF51: 1 | AG51: 1 | AH51: 1 | AI51: 1 | AJ51: 1 | AK51: 3 | AL51: 3 | AM51: 1 | AN51: 1 | AO51: 1 | AP51: 1 | AR51: 21 | AS51: 0 | AT51: 9 | AU51: 0 | AV51: 0 | AW51: 0 | AX51: 0 | AY51: 0 | AZ51: 0 | BA51: 30 | CP51: 0 | CQ51: =VLOOKUP(C51,SEGURO!$A$2:$C$28,3,0) -> 46667 | CR51: =VLOOKUP(C51,FALP!$A$2:$C$13,3,0) -> 8800
A52: 51 | B52: 13975512-k | C52: 13975512 | D52: BRUNA | E52: MUÑOZ | F52: EDUARDO ENRIQUE | G52: MAESTRO PRIMERA GEOSINTETICOS | H52: 46041 | I52: D | J52: M | K52: 14X14 B | L52: 1790000090 | M52: 3 | N52: 3 | O52: 3 | P52: 3 | Q52: 3 | R52: 3 | S52: 3 | T52: 2 | U52: 2 | V52: 2 | W52: 2 | X52: 2 | Y52: 2 | Z52: 2 | AA52: 2 | AB52: 2 | AC52: 2 | AD52: 2 | AE52: 2 | AF52: 2 | AG52: 2 | AH52: 3 | AI52: 3 | AJ52: 3 | AK52: 3 | AL52: 3 | AM52: 3 | AN52: 3 | AO52: 3 | AP52: 3 | AR52: 0 | AS52: 14 | AT52: 16 | AU52: 0 | AV52: 0 | AW52: 0 | AX52: 0 | AY52: 0 | AZ52: 0 | BA52: 30 | BC52: 235333 | BD52: DESCANSO PENDIENTE POR CIERRE LABORAL AL 30-04-2026 | BP52: 75000 | CI52: 473333 | CP52: 0 | CQ52: 0 | CR52: 0
A53: 52 | B53: 13976044-1 | C53: 13976044 | D53: VALENZUELA | E53: SEGOVIA | F53: RODRIGO ANTONIO | G53: MAESTRO PRIMERA GEOSINTETICOS | H53: 45997 | I53: D | J53: M | K53: 14x14 B | L53: 1790000090 | M53: 3 | N53: 3 | O53: 3 | P53: 3 | Q53: 3 | R53: 3 | S53: 3 | T53: 2 | U53: 2 | V53: 2 | W53: 2 | X53: 2 | Y53: 2 | Z53: 2 | AA53: 2 | AB53: 2 | AC53: 2 | AD53: 2 | AE53: 2 | AF53: 2 | AG53: 2 | AH53: 3 | AI53: 3 | AJ53: 3 | AK53: 3 | AL53: 3 | AM53: 3 | AN53: 3 | AO53: 3 | AP53: 3 | AR53: 0 | AS53: 14 | AT53: 16 | AU53: 0 | AV53: 0 | AW53: 0 | AX53: 0 | AY53: 0 | AZ53: 0 | BA53: 30 | BC53: 235333 | BD53: DESCANSO PENDIENTE POR CIERRE LABORAL AL 30-04-2026 | BP53: 75000 | CI53: 473333 | CP53: 0 | CQ53: 0 | CR53: 0
A54: 53 | B54: 13976656-3 | C54: 13976656 | D54: ARAYA | E54: CORTES | F54: HUGO ALFONSO | G54: MAESTRO PRIMERA GEOSINTETICO | H54: 46099 | I54: D | J54: M | K54: 7X7 | L54: 1790000091 | M54: 3 | N54: 3 | O54: 3 | P54: 3 | Q54: 3 | R54: 3 | S54: 3 | T54: 2 | U54: 2 | V54: 2 | W54: 2 | X54: 2 | Y54: 2 | Z54: 2 | AA54: 3 | AB54: 3 | AC54: 3 | AD54: 3 | AE54: 3 | AF54: 3 | AG54: 3 | AH54: 2 | AI54: 2 | AJ54: 2 | AK54: 2 | AL54: 2 | AM54: 2 | AN54: 2 | AO54: 3 | AP54: 3 | AR54: 0 | AS54: 14 | AT54: 16 | AU54: 0 | AV54: 0 | AW54: 0 | AX54: 0 | AY54: 0 | AZ54: 0 | BA54: 30 | BY54: 50000 | CP54: 0 | CQ54: 0 | CR54: 0
A55: 54 | B55: 14016056-3 | C55: 14016056 | D55: VALDIVIA | E55: TORRES | F55: GONZALO EDUARDO | G55: GENERALISTA GESTION PERSONAS | H55: 46104 | I55: I | J55: M | K55: 5X2 | L55: 1720000001 | M55: 1 | N55: 1 | O55: 3 | P55: 3 | Q55: 3 | R55: 1 | S55: 3 | T55: 3 | U55: 1 | V55: 1 | W55: 1 | X55: 1 | Y55: 1 | Z55: 3 | AA55: 3 | AB55: 1 | AC55: 1 | AD55: 1 | AE55: 1 | AF55: 1 | AG55: 3 | AH55: 3 | AI55: 1 | AJ55: 1 | AK55: 1 | AL55: 1 | AM55: 1 | AN55: 1 | AO55: 1 | AP55: 1 | AR55: 21 | AS55: 0 | AT55: 9 | AU55: 0 | AV55: 0 | AW55: 0 | AX55: 0 | AY55: 0 | AZ55: 0 | BA55: 30 | CP55: 0 | CQ55: 0 | CR55: 0
A56: 55 | B56: 14113613-5 | C56: 14113613 | D56: BARRIOS | E56: ACUÑA | F56: NELSON ENRIQUE | G56: JEFE GESTION PERSONAS | I56: I | J56: M | K56: 5X2 | L56: 1740000001 | M56: 1 | N56: 1 | O56: 3 | P56: 3 | Q56: 3 | R56: 1 | S56: 1 | T56: 1 | U56: 1 | V56: 1 | W56: 3 | X56: 3 | Y56: 1 | Z56: 1 | AA56: 1 | AB56: 1 | AC56: 1 | AD56: 3 | AE56: 3 | AF56: 1 | AG56: 1 | AH56: 1 | AI56: 1 | AJ56: 1 | AK56: 3 | AL56: 3 | AM56: 1 | AN56: 1 | AO56: 1 | AP56: 1 | AR56: 21 | AS56: 0 | AT56: 9 | AU56: 0 | AV56: 0 | AW56: 0 | AX56: 0 | AY56: 0 | AZ56: 0 | BA56: 30 | CP56: 0 | CQ56: =VLOOKUP(C56,SEGURO!$A$2:$C$28,3,0) -> 46667 | CR56: 0
A57: 56 | B57: 14129064-9 | C57: 14129064 | D57: DIAZ | E57: BASOALTO | F57: ANDRES EDUARDO | G57: SUBGERENTE DE CONTABILIDAD Y FINANZAS | I57: I | J57: M | K57: 5X2 | L57: 1720000002 | M57: 1 | N57: 1 | O57: 3 | P57: 3 | Q57: 3 | R57: 1 | S57: 1 | T57: 1 | U57: 1 | V57: 1 | W57: 3 | X57: 3 | Y57: 1 | Z57: 1 | AA57: 1 | AB57: 1 | AC57: 1 | AD57: 3 | AE57: 3 | AF57: 1 | AG57: 1 | AH57: 1 | AI57: 1 | AJ57: 1 | AK57: 3 | AL57: 3 | AM57: 1 | AN57: 1 | AO57: 1 | AP57: 1 | AR57: 21 | AS57: 0 | AT57: 9 | AU57: 0 | AV57: 0 | AW57: 0 | AX57: 0 | AY57: 0 | AZ57: 0 | BA57: 30 | BP57: 240000 | CP57: 0 | CQ57: =VLOOKUP(C57,SEGURO!$A$2:$C$28,3,0) -> 46667 | CR57: =VLOOKUP(C57,FALP!$A$2:$C$13,3,0) -> 17600
A58: 57 | B58: 14296775-8 | C58: 14296775 | D58: CORTES | E58: HINAREJO | F58: ALEXIS RODRIGO | G58: JEFE DE TERRENO | H58: 46054 | I58: I | J58: M | K58: 7X7 | L58: 1790000091 | M58: 3 | N58: 3 | O58: 3 | P58: 3 | Q58: 3 | R58: 3 | S58: 3 | T58: 2 | U58: 2 | V58: 2 | W58: 2 | X58: 2 | Y58: 2 | Z58: 2 | AA58: 3 | AB58: 3 | AC58: 3 | AD58: 3 | AE58: 3 | AF58: 3 | AG58: 3 | AH58: 2 | AI58: 2 | AJ58: 2 | AK58: 2 | AL58: 2 | AM58: 2 | AN58: 2 | AO58: 3 | AP58: 3 | AR58: 0 | AS58: 14 | AT58: 16 | AU58: 0 | AV58: 0 | AW58: 0 | AX58: 0 | AY58: 0 | AZ58: 0 | BA58: 30 | BE58: 1644000 | BF58: Bono asignación de obra | CE58: 77281 | CM58: 248154 | CO58: =VLOOKUP(C58,'LOS HEROES'!$A$2:$D$30,4,0) -> 388170 | CP58: 0 | CQ58: 0 | CR58: 0
A59: 58 | B59: 14309302-6 | C59: 14309302 | D59: CASTRO | E59: GARAY | F59: IVAN DARIO | G59: EXPEDITOR | H59: 46031 | I59: I | J59: M | K59: 14x14 D | L59: 1790000090 | M59: 2 | N59: 2 | O59: 3 | P59: 3 | Q59: 3 | R59: 2 | S59: 2 | T59: 2 | U59: 2 | V59: 3 | W59: 3 | X59: 3 | Y59: 3 | Z59: 3 | AA59: 2 | AB59: 2 | AC59: 2 | AD59: 2 | AE59: 2 | AF59: 2 | AG59: 2 | AH59: 2 | AI59: 2 | AJ59: 2 | AK59: 2 | AL59: 2 | AM59: 2 | AN59: 2 | AO59: 3 | AP59: 3 | AR59: 0 | AS59: 20 | AT59: 10 | AU59: 0 | AV59: 0 | AW59: 0 | AX59: 0 | AY59: 0 | AZ59: 0 | BA59: 30 | BC59: 674400 | BD59: DESCANSO PENDIENTE POR CIERRE LABORAL AL 30-04-2026 | BK59: 168600 | BL59: 1 DIA ADICIONAL POR APOYO EN DESMOVILIZACION | BP59: 75000 | BY59: 15500 | CI59: 473333 | CP59: 0 | CQ59: =VLOOKUP(C59,SEGURO!$A$2:$C$28,3,0) -> 46667 | CR59: 0
A60: 59 | B60: 14456911-3 | C60: 14456911 | D60: ACEVEDO | E60: ZAMBRANO | F60: LUIS MARCELINO | G60: EXPEDITOR | H60: 45992 | I60: I | J60: M | K60: 4x3 | L60: 1790000090 | M60: 2 | N60: 2 | O60: 3 | P60: 3 | Q60: 3 | R60: 2 | S60: 2 | T60: 2 | U60: 2 | V60: 3 | W60: 3 | X60: 3 | Y60: 2 | Z60: 2 | AA60: 2 | AB60: 2 | AC60: 3 | AD60: 3 | AE60: 3 | AF60: 2 | AG60: 2 | AH60: 2 | AI60: 2 | AJ60: 3 | AK60: 3 | AL60: 3 | AR60: 0 | AS60: 14 | AT60: 12 | AU60: 0 | AV60: 0 | AW60: 0 | AX60: 0 | AY60: 0 | AZ60: 0 | BA60: 26 | BW60: 110000 | BX60: Acurdo departamento | CP60: 0 | CQ60: 0 | CR60: 0
A61: 60 | B61: 15012307-0 | C61: 15012307 | D61: YAÑEZ | E61: VELIZ | F61: JORGE ANDRES | G61: MAESTRO SEGUNDA GEOSINTETICOS | H61: 46041 | I61: D | J61: M | K61: 14X14 B | L61: 1790000090 | M61: 3 | N61: 3 | O61: 3 | P61: 3 | Q61: 3 | R61: 3 | S61: 3 | T61: 4 | U61: 4 | V61: 4 | W61: 4 | X61: 4 | Y61: 4 | Z61: 4 | AA61: 4 | AB61: 4 | AC61: 4 | AD61: 4 | AE61: 4 | AF61: 4 | AG61: 4 | AH61: 4 | AI61: 3 | AR61: 0 | AS61: 0 | AT61: 8 | AU61: 15 | AV61: 0 | AW61: 0 | AX61: 0 | AY61: 0 | AZ61: 0 | BA61: 8 | CI61: 473333 | CP61: 0 | CQ61: 0 | CR61: 0
A62: 61 | B62: 15018611-0 | C62: 15018611 | D62: GUERRA | E62: YAPOR | F62: JORGE ANDRES | G62: SUBGERENTE CONTRATOS Y SERVICIOS | H62: 45689 | I62: I | J62: M | K62: 4X3 | L62: 1790000088 | M62: 1 | N62: 1 | O62: 3 | P62: 3 | Q62: 3 | R62: 1 | S62: 1 | T62: 1 | U62: 1 | V62: 3 | W62: 3 | X62: 3 | Y62: 1 | Z62: 1 | AA62: 1 | AB62: 1 | AC62: 3 | AD62: 3 | AE62: 3 | AF62: 1 | AG62: 1 | AH62: 1 | AI62: 1 | AJ62: 3 | AK62: 3 | AL62: 3 | AM62: 1 | AN62: 1 | AO62: 1 | AP62: 1 | AR62: 18 | AS62: 0 | AT62: 12 | AU62: 0 | AV62: 0 | AW62: 0 | AX62: 0 | AY62: 0 | AZ62: 0 | BA62: 30 | BB62: 1508437 | BM62: 0 | CA62: 180000 | CB62: Gastos aseo depa | CP62: 0 | CQ62: =VLOOKUP(C62,SEGURO!$A$2:$C$28,3,0) -> 46667 | CR62: 0
A63: 62 | B63: 15033526-4 | C63: 15033526 | D63: VILLEGAS | E63: SANTIBAÑEZ | F63: HERMAN ALEXIS | G63: CAPATAZ GEOSINTETICOS | H63: 46056 | I63: D | J63: M | K63: 14X14 B | L63: 1790000090 | M63: 3 | N63: 3 | O63: 3 | P63: 3 | Q63: 3 | R63: 3 | S63: 3 | T63: 2 | U63: 2 | V63: 2 | W63: 2 | X63: 2 | Y63: 2 | Z63: 2 | AA63: 2 | AB63: 2 | AC63: 2 | AD63: 2 | AE63: 2 | AF63: 2 | AG63: 2 | AH63: 3 | AI63: 3 | AJ63: 3 | AK63: 3 | AL63: 3 | AM63: 3 | AN63: 3 | AO63: 3 | AP63: 3 | AR63: 0 | AS63: 14 | AT63: 16 | AU63: 0 | AV63: 0 | AW63: 0 | AX63: 0 | AY63: 0 | AZ63: 0 | BA63: 30 | BC63: 266667 | BD63: DESCANSO PENDIENTE POR CIERRE LABORAL AL 30-04-2026 | BK63: 160000 | BL63: 1 DIA ADICIONAL POR COUCHING EN ANTOFAGASTA | BP63: 75000 | CI63: 315556 | CP63: 0 | CQ63: 0 | CR63: 0
A64: 63 | B64: 15036703-4 | C64: 15036703 | D64: RIVERA | E64: ROJAS | F64: JORGE NIBALDO | G64: JEFE DE TERRENO | H64: 45704 | I64: I | J64: M | K64: A | L64: 1790000088 | M64: 2 | N64: 2 | O64: 8 | P64: 8 | Q64: 2 | R64: 2 | S64: 2 | T64: 3 | U64: 3 | V64: 3 | W64: 3 | X64: 3 | Y64: 3 | Z64: 3 | AA64: 3 | AB64: 3 | AC64: 3 | AD64: 3 | AE64: 3 | AF64: 3 | AG64: 3 | AH64: 2 | AI64: 2 | AJ64: 2 | AK64: 2 | AL64: 2 | AM64: 2 | AN64: 2 | AO64: 2 | AP64: 2 | AR64: 0 | AS64: 14 | AT64: 14 | AU64: 0 | AV64: 0 | AW64: 0 | AX64: 0 | AY64: 2 | AZ64: 0 | BA64: 30 | BM64: 2 | BN64: 717998 | BY64: 73050 | CP64: 0 | CQ64: 0 | CR64: 0
A65: 64 | B65: 15043166-2 | C65: 15043166 | D65: PEREIRA | E65: CORTES | F65: HUGO SALATIER | G65: AYUDANTE GEOSINTETICOS | H65: 45997 | I65: D | J65: M | K65: 14x14 B | L65: 1790000090 | M65: 3 | N65: 3 | O65: 3 | P65: 3 | Q65: 3 | R65: 3 | S65: 3 | T65: 2 | U65: 2 | V65: 2 | W65: 2 | X65: 2 | Y65: 2 | Z65: 2 | AA65: 2 | AB65: 2 | AC65: 2 | AD65: 2 | AE65: 2 | AF65: 2 | AG65: 2 | AH65: 3 | AI65: 3 | AJ65: 3 | AK65: 3 | AL65: 3 | AM65: 3 | AN65: 3 | AO65: 3 | AP65: 3 | AR65: 0 | AS65: 14 | AT65: 16 | AU65: 0 | AV65: 0 | AW65: 0 | AX65: 0 | AY65: 0 | AZ65: 0 | BA65: 30 | BC65: 130833 | BD65: DESCANSO PENDIENTE POR CIERRE LABORAL AL 30-04-2026 | BP65: 75000 | CI65: 473333 | CJ65: 213354 | CP65: 0 | CQ65: 0 | CR65: 0
A66: 65 | B66: 15043532-3 | C66: 15043532 | D66: MUÑOZ | E66: BUGUEÑO | F66: AGUSTIN EDGARD | G66: MAESTRO PRIMERA GEOSINTETICOS | H66: 46082 | I66: D | J66: M | K66: 14X14 A | L66: 1790000090 | M66: 2 | N66: 2 | O66: 8 | P66: 8 | Q66: 2 | R66: 2 | S66: 2 | T66: 3 | U66: 3 | V66: 3 | W66: 3 | X66: 3 | Y66: 3 | Z66: 3 | AA66: 3 | AB66: 3 | AC66: 3 | AD66: 3 | AE66: 3 | AF66: 3 | AG66: 3 | AH66: 2 | AI66: 2 | AJ66: 2 | AK66: 2 | AL66: 2 | AM66: 2 | AN66: 2 | AO66: 2 | AP66: 2 | AR66: 0 | AS66: 14 | AT66: 14 | AU66: 0 | AV66: 0 | AW66: 0 | AX66: 0 | AY66: 2 | AZ66: 0 | BA66: 30 | BM66: 2 | BN66: 282400 | BP66: 75000 | CI66: 315556 | CK66: 1270799 | CL66: 100000 | CP66: 0 | CQ66: 0 | CR66: 0
A67: 66 | B67: 15050650-6 | C67: 15050650 | D67: CODOCEO | E67: ORMEÑO | F67: JOEL ALEXANDER | G67: OPERADOR CAMION PLUMA | H67: 45985 | I67: D | J67: M | K67: 14x14 A | L67: 1790000090 | M67: 2 | N67: 2 | O67: 8 | P67: 8 | Q67: 2 | R67: 2 | S67: 2 | T67: 3 | U67: 3 | V67: 3 | W67: 3 | X67: 3 | Y67: 3 | Z67: 3 | AA67: 3 | AB67: 3 | AC67: 3 | AD67: 3 | AE67: 3 | AF67: 3 | AG67: 3 | AH67: 2 | AI67: 2 | AJ67: 2 | AK67: 2 | AL67: 2 | AM67: 2 | AN67: 2 | AO67: 2 | AP67: 2 | AR67: 0 | AS67: 14 | AT67: 14 | AU67: 0 | AV67: 0 | AW67: 0 | AX67: 0 | AY67: 2 | AZ67: 0 | BA67: 30 | BM67: 2 | BN67: 337200 | BP67: 75000 | CI67: 473333 | CK67: 1517399 | CL67: 100000 | CO67: =VLOOKUP(C67,'LOS HEROES'!$A$2:$D$30,4,0) -> 184089 | CP67: 0 | CQ67: 0 | CR67: 0
A68: 67 | B68: 15164558-5 | C68: 15164558 | D68: SEPULVEDA | E68: VARGAS | F68: ESTEBAN ANDRES | G68: TECNICO RRHH PROYECTO | H68: 46054 | I68: I | J68: M | K68: 7X7 | L68: 1790000091 | M68: 3 | N68: 3 | O68: 8 | P68: 3 | Q68: 3 | R68: 3 | S68: 3 | T68: 2 | U68: 2 | V68: 2 | W68: 2 | X68: 2 | Y68: 2 | Z68: 2 | AA68: 3 | AB68: 3 | AC68: 3 | AD68: 3 | AE68: 3 | AF68: 3 | AG68: 3 | AH68: 2 | AI68: 2 | AJ68: 2 | AK68: 2 | AL68: 2 | AM68: 2 | AN68: 2 | AO68: 3 | AP68: 3 | AR68: 0 | AS68: 14 | AT68: 15 | AU68: 0 | AV68: 0 | AW68: 0 | AX68: 0 | AY68: 1 | AZ68: 0 | BA68: 30 | BM68: 1 | BN68: 243000 | BY68: 82000 | CO68: =VLOOKUP(C68,'LOS HEROES'!$A$2:$D$30,4,0) -> 250278 | CP68: 0 | CQ68: =VLOOKUP(C68,SEGURO!$A$2:$C$28,3,0) -> 46667 | CR68: 0
A69: 68 | B69: 15356694-1 | C69: 15356694 | D69: AYALA | E69: VENEGAS | F69: RAÚL EDUARDO | G69: RIGGER | H69: 45823 | I69: D | J69: M | K69: B | L69: 1790000088 | M69: 3 | N69: 3 | O69: 3 | P69: 3 | Q69: 3 | R69: 3 | S69: 3 | T69: 1 | U69: 1 | V69: 1 | W69: 1 | X69: 1 | Y69: 1 | Z69: 1 | AA69: 1 | AB69: 1 | AC69: 1 | AD69: 1 | AE69: 1 | AF69: 1 | AG69: 1 | AH69: 3 | AI69: 3 | AJ69: 3 | AK69: 3 | AL69: 3 | AM69: 3 | AN69: 3 | AO69: 3 | AP69: 3 | AR69: 14 | AS69: 0 | AT69: 16 | AU69: 0 | AV69: 0 | AW69: 0 | AX69: 0 | AY69: 0 | AZ69: 0 | BA69: 30 | BM69: 0 | CP69: 0 | CQ69: 0 | CR69: 0
A70: 69 | B70: 15441205-0 | C70: 15441205 | D70: ROBLES | E70: CUEVAS | F70: RONALD ROLF | G70: TECNICO CONTROL CALIDAD | H70: 46078 | I70: D | J70: M | K70: 7X7 | L70: 1790000091 | M70: 3 | N70: 3 | O70: 3 | P70: 3 | Q70: 3 | R70: 3 | S70: 3 | T70: 2 | U70: 2 | V70: 2 | W70: 2 | X70: 2 | Y70: 2 | Z70: 2 | AA70: 3 | AB70: 3 | AC70: 3 | AD70: 3 | AE70: 3 | AF70: 3 | AG70: 3 | AH70: 2 | AI70: 2 | AJ70: 2 | AK70: 2 | AL70: 2 | AM70: 2 | AN70: 2 | AO70: 3 | AP70: 3 | AR70: 0 | AS70: 14 | AT70: 16 | AU70: 0 | AV70: 0 | AW70: 0 | AX70: 0 | AY70: 0 | AZ70: 0 | BA70: 30 | CP70: 0 | CQ70: 0 | CR70: 0
A71: 70 | B71: 15494188-6 | C71: 15494188 | D71: ARAYA | E71: GALLEGUILLOS | F71: CARLOS ALBERTO | G71: JEFE OFICINA TECNICA | H71: 46064 | I71: I | J71: M | K71: 4X3 | L71: 1790000090 | M71: 2 | N71: 2 | O71: 3 | P71: 3 | Q71: 3 | R71: 2 | S71: 2 | T71: 2 | U71: 2 | V71: 3 | W71: 3 | X71: 3 | Y71: 2 | Z71: 2 | AA71: 2 | AB71: 2 | AC71: 3 | AD71: 3 | AE71: 3 | AF71: 2 | AG71: 2 | AH71: 2 | AI71: 2 | AJ71: 3 | AK71: 3 | AL71: 3 | AM71: 2 | AN71: 2 | AO71: 2 | AP71: 2 | AR71: 0 | AS71: 18 | AT71: 12 | AU71: 0 | AV71: 0 | AW71: 0 | AX71: 0 | AY71: 0 | AZ71: 0 | BA71: 30 | BY71: 265000 | CI71: 315556 | CP71: 0 | CQ71: 0 | CR71: 0
A72: 71 | B72: 15494232-7 | C72: 15494242 | D72: AGUILERA | E72: ROJAS | F72: OSCAR ALEXI | G72: MAESTRO PRIMERA GEOSINTETICOS | H72: 45997 | I72: D | J72: M | K72: 14x14 B | L72: 1790000090 | M72: 3 | N72: 3 | O72: 3 | P72: 3 | Q72: 3 | R72: 3 | S72: 3 | T72: 2 | U72: 2 | V72: 2 | W72: 2 | X72: 2 | Y72: 2 | Z72: 2 | AA72: 2 | AB72: 2 | AC72: 2 | AD72: 2 | AE72: 2 | AF72: 2 | AG72: 2 | AH72: 3 | AI72: 3 | AJ72: 3 | AK72: 3 | AL72: 3 | AM72: 3 | AN72: 3 | AO72: 3 | AP72: 3 | AR72: 0 | AS72: 14 | AT72: 16 | AU72: 0 | AV72: 0 | AW72: 0 | AX72: 0 | AY72: 0 | AZ72: 0 | BA72: 30 | BC72: 235333 | BD72: DESCANSO PENDIENTE POR CIERRE LABORAL AL 30-04-2026 | BP72: 75000 | CI72: 473333 | CP72: 0 | CQ72: 0 | CR72: 0
A73: 72 | B73: 15575503-2 | C73: 15575503 | D73: JULIO | E73: TAPIA | F73: MANUEL ALEJANDRO | G73: MAESTRO SEGUNDA GEOSINTETICOS | H73: 46104 | I73: D | J73: M | K73: 14x14 A | L73: 1790000090 | M73: 1 | N73: 1 | O73: 1 | P73: 1 | Q73: 1 | R73: 1 | S73: 1 | T73: 3 | U73: 3 | V73: 3 | W73: 3 | X73: 3 | Y73: 3 | Z73: 3 | AA73: 3 | AB73: 3 | AR73: 7 | AS73: 0 | AT73: 9 | AU73: 0 | AV73: 0 | AW73: 0 | AX73: 0 | AY73: 0 | AZ73: 0 | BA73: 16 | CI73: 0 | CP73: 0 | CQ73: 0 | CR73: 0
A74: 73 | B74: 15661268-5 | C74: 15661268 | D74: REBOLLEDO | E74: ROSALES | F74: LUIS ANDRES | G74: INGENIERO DE PROYECTOS | I74: I | J74: M | K74: 5X2 | L74: 1750000001 | M74: 1 | N74: 1 | O74: 3 | P74: 3 | Q74: 3 | R74: 1 | S74: 1 | T74: 1 | U74: 1 | V74: 1 | W74: 1 | X74: 1 | Y74: 1 | Z74: 1 | AA74: 1 | AB74: 1 | AC74: 1 | AD74: 3 | AE74: 3 | AF74: 1 | AG74: 1 | AH74: 1 | AI74: 1 | AJ74: 1 | AK74: 3 | AL74: 3 | AM74: 1 | AN74: 1 | AO74: 1 | AP74: 1 | AR74: 23 | AS74: 0 | AT74: 7 | AU74: 0 | AV74: 0 | AW74: 0 | AX74: 0 | AY74: 0 | AZ74: 0 | BA74: 30 | CP74: 0 | CQ74: =VLOOKUP(C74,SEGURO!$A$2:$C$28,3,0) -> 46667 | CR74: =VLOOKUP(C74,FALP!$A$2:$C$13,3,0) -> 17600
A75: 74 | B75: 15684747-k | C75: 15684747 | D75: GONZALEZ | E75: TAPIA | F75: SARA NOEMI | G75: JEFE DE CALIDAD | H75: 45748 | I75: I | J75: F | K75: 4X3 | L75: 1790000088 | M75: 1 | N75: 1 | O75: 3 | P75: 3 | Q75: 3 | R75: 1 | S75: 1 | T75: 1 | U75: 1 | V75: 3 | W75: 3 | X75: 3 | Y75: 1 | Z75: 1 | AA75: 1 | AB75: 1 | AC75: 8 | AD75: 3 | AE75: 3 | AF75: 1 | AG75: 1 | AH75: 1 | AI75: 1 | AJ75: 3 | AK75: 3 | AL75: 3 | AM75: 1 | AN75: 1 | AO75: 1 | AP75: 1 | AR75: 18 | AS75: 0 | AT75: 11 | AU75: 0 | AV75: 0 | AW75: 0 | AX75: 0 | AY75: 1 | AZ75: 0 | BA75: 30 | BE75: 1634000 | BF75: Bono para llegar a monto asignado | BM75: 1 | BN75: 171299 | BY75: 64263 | CE75: 77281 | CP75: 0 | CQ75: =VLOOKUP(C75,SEGURO!$A$2:$C$28,3,0) -> 46667 | CR75: 0
A76: 75 | B76: 15757199-0 | C76: 15757199 | D76: CARRASCO | E76: HERMOSILLA | F76: WILLIAMS ALEX | G76: AYUDANTE GEOSINTETICOS | H76: 46023 | I76: D | J76: M | K76: 14x14 A | L76: 1790000090 | M76: 2 | N76: 2 | O76: 8 | P76: 8 | Q76: 2 | R76: 2 | S76: 2 | T76: 3 | U76: 3 | V76: 3 | W76: 3 | X76: 3 | Y76: 3 | Z76: 3 | AA76: 3 | AB76: 3 | AC76: 3 | AD76: 3 | AE76: 3 | AF76: 3 | AG76: 3 | AR76: 0 | AS76: 5 | AT76: 14 | AU76: 0 | AV76: 0 | AW76: 0 | AX76: 0 | AY76: 2 | AZ76: 0 | BA76: 21 | BM76: 2 | BN76: 157000 | BP76: 52500 | CI76: 315555 | CP76: 0 | CQ76: 0 | CR76: 0
A77: 76 | B77: 15802017-3 | C77: 15802017 | D77: ARGANDOÑA | E77: IBACACHE | F77: PABLO CÉSAR | G77: MAESTRO PRIMERA GEOSINTETICOS | H77: 45974 | I77: D | J77: M | K77: 14x14 A | L77: 1790000090 | M77: 2 | N77: 2 | O77: 8 | P77: 8 | Q77: 2 | R77: 2 | S77: 2 | T77: 3 | U77: 3 | V77: 3 | W77: 3 | X77: 3 | Y77: 3 | Z77: 3 | AA77: 3 | AB77: 3 | AC77: 3 | AD77: 3 | AE77: 3 | AF77: 3 | AG77: 3 | AH77: 2 | AI77: 2 | AJ77: 2 | AK77: 2 | AL77: 2 | AM77: 2 | AN77: 2 | AO77: 2 | AP77: 2 | AR77: 0 | AS77: 14 | AT77: 14 | AU77: 0 | AV77: 0 | AW77: 0 | AX77: 0 | AY77: 2 | AZ77: 0 | BA77: 30 | BM77: 2 | BN77: 282400 | BP77: 75000 | CI77: 473333 | CO77: =VLOOKUP(C77,'LOS HEROES'!$A$2:$D$30,4,0) -> 154145 | CP77: 0 | CQ77: 0 | CR77: 0
A78: 77 | B78: 15802541-8 | C78: 15802541 | D78: GALLARDO | E78: ROJAS | F78: JAIME RODRIGO | G78: MAESTRO SEGUNDA GEOSINTETICOS | H78: 46006 | I78: D | J78: M | K78: 14X14 B | L78: 1790000090 | M78: 3 | N78: 3 | O78: 3 | P78: 3 | Q78: 3 | R78: 3 | S78: 3 | T78: 2 | U78: 2 | V78: 2 | W78: 2 | X78: 2 | Y78: 2 | Z78: 2 | AA78: 2 | AB78: 2 | AC78: 2 | AD78: 2 | AE78: 2 | AF78: 2 | AG78: 2 | AH78: 3 | AI78: 3 | AJ78: 3 | AK78: 3 | AL78: 3 | AM78: 3 | AN78: 3 | AO78: 3 | AP78: 3 | AR78: 0 | AS78: 14 | AT78: 16 | AU78: 0 | AV78: 0 | AW78: 0 | AX78: 0 | AY78: 0 | AZ78: 0 | BA78: 30 | BC78: 150000 | BD78: DESCANSO PENDIENTE POR CIERRE LABORAL AL 30-04-2026 | BP78: 75000 | CI78: 473333 | CP78: 0 | CQ78: 0 | CR78: 0
A79: 78 | B79: 15834377-0 | C79: 15834377 | D79: LEON | E79: PLAZA | F79: WILLIAMS NELSON | G79: MAESTRO SEGUNDA GEOSINTETICOS | H79: 46054 | I79: D | J79: M | K79: 14X14 A | L79: 1790000090 | M79: 2 | N79: 2 | O79: 8 | P79: 8 | Q79: 2 | R79: 2 | S79: 2 | T79: 3 | U79: 3 | V79: 3 | W79: 3 | X79: 3 | Y79: 3 | Z79: 3 | AA79: 3 | AB79: 3 | AC79: 3 | AD79: 3 | AE79: 3 | AF79: 3 | AG79: 3 | AR79: 0 | AS79: 5 | AT79: 14 | AU79: 0 | AV79: 0 | AW79: 0 | AX79: 0 | AY79: 2 | AZ79: 0 | BA79: 21 | BM79: 2 | BN79: 180000 | BP79: 52500 | CI79: 315555 | CP79: 0 | CQ79: 0 | CR79: 0
A80: 79 | B80: 15876024-k | C80: 15876024 | D80: STUARDO | E80: SEPULVEDA | F80: MANUEL ANTONIO | G80: MAESTRO SEGUNDA CONTROL CALIDAD | H80: 46069 | I80: D | J80: M | K80: 14X14 B | L80: 1790000090 | M80: 3 | N80: 3 | O80: 3 | P80: 3 | Q80: 3 | R80: 3 | S80: 3 | T80: 2 | U80: 2 | V80: 2 | W80: 2 | X80: 2 | Y80: 2 | Z80: 2 | AA80: 2 | AB80: 2 | AC80: 2 | AD80: 2 | AE80: 2 | AF80: 2 | AG80: 2 | AH80: 3 | AI80: 3 | AJ80: 3 | AK80: 3 | AL80: 3 | AM80: 3 | AN80: 3 | AO80: 3 | AP80: 3 | AR80: 0 | AS80: 14 | AT80: 16 | AU80: 0 | AV80: 0 | AW80: 0 | AX80: 0 | AY80: 0 | AZ80: 0 | BA80: 30 | BC80: 150000 | BD80: DESCANSO PENDIENTE POR CIERRE LABORAL AL 30-04-2026 | BP80: 75000 | CI80: 315556 | CP80: =VLOOKUP(C80,'LA ARAUCANA'!$A$2:$D$5,4,0) -> 101408 | CQ80: 0 | CR80: 0
A81: 80 | B81: 15936945-5 | C81: 15936945 | D81: SEPULVEDA | E81: VERGARA | F81: KARLA ANDREA | G81: SUBGERENTE DE ESTUDIO DE PROYECTOS | I81: I | J81: F | K81: 5X2 | L81: 1750000001 | M81: 1 | N81: 1 | O81: 3 | P81: 3 | Q81: 3 | R81: 1 | S81: 1 | T81: 1 | U81: 1 | V81: 1 | W81: 3 | X81: 3 | Y81: 1 | Z81: 1 | AA81: 1 | AB81: 1 | AC81: 1 | AD81: 3 | AE81: 3 | AF81: 1 | AG81: 1 | AH81: 1 | AI81: 1 | AJ81: 1 | AK81: 3 | AL81: 3 | AM81: 1 | AN81: 1 | AO81: 1 | AP81: 1 | AR81: 21 | AS81: 0 | AT81: 9 | AU81: 0 | AV81: 0 | AW81: 0 | AX81: 0 | AY81: 0 | AZ81: 0 | BA81: 30 | CP81: 0 | CQ81: =VLOOKUP(C81,SEGURO!$A$2:$C$28,3,0) -> 32725 | CR81: =VLOOKUP(C81,FALP!$A$2:$C$13,3,0) -> 8800
A82: 81 | B82: 15969632-4 | C82: 15969632 | D82: ARROUCH | E82: MOLINA | F82: EDUARDO ANDRES | G82: OPERADOR CAMIÓN PLUMA | H82: 45824 | I82: D | J82: M | K82: B | L82: 1790000088 | M82: 3 | N82: 3 | O82: 3 | P82: 3 | Q82: 3 | R82: 3 | S82: 3 | T82: 1 | U82: 1 | V82: 1 | W82: 1 | X82: 1 | Y82: 1 | Z82: 1 | AA82: 1 | AB82: 1 | AC82: 1 | AD82: 1 | AE82: 1 | AF82: 1 | AG82: 1 | AH82: 3 | AI82: 3 | AJ82: 3 | AK82: 3 | AL82: 3 | AM82: 3 | AN82: 3 | AO82: 3 | AP82: 3 | AR82: 14 | AS82: 0 | AT82: 16 | AU82: 0 | AV82: 0 | AW82: 0 | AX82: 0 | AY82: 0 | AZ82: 0 | BA82: 30 | BM82: 0 | CP82: 0 | CQ82: 0 | CR82: 0
A83: 82 | B83: 15975698-k | C83: 15975698 | D83: ACEVEDO | E83: ARANCIBIA | F83: JORGE ALEJANDRO | G83: BODEGUERO | H83: 46003 | I83: I | J83: M | K83: 14X14 B | L83: 1790000090 | M83: 3 | N83: 3 | O83: 3 | P83: 3 | Q83: 3 | R83: 3 | S83: 3 | T83: 2 | U83: 2 | V83: 2 | W83: 2 | X83: 2 | Y83: 2 | Z83: 2 | AA83: 2 | AB83: 2 | AC83: 2 | AD83: 2 | AE83: 2 | AF83: 2 | AG83: 2 | AH83: 3 | AI83: 3 | AJ83: 3 | AK83: 3 | AL83: 3 | AM83: 3 | AN83: 3 | AO83: 3 | AP83: 3 | AR83: 0 | AS83: 14 | AT83: 16 | AU83: 0 | AV83: 0 | AW83: 0 | AX83: 0 | AY83: 0 | AZ83: 0 | BA83: 30 | BC83: 182167 | BD83: DESCANSO PENDIENTE POR CIERRE LABORAL AL 30-04-2026 | BP83: 75000 | CI83: 473333 | CP83: 0 | CQ83: 0 | CR83: 0
A84: 83 | B84: 15980010-5 | C84: 15980010 | D84: CORTES | E84: SOTO | F84: MARIO HERNAN | G84: SUPERVISOR CONTROL CALIDAD | H84: 45704 | I84: I | J84: M | K84: A | L84: 1790000088 | M84: 2 | N84: 2 | O84: 8 | P84: 8 | Q84: 2 | R84: 2 | S84: 2 | T84: 3 | U84: 3 | V84: 3 | W84: 3 | X84: 3 | Y84: 3 | Z84: 3 | AA84: 3 | AB84: 3 | AC84: 3 | AD84: 3 | AE84: 3 | AF84: 3 | AG84: 3 | AH84: 2 | AI84: 2 | AJ84: 2 | AK84: 2 | AL84: 2 | AM84: 2 | AN84: 2 | AO84: 2 | AP84: 2 | AR84: 0 | AS84: 14 | AT84: 14 | AU84: 0 | AV84: 0 | AW84: 0 | AX84: 0 | AY84: 2 | AZ84: 0 | BA84: 30 | BM84: 2 | BN84: 461598 | CP84: 0 | CQ84: 0 | CR84: 0
A85: 84 | B85: 15982591-4 | C85: 15982591 | D85: SIARES | E85: GUZMÁN | F85: RICHARD ALEXANDER | G85: ADMINISTRADOR DE CONTRATOS | H85: 45962 | I85: I | J85: M | K85: 4X3 | L85: 1790000090 | M85: 2 | N85: 2 | O85: 3 | P85: 3 | Q85: 3 | R85: 2 | S85: 2 | T85: 2 | U85: 2 | V85: 3 | W85: 3 | X85: 3 | Y85: 2 | Z85: 2 | AA85: 2 | AB85: 2 | AC85: 3 | AD85: 3 | AE85: 3 | AF85: 2 | AG85: 2 | AH85: 2 | AI85: 2 | AJ85: 3 | AK85: 3 | AL85: 3 | AM85: 2 | AN85: 2 | AO85: 2 | AP85: 2 | AR85: 0 | AS85: 18 | AT85: 12 | AU85: 0 | AV85: 0 | AW85: 0 | AX85: 0 | AY85: 0 | AZ85: 0 | BA85: 30 | BE85: 940000 | BF85: Bono acuerdo salarial | CI85: 473333 | CP85: 0 | CQ85: =VLOOKUP(C85,SEGURO!$A$2:$C$28,3,0) -> 18779 | CR85: 0
A86: 85 | B86: 16054274-8 | C86: 16054274 | D86: MAYORGA | E86: ARCOS | F86: CARLOS MANUEL | G86: TECNICO CONTROL CALIDAD | H86: 45889 | I86: D | J86: M | K86: B | L86: 1790000088 | M86: 3 | N86: 3 | O86: 3 | P86: 3 | Q86: 3 | R86: 3 | S86: 3 | T86: 2 | U86: 2 | V86: 2 | W86: 2 | X86: 2 | Y86: 2 | Z86: 2 | AA86: 2 | AB86: 2 | AC86: 2 | AD86: 2 | AE86: 2 | AF86: 2 | AG86: 2 | AH86: 3 | AI86: 3 | AJ86: 3 | AK86: 3 | AL86: 3 | AM86: 3 | AN86: 3 | AO86: 3 | AP86: 3 | AR86: 0 | AS86: 14 | AT86: 16 | AU86: 0 | AV86: 0 | AW86: 0 | AX86: 0 | AY86: 0 | AZ86: 0 | BA86: 30 | BM86: 0 | CP86: 0 | CQ86: 0 | CR86: 0
A87: 86 | B87: 16055086-4 | C87: 16055086 | D87: CÁCERES | E87: OGALDE | F87: SEBASTIAN LORENZO | G87: TECNICO INSPECTOR Y DETECTOR DE FUGAS | H87: 45820 | I87: D | J87: M | K87: A | L87: 1790000088 | M87: 2 | N87: 2 | O87: 8 | P87: 8 | Q87: 2 | R87: 2 | S87: 1 | T87: 3 | U87: 3 | V87: 3 | W87: 3 | X87: 3 | Y87: 3 | Z87: 3 | AA87: 3 | AB87: 3 | AC87: 3 | AD87: 3 | AE87: 3 | AF87: 3 | AG87: 3 | AH87: 2 | AI87: 2 | AJ87: 2 | AK87: 2 | AL87: 2 | AM87: 2 | AN87: 2 | AO87: 2 | AP87: 2 | AR87: 1 | AS87: 13 | AT87: 14 | AU87: 0 | AV87: 0 | AW87: 0 | AX87: 0 | AY87: 2 | AZ87: 0 | BA87: 30 | BM87: 2 | BN87: 170000 | CP87: 0 | CQ87: 0 | CR87: 0
A88: 87 | B88: 16109258-4 | C88: 16109258 | D88: VALDERRAMA | E88: TABILO | F88: JOSE ORLANDO | G88: AYUDANTE GEOSINTETICOS | H88: 46096 | I88: D | J88: M | K88: 7X7 | L88: 1790000091 | M88: 3 | N88: 3 | O88: 3 | P88: 3 | Q88: 3 | R88: 3 | S88: 3 | T88: 2 | U88: 2 | V88: 2 | W88: 2 | X88: 2 | Y88: 2 | Z88: 2 | AA88: 3 | AB88: 3 | AC88: 3 | AD88: 3 | AE88: 3 | AF88: 3 | AG88: 3 | AH88: 2 | AI88: 2 | AJ88: 2 | AK88: 2 | AL88: 2 | AM88: 2 | AN88: 2 | AO88: 3 | AP88: 3 | AR88: 0 | AS88: 14 | AT88: 16 | AU88: 0 | AV88: 0 | AW88: 0 | AX88: 0 | AY88: 0 | AZ88: 0 | BA88: 30 | BY88: 25000 | CO88: =VLOOKUP(C88,'LOS HEROES'!$A$2:$D$30,4,0) -> 5522 | CP88: 0 | CQ88: 0 | CR88: 0
A89: 88 | B89: 16110209-1 | C89: 16110209 | D89: GUAJARDO | E89: SALAS | F89: CRISTIAN LENIER | G89: OPERADOR CAMION PLUMA | H89: 46063 | I89: D | J89: M | K89: 7X7 | L89: 1790000091 | M89: 3 | N89: 3 | O89: 3 | P89: 3 | Q89: 3 | R89: 3 | S89: 3 | T89: 2 | U89: 2 | V89: 2 | W89: 2 | X89: 2 | Y89: 2 | Z89: 2 | AA89: 3 | AB89: 3 | AC89: 3 | AD89: 3 | AE89: 3 | AF89: 3 | AG89: 3 | AH89: 2 | AI89: 2 | AJ89: 2 | AK89: 2 | AL89: 2 | AM89: 2 | AN89: 2 | AO89: 3 | AP89: 3 | AR89: 0 | AS89: 14 | AT89: 16 | AU89: 0 | AV89: 0 | AW89: 0 | AX89: 0 | AY89: 0 | AZ89: 0 | BA89: 30 | CP89: 0 | CQ89: 0 | CR89: 0
A90: 89 | B90: 16352344-2 | C90: 16352344 | D90: MUÑOZ | E90: ABARCA | F90: JIMMY ALEJANDRO | G90: MAESTRO SEGUNDA GEOSINTETICOS | H90: 45839 | I90: D | J90: M | K90: A | L90: 1790000088 | M90: 2 | N90: 2 | O90: 8 | P90: 8 | Q90: 2 | R90: 2 | S90: 2 | T90: 3 | U90: 3 | V90: 3 | W90: 3 | X90: 3 | Y90: 3 | Z90: 3 | AA90: 3 | AB90: 3 | AC90: 3 | AD90: 3 | AE90: 3 | AF90: 3 | AG90: 3 | AH90: 2 | AI90: 2 | AJ90: 2 | AK90: 2 | AL90: 2 | AM90: 2 | AN90: 2 | AO90: 2 | AP90: 2 | AR90: 0 | AS90: 14 | AT90: 14 | AU90: 0 | AV90: 0 | AW90: 0 | AX90: 0 | AY90: 2 | AZ90: 0 | BA90: 30 | BM90: 2 | BN90: 170000 | BY90: 36050 | CP90: 0 | CQ90: 0 | CR90: 0
A91: 90 | B91: 16401293-k | C91: 16401293 | D91: ABARCA | E91: TUDESCA | F91: LEANDRO ISAAC | G91: MAESTRO PRIMERA GEOSINTETICOS | H91: 45846 | I91: D | J91: M | K91: B | L91: 1790000088 | M91: 3 | N91: 3 | O91: 3 | P91: 3 | Q91: 3 | R91: 3 | S91: 3 | T91: 2 | U91: 2 | V91: 2 | W91: 2 | X91: 2 | Y91: 2 | Z91: 2 | AA91: 2 | AB91: 2 | AC91: 2 | AD91: 2 | AE91: 2 | AF91: 2 | AG91: 2 | AH91: 3 | AI91: 3 | AJ91: 3 | AK91: 3 | AL91: 3 | AM91: 3 | AN91: 3 | AO91: 3 | AP91: 3 | AR91: 0 | AS91: 14 | AT91: 16 | AU91: 0 | AV91: 0 | AW91: 0 | AX91: 0 | AY91: 0 | AZ91: 0 | BA91: 30 | BM91: 0 | CP91: 0 | CQ91: 0 | CR91: 0
A92: 91 | B92: 16407359-9 | C92: 16407359 | D92: GARRIDO | E92: ARRATIA | F92: JONATHAN VICTOR | G92: AYUDANTE GEOSINTETICOS | H92: 45846 | I92: D | J92: M | K92: B | L92: 1790000088 | M92: 1 | N92: 1 | O92: 1 | P92: 1 | Q92: 1 | R92: 1 | S92: 1 | T92: 1 | U92: 1 | V92: 1 | W92: 1 | AR92: 11 | AS92: 0 | AT92: 0 | AU92: 0 | AV92: 0 | AW92: 0 | AX92: 0 | AY92: 0 | AZ92: 0 | BA92: 11 | BM92: 0 | BY92: 7480 | CP92: 0 | CQ92: 0 | CR92: 0
A93: 92 | B93: 16443686-1 | C93: 16443686 | D93: ESQUIVEL | E93: OPAZO | F93: JUAN HERMAN ULIESES OPAZO | G93: ASESOR PREVENCION DE RIESGOS | H93: 46054 | I93: I | J93: M | K93: 7X7 | L93: 1790000091 | M93: 3 | N93: 3 | O93: 3 | P93: 3 | Q93: 3 | R93: 3 | S93: 3 | T93: 2 | U93: 2 | V93: 2 | W93: 2 | X93: 2 | Y93: 2 | Z93: 2 | AA93: 3 | AB93: 3 | AC93: 3 | AD93: 3 | AE93: 3 | AF93: 3 | AG93: 3 | AH93: 2 | AI93: 2 | AJ93: 2 | AK93: 2 | AL93: 2 | AM93: 2 | AN93: 2 | AO93: 3 | AP93: 3 | AR93: 0 | AS93: 14 | AT93: 16 | AU93: 0 | AV93: 0 | AW93: 0 | AX93: 0 | AY93: 0 | AZ93: 0 | BA93: 30 | CP93: 0 | CQ93: 0 | CR93: 0
A94: 93 | B94: 16481993-0 | C94: 16481993 | D94: GOLOTT | E94: VALDES | F94: MARIA JOSE IGNACIA | G94: CONDUCTOR CAMION RAMPA | I94: D | J94: F | K94: 5X2 | L94: 1740000002 | M94: 1 | N94: 1 | O94: 3 | P94: 3 | Q94: 3 | R94: 1 | S94: 1 | T94: 1 | U94: 1 | V94: 1 | W94: 3 | X94: 3 | Y94: 1 | Z94: 1 | AA94: 1 | AB94: 1 | AC94: 1 | AD94: 3 | AE94: 3 | AF94: 1 | AG94: 1 | AH94: 1 | AI94: 1 | AJ94: 1 | AK94: 3 | AL94: 3 | AM94: 1 | AN94: 1 | AO94: 1 | AP94: 1 | AR94: 21 | AS94: 0 | AT94: 9 | AU94: 0 | AV94: 0 | AW94: 0 | AX94: 0 | AY94: 0 | AZ94: 0 | BA94: 30 | CC94: 1200000 | CP94: 0 | CQ94: 0 | CR94: 0
A95: 94 | B95: 16518571-4 | C95: 16518571 | D95: ORTEGA | E95: VALDERRAMA | F95: MARCELO ALEJANDRO | G95: RIGGER | H95: 46054 | I95: D | J95: M | K95: 14X14 B | L95: 1790000090 | M95: 3 | N95: 3 | O95: 3 | P95: 3 | Q95: 3 | R95: 3 | S95: 3 | T95: 2 | U95: 2 | V95: 2 | W95: 2 | X95: 2 | Y95: 2 | Z95: 2 | AA95: 2 | AB95: 2 | AC95: 2 | AD95: 2 | AE95: 2 | AF95: 2 | AG95: 2 | AH95: 3 | AI95: 3 | AJ95: 3 | AK95: 3 | AL95: 3 | AM95: 3 | AN95: 3 | AO95: 3 | AP95: 3 | AR95: 0 | AS95: 14 | AT95: 16 | AU95: 0 | AV95: 0 | AW95: 0 | AX95: 0 | AY95: 0 | AZ95: 0 | BA95: 30 | BC95: 235333 | BD95: DESCANSO PENDIENTE POR CIERRE LABORAL AL 30-04-2026 | BP95: 75000 | CI95: 473333 | CP95: 0 | CQ95: 0 | CR95: 0
A96: 95 | B96: 16538795-3 | C96: 16538795 | D96: VASQUEZ | E96: BRAVO | F96: LUIS ALEXIS FERNANDO | G96: CAPATAZ GEOSINTETICOS | H96: 45992 | I96: D | J96: M | K96: 14x14 A | L96: 1790000090 | M96: 2 | N96: 2 | O96: 8 | P96: 8 | Q96: 2 | R96: 2 | S96: 2 | T96: 3 | U96: 3 | V96: 3 | W96: 3 | X96: 3 | Y96: 3 | Z96: 3 | AA96: 3 | AB96: 3 | AC96: 3 | AD96: 3 | AE96: 3 | AF96: 3 | AG96: 3 | AH96: 2 | AI96: 2 | AJ96: 2 | AK96: 2 | AL96: 2 | AM96: 2 | AN96: 2 | AO96: 2 | AP96: 2 | AR96: 0 | AS96: 14 | AT96: 14 | AU96: 0 | AV96: 0 | AW96: 0 | AX96: 0 | AY96: 2 | AZ96: 0 | BA96: 30 | BM96: 2 | BN96: 320000 | BP96: 75000 | BY96: 56000 | CI96: 473333 | CP96: 0 | CQ96: 0 | CR96: 0
A97: 96 | B97: 16687732-6 | C97: 16687732 | D97: PEREZ | E97: CALLEJAS | F97: HERMAN ENRIQUE | G97: MAESTRO SEGUNDA GEOSINTETICOS | H97: 46041 | I97: D | J97: M | K97: 14X14 B | L97: 1790000090 | M97: 3 | N97: 3 | O97: 3 | P97: 3 | Q97: 3 | R97: 3 | S97: 3 | T97: 2 | U97: 2 | V97: 2 | W97: 2 | X97: 2 | Y97: 2 | Z97: 2 | AA97: 2 | AB97: 2 | AC97: 2 | AD97: 2 | AE97: 2 | AF97: 2 | AG97: 2 | AH97: 3 | AI97: 3 | AJ97: 3 | AK97: 3 | AL97: 3 | AM97: 3 | AN97: 3 | AO97: 3 | AP97: 3 | AR97: 0 | AS97: 14 | AT97: 16 | AU97: 0 | AV97: 0 | AW97: 0 | AX97: 0 | AY97: 0 | AZ97: 0 | BA97: 30 | BC97: 150000 | BD97: DESCANSO PENDIENTE POR CIERRE LABORAL AL 30-04-2026 | BP97: 75000 | CI97: 473333 | CP97: 0 | CQ97: 0 | CR97: 0
A98: 97 | B98: 16911975-9 | C98: 16911975 | D98: DIAZ | E98: GUAJARDO | F98: KATHRINE VALESKA | G98: ENCARGADA DOCUMENTAL DE DESPACHOS | I98: I | J98: F | K98: 5X2 | L98: 1720000002 | M98: 1 | N98: 1 | O98: 3 | P98: 3 | Q98: 3 | R98: 1 | S98: 1 | T98: 1 | U98: 1 | V98: 1 | W98: 3 | X98: 3 | Y98: 1 | Z98: 1 | AA98: 1 | AB98: 1 | AC98: 1 | AD98: 3 | AE98: 3 | AF98: 1 | AG98: 1 | AH98: 1 | AI98: 1 | AJ98: 1 | AK98: 3 | AL98: 3 | AM98: 1 | AN98: 1 | AO98: 1 | AP98: 1 | AR98: 21 | AS98: 0 | AT98: 9 | AU98: 0 | AV98: 0 | AW98: 0 | AX98: 0 | AY98: 0 | AZ98: 0 | BA98: 30 | CO98: =VLOOKUP(C98,'LOS HEROES'!$A$2:$D$30,4,0) -> 323598 | CP98: 0 | CQ98: =VLOOKUP(C98,SEGURO!$A$2:$C$28,3,0) -> 46667 | CR98: 0
A99: 98 | B99: 16971879-2 | C99: 16971879 | D99: MESSINA | E99: TRAIPE | F99: EDUARD NASKY | G99: AYUDANTE CONTROL CALIDAD | H99: 45880 | I99: D | J99: M | K99: B | L99: 1790000088 | M99: 3 | N99: 3 | O99: 3 | P99: 3 | Q99: 3 | R99: 3 | S99: 3 | T99: 2 | U99: 2 | V99: 2 | W99: 2 | X99: 2 | Y99: 2 | Z99: 2 | AA99: 2 | AB99: 2 | AC99: 2 | AD99: 2 | AE99: 2 | AF99: 2 | AG99: 2 | AH99: 3 | AI99: 3 | AJ99: 3 | AK99: 3 | AL99: 3 | AM99: 3 | AN99: 3 | AO99: 3 | AP99: 3 | AR99: 0 | AS99: 14 | AT99: 16 | AU99: 0 | AV99: 0 | AW99: 0 | AX99: 0 | AY99: 0 | AZ99: 0 | BA99: 30 | BE99: 250000 | BF99: bono innovacheck( correo) | BM99: 0 | CP99: 0 | CQ99: 0 | CR99: 0
A100: 99 | B100: 17003626-3 | C100: 17003626 | D100: MANSILLA | E100: MANSILLA | F100: GONZALO ANTONIO | G100: TECNICO CONTROL CALIDAD | H100: 45839 | I100: D | J100: M | K100: A | L100: 1790000088 | M100: 2 | N100: 2 | O100: 8 | P100: 8 | Q100: 2 | R100: 2 | S100: 2 | T100: 3 | U100: 3 | V100: 3 | W100: 3 | X100: 3 | Y100: 3 | Z100: 3 | AA100: 3 | AB100: 3 | AC100: 3 | AD100: 3 | AE100: 3 | AF100: 3 | AG100: 3 | AH100: 2 | AI100: 2 | AJ100: 2 | AK100: 2 | AL100: 2 | AM100: 2 | AN100: 2 | AO100: 2 | AP100: 2 | AR100: 0 | AS100: 14 | AT100: 14 | AU100: 0 | AV100: 0 | AW100: 0 | AX100: 0 | AY100: 2 | AZ100: 0 | BA100: 30 | BM100: 2 | BN100: 262998 | CP100: 0 | CQ100: 0 | CR100: 0
...

Sheet LOS HEROES
A1: Rut Trabajador | B1: DV RUT | C1: Nombre del Trabajador | D1: Valor Cuota
A2: 7365743 | B2: 1 | C2: BONE SANTIS CARLOS ALBERTO | D2: 552163
A3: 9430404 | B3: 0 | C3: BARRIA BARRIENTOS HARRY ISMAEL | D3: 64673
A4: 9583446 | B4: 9 | C4: CARJA JARA CRESCENTE ARTURO | D4: 46152
A5: 9717041 | B5: K | C5: OLIVARES DIAZ GONZALO LUIS | D5: 100429
A6: 11511458 | B6: 1 | C6: ASTUDILLO FRE JUAN LUIS | D6: 62330
A7: 11876153 | B7: 7 | C7: HERNANDEZ DE LA FUENTE FERNANDO HIPOLIT | D7: 451560
A8: 11922653 | B8: 8 | C8: ANDRADE CASTRO LUIS BERNARDO | D8: 309350
A9: 12713498 | B9: 7 | C9: ENIPANE CANOBRA RENE | D9: 19252
A10: 12943659 | B10: K | C10: SANTANDER SANTANDER CARLOS LUIS | D10: 290002
A11: 13205525 | B11: 4 | C11: ORTIZ MEDEL SEBASTIAN DEL CARMEN | D11: 343828
A12: 14296775 | B12: 8 | C12: CORTES HINAREJO ALEXIS RODRIGO | D12: 388170
A13: 15050650 | B13: 6 | C13: CODOCEO ORMENO JOEL ALEXANDER | D13: 184089
A14: 15164558 | B14: 5 | C14: SEPULVEDA VARGAS ESTEBAN ANDRES | D14: 250278
A15: 15373866 | B15: 1 | C15: ESTAY MORALES RENE ORLANDO | D15: 26705
A16: 15802017 | B16: 3 | C16: ARGANDONA IBACACHE PABLO CESAR | D16: 154145
A17: 16109258 | B17: 4 | C17: JOSE ORLANDO VALDERRAMA TABILO | D17: 5522
A18: 16596546 | B18: 9 | C18: GALLEGUILLOS GALLEGUILLOS WALDO GABRIEL | D18: 39152
A19: 16911975 | B19: 9 | C19: DIAZ GUAJARDO KATHERINE VALESKA | D19: 323598
A20: 17164817 | B20: 3 | C20: HERRERA CARVALLO FANNY DENIS | D20: 445677
A21: 17887975 | B21: 8 | C21: PIZARRO VEGA CRISTIAN FERNANDO | D21: 170812
A22: 18193913 | B22: 3 | C22: JOSE MIGUEL CALDERON ALVAREZ | D22: 5522
A23: 18217453 | B23: K | C23: PASTEN GUZMAN JAIRO BRAYAN | D23: 73099
A24: 18353315 | B24: 0 | C24: SEGOVIA ALFARO FABIAN EDGARDO | D24: 172524
A25: 19302584 | B25: 6 | C25: CASTILLO RODRIGUEZ JONATHAN ALEXANDER | D25: 197253
A26: 19467130 | B26: K | C26: IVAN MARCELO VILLEGAS CARMONA | D26: 5522
A27: 19496318 | B27: 1 | C27: GUERRERO LOPEZ CRISTOFHER ANDRES | D27: 63000
A28: 20051179 | B28: 4 | C28: PATRICIO ANDRES HIDALGO SEGOVIA | D28: 5522
A29: 20494956 | B29: 5 | C29: JOSE IGNACIO BARAHONA BERRIOS | D29: 5522
A30: 20866663 | B30: 0 | C30: ALVARO ALFONSO EXEQUIEL PEREZ ROJAS | D30: 5522

Sheet LA ARAUCANA
A1: RutAfiliado | B1: DvAfiliado | C1: NombreAfiliado | D1: MontoCuotaPendiente
A2: 13327527 | B2: 4 | C2: VICTOR POBLETE | D2: 154868
A3: 8532533 | B3: 7 | C3: ALEJANDRO ELGUETA | D3: 176117
A4: 15876024 | B4: K | C4: MANUEL STUARDO | D4: 101408
A5: 10904003 | B5: 7 | C5: DAVID EXEQUIEL | D5: 116803

Sheet SEGURO
A1: RUT | B1: TOTAL | C1: 0.3
A2: 10675506 | B2: 155558 | C2: 46667
A3: 11265430 | B3: 151060 | C3: 45318
A4: 11876153 | B4: 155558 | C4: 46667
A5: 11922653 | B5: 109083 | C5: 32725
A6: 12227004 | B6: 109083 | C6: 32725
A7: 12487485 | B7: 62596 | C7: 18779
A8: 13419327 | B8: 155558 | C8: 46667
A9: 13531208 | B9: 155558 | C9: 46667
A10: 13702938 | B10: 155558 | C10: 46667
A11: 13904453 | B11: 155558 | C11: 46667
A12: 14113613 | B12: 155558 | C12: 46667
A13: 14129064 | B13: 155558 | C13: 46667
... A28: 13531208 | B28: 155558 | C28: 46667

Sheet FALP
A1: R.U.T. | B1: Nombre | C1: Total
A2: 14129064 | B2: DIAZ BASUALTO, ANDRES | C2: 17600
A3: 15661268 | B3: REBOLLEDO ROSALES, LUIS | C3: 17600
A4: 13531208 | B4: ARAYA REYES, MARCO | C4: 17600
A5: 15936945 | B5: SEPULVEDA VERGAR, KARLA | C5: 8800
A6: 17164817 | B6: HERRERA CARVALLO, FANNY DENIS | C6: 8800
A7: 11876153 | B7: HERNANDEZ DE LA FUENTE, FERNANDO | C7: 17600
A8: 12227004 | B8: NARVAEZ PEÑA, ALDO | C8: 17600
A9: 10675506 | B9: CAMPILLAI NAVARRO, VICTOR | C9: 17600
A10: 17119888 | B10: LABRA RAMIREZ, JANITZA ANABAENA | C10: 17600
A11: 13904453 | B11: TORO ANDRADE, ESTEBAN | C11: 8800
A12: 8077970 | B12: RETAMAL ARAYA, JAIME LORENZO | C12: 17600
A13: 12487485 | B13: SILVA BOCK, DANIELA | C13: 17600

Sheet 04_2026_OF
A1: Nº | B1: RUT (sin puntos y con guion) | C1: ID (rut sin puntos, sin guión ni digito vertificador) | D1: APELLIDO PATERNO | E1: APELLIDO MATERNO | F1: NOMBRES | G1: CARGO | H1: INICIO DE CONTRATO | I1: D/I | J1: GENERO M/F | K1: TURNO (5x2-4x3-14x14 -art22) | L1: CC | M1: 1 | N1: 2 | O1: 3 | P1: 4 | Q1: 5 | R1: 6 | S1: 7 | T1: 8 | U1: 9 | V1: 10 | W1: 11 | X1: 12 | Y1: 13 | Z1: 14 | AA1: 15 | AB1: 16 | AC1: 17 | AD1: 18 | AE1: 19 | AF1: 20 | AG1: 21 | AH1: 22 | AI1: 23 | AJ1: 24 | AK1: 25 | AL1: 26 | AM1: 27 | AN1: 28 | AO1: 29 | AP1: 30 | AQ1: 31 | AR1: (1) | AS1: (2) | AT1: (3) | AU1: (4) | AV1: (5) | AW1: (6) | AX1: (7) | AY1: (8) | AZ1: (9) | BA1: T.D.T. | BB1: 1033-Bono Gestión Variable | BC1: 1029-Bono Compensatorio descanso | BD1: Justificación Bono 10-29 (Compensatorio descanso) | BE1: 1034-Bono Incentivo variable | BF1: Justificación Bono 1034 (Incentivo variable) | BG1: 1140-Bono Responsabilidad 2 | BH1: Justificación 1140 (Bono Responsabilidad) | BI1: 1041-Bono Terreno (Exclusivo proyecto Techint-CMDIC) | BJ1: 1031-Bono Escolaridad I/T (Uso exclusivo Area de Compensaciones) | BK1: 1092-Diferencia de haber | BL1: Justificación Bono 1092 (Diferencia de Haber) | BM1: Cantidad de feriados del mes | BN1: 1082-Bono Compens. Feriado | BO1: 1020-Aguinaldo I/T | BP1: 1140-Bono de Permanencia (Plan de Beneficios) | BQ1: Bono Seguridad BESALCO-MEL | BR1: Bono Q1 (Exclusivo Collahuasi) | BS1: Bono Q2 (Exclusivo Collahuasi) | BT1: Bono Q3 (Exclusivo Collahuasi) | BU1: Bono Q4 (Exclusivo Collahuasi) | BV1: Bono RSA (Exclusivo Collahuasi) | BW1: 1044-Asignación Colación | BX1: Justificación Asignacion Colacion | BY1: 1165-Asignación Movilización 2 | BZ1: Justificación Asignación Movilización 2 | CA1: 1172-Viatico 2 | CB1: Justificación Viatico | CC1: 1073-Otras Asignaciones N/I (Beneficios) | CD1: Justificaciión de Asignación (Detalle del beneficio) | CE1: 1032-Bono Escolaridad N/I | CF1: 1124-Asignación familiar Retroactiva | CG1: Descuento por aporte voluntario | CH1: Observaciones generales | CI1: ACUERDO MARCO ACCIONA-CODELCO | CJ1: GRATIFICACION ACUERD MARCO ACCIONA-CODELCO2 | CK1: DIAS ADICIONALES CHIQUICAMATA | CL1: BONO PARTICIPACION CHIQUI
A2: 1 | B2: 7365743-1 | C2: 7365743 | D2: BONE | E2: SANTIS | F2: CARLOS ALBERTO | G2: GERENTE GENERAL | I2: I | J2: M | K2: 5X2 | L2: 1710000001 | M2: 1 | N2: 1 | O2: 3 | P2: 3 | Q2: 3 | R2: 1 | S2: 1 | T2: 1 | U2: 1 | V2: 1 | W2: 3 | X2: 3 | Y2: 1 | Z2: 1 | AA2: 1 | AB2: 1 | AC2: 1 | AD2: 3 | AE2: 3 | AF2: 1 | AG2: 1 | AH2: 1 | AI2: 1 | AJ2: 1 | AK2: 3 | AL2: 3 | AM2: 1 | AN2: 1 | AO2: 1 | AP2: 1 | AR2: 21 | AS2: 0 | AT2: 9 | AU2: 0 | AV2: 0 | AW2: 0 | AX2: 0 | AY2: 0 | AZ2: 0 | BA2: 30
A3: 2 | B3: 9205219-2 | C3: 9205219 | D3: JOGLAR | E3: ZAMBRANA | F3: ADOLFO | G3: GERENTE GESTION PERSONAS | I3: I | J3: M | K3: 5X2 | L3: 1720000001 | M3: 1 | N3: 1 | O3: 3 | P3: 3 | Q3: 3 | R3: 1 | S3: 1 | T3: 1 | U3: 1 | V3: 3 | W3: 3 | X3: 3 | Y3: 1 | Z3: 1 | AA3: 1 | AB3: 1 | AC3: 3 | AD3: 3 | AE3: 3 | AF3: 1 | AG3: 1 | AH3: 1 | AI3: 1 | AJ3: 3 | AK3: 3 | AL3: 3 | AM3: 1 | AN3: 1 | AO3: 1 | AP3: 1 | AR3: 18 | AS3: 0 | AT3: 12 | AU3: 0 | AV3: 0 | AW3: 0 | AX3: 0 | AY3: 0 | AZ3: 0 | BA3: 30
A4: 3 | B4: 9430404-0 | C4: 9430404 | D4: BARRIA | E4: BARRIENTOS | F4: HARRY ISMAEL | G4: ENCARGADO TALLER MANTENCION | I4: I | J4: M | K4: 5X2 | L4: 1740000002 | M4: 1 | N4: 1 | O4: 3 | P4: 3 | Q4: 3 | R4: 9 | S4: 9 | T4: 9 | U4: 9 | V4: 9 | W4: 9 | X4: 9 | Y4: 9 | Z4: 9 | AA4: 9 | AB4: 9 | AC4: 9 | AD4: 9 | AE4: 9 | AF4: 1 | AG4: 1 | AH4: 1 | AI4: 1 | AJ4: 1 | AK4: 3 | AL4: 3 | AM4: 1 | AN4: 1 | AO4: 1 | AP4: 1 | AR4: 11 | AS4: 0 | AT4: 5 | AU4: 0 | AV4: 0 | AW4: 0 | AX4: 0 | AY4: 0 | AZ4: 14 | BA4: 30 | CA4: 30000 | CB4: Viatico para traslado terminal buses oficina (4 am)
A5: 4 | B5: 10675506-K | C5: 10675506 | D5: CAMPILLAI | E5: NAVARRO | F5: VICTOR JAVIER | G5: JEFE DE UNIDAD LOGISTICA | I5: I | J5: M | K5: 5X2 | L5: 1740000003 | M5: 1 | N5: 1 | O5: 3 | P5: 3 | Q5: 3 | R5: 1 | S5: 1 | T5: 1 | U5: 1 | V5: 1 | W5: 3 | X5: 3 | Y5: 1 | Z5: 1 | AA5: 1 | AB5: 1 | AC5: 1 | AD5: 3 | AE5: 3 | AF5: 1 | AG5: 1 | AH5: 1 | AI5: 1 | AJ5: 1 | AK5: 3 | AL5: 3 | AM5: 1 | AN5: 1 | AO5: 1 | AP5: 1 | AR5: 21 | AS5: 0 | AT5: 9 | AU5: 0 | AV5: 0 | AW5: 0 | AX5: 0 | AY5: 0 | AZ5: 0 | BA5: 30 | BW5: 110000
A6: 5 | B6: 12227004-1 | C6: 12227004 | D6: NARVAEZ | E6: PEÑA | F6: ALDO IVAN | G6: SUBGERENTE TECNICO | I6: I | J6: M | K6: 5X2 | L6: 1760000001 | M6: 1 | N6: 1 | O6: 3 | P6: 3 | Q6: 3 | R6: 1 | S6: 1 | T6: 1 | U6: 1 | V6: 1 | W6: 3 | X6: 3 | Y6: 1 | Z6: 1 | AA6: 1 | AB6: 1 | AC6: 1 | AD6: 3 | AE6: 3 | AF6: 1 | AG6: 1 | AH6: 1 | AI6: 1 | AJ6: 1 | AK6: 3 | AL6: 3 | AM6: 1 | AN6: 1 | AO6: 1 | AP6: 1 | AR6: 21 | AS6: 0 | AT6: 9 | AU6: 0 | AV6: 0 | AW6: 0 | AX6: 0 | AY6: 0 | AZ6: 0 | BA6: 30 | BE6: 179000 | BF6: Bono ajuste liquido pactado
A7: 6 | B7: 12487485-8 | C7: 12487485 | D7: SILVA | E7: BOCK | F7: DANIELA VIVIAN | G7: JEFE UNIDAD COMPENSACIONES | I7: I | J7: F | K7: 5X2 | L7: 1720000001 | M7: 1 | N7: 1 | O7: 3 | P7: 3 | Q7: 3 | R7: 1 | S7: 1 | T7: 1 | U7: 1 | V7: 1 | W7: 3 | X7: 3 | Y7: 1 | Z7: 1 | AA7: 1 | AB7: 1 | AC7: 9 | AD7: 3 | AE7: 3 | AF7: 1 | AG7: 1 | AH7: 1 | AI7: 1 | AJ7: 1 | AK7: 3 | AL7: 3 | AM7: 1 | AN7: 1 | AO7: 1 | AP7: 1 | AR7: 20 | AS7: 0 | AT7: 9 | AU7: 0 | AV7: 0 | AW7: 0 | AX7: 0 | AY7: 0 | AZ7: 1 | BA7: 30
A8: 7 | B8: 13904453-3 | C8: 13904453 | D8: TORO | E8: ANDRADE | F8: ESTEBAN | G8: GERENTE DE PLANIFICACION Y CONTROL | I8: I | J8: M | K8: 5X2 | L8: 1740000001 | M8: 1 | N8: 1 | O8: 3 | P8: 3 | Q8: 3 | R8: 1 | S8: 1 | T8: 1 | U8: 1 | V8: 1 | W8: 3 | X8: 3 | Y8: 1 | Z8: 1 | AA8: 1 | AB8: 1 | AC8: 1 | AD8: 3 | AE8: 3 | AF8: 1 | AG8: 1 | AH8: 1 | AI8: 1 | AJ8: 1 | AK8: 3 | AL8: 3 | AM8: 1 | AN8: 1 | AO8: 1 | AP8: 1 | AR8: 21 | AS8: 0 | AT8: 9 | AU8: 0 | AV8: 0 | AW8: 0 | AX8: 0 | AY8: 0 | AZ8: 0 | BA8: 30
A9: 8 | B9: 14113613-5 | C9: 14113613 | D9: BARRIOS | E9: ACUÑA | F9: NELSON ENRIQUE | G9: JEFE GESTION PERSONAS | I9: I | J9: M | K9: 5X2 | L9: 1740000001 | M9: 1 | N9: 1 | O9: 3 | P9: 3 | Q9: 3 | R9: 1 | S9: 1 | T9: 1 | U9: 1 | V9: 1 | W9: 3 | X9: 3 | Y9: 1 | Z9: 1 | AA9: 1 | AB9: 1 | AC9: 1 | AD9: 3 | AE9: 3 | AF9: 1 | AG9: 1 | AH9: 1 | AI9: 1 | AJ9: 1 | AK9: 3 | AL9: 3 | AM9: 1 | AN9: 1 | AO9: 1 | AP9: 1 | AR9: 21 | AS9: 0 | AT9: 9 | AU9: 0 | AV9: 0 | AW9: 0 | AX9: 0 | AY9: 0 | AZ9: 0 | BA9: 30
A10: 9 | B10: 14129064-9 | C10: 14129064 | D10: DIAZ | E10: BASOALTO | F10: ANDRES EDUARDO | G10: SUBGERENTE DE CONTABILIDAD Y FINANZAS | I10: I | J10: M | K10: 5X2 | L10: 1720000002 | M10: 1 | N10: 1 | O10: 3 | P10: 3 | Q10: 3 | R10: 1 | S10: 1 | T10: 1 | U10: 1 | V10: 1 | W10: 3 | X10: 3 | Y10: 1 | Z10: 1 | AA10: 1 | AB10: 1 | AC10: 1 | AD10: 3 | AE10: 3 | AF10: 1 | AG10: 1 | AH10: 1 | AI10: 1 | AJ10: 1 | AK10: 3 | AL10: 3 | AM10: 1 | AN10: 1 | AO10: 1 | AP10: 1 | AR10: 21 | AS10: 0 | AT10: 9 | AU10: 0 | AV10: 0 | AW10: 0 | AX10: 0 | AY10: 0 | AZ10: 0 | BA10: 30
A11: 10 | B11: 15661268-5 | C11: 15661268 | D11: REBOLLEDO | E11: ROSALES | F11: LUIS ANDRES | G11: INGENIERO DE PROYECTOS | I11: I | J11: M | K11: 5X2 | L11: 1750000001 | M11: 1 | N11: 1 | O11: 3 | P11: 3 | Q11: 3 | R11: 1 | S11: 1 | T11: 1 | U11: 1 | V11: 1 | W11: 1 | X11: 1 | Y11: 1 | Z11: 1 | AA11: 1 | AB11: 1 | AC11: 1 | AD11: 3 | AE11: 3 | AF11: 1 | AG11: 1 | AH11: 1 | AI11: 1 | AJ11: 1 | AK11: 3 | AL11: 3 | AM11: 1 | AN11: 1 | AO11: 1 | AP11: 1 | AR11: 23 | AS11: 0 | AT11: 7 | AU11: 0 | AV11: 0 | AW11: 0 | AX11: 0 | AY11: 0 | AZ11: 0 | BA11: 30
A12: 11 | B12: 15936945-5 | C12: 15936945 | D12: SEPULVEDA | E12: VERGARA | F12: KARLA ANDREA | G12: SUBGERENTE DE ESTUDIO DE PROYECTOS | I12: I | J12: F | K12: 5X2 | L12: 1750000001 | M12: 1 | N12: 1 | O12: 3 | P12: 3 | Q12: 3 | R12: 1 | S12: 1 | T12: 1 | U12: 1 | V12: 1 | W12: 3 | X12: 3 | Y12: 1 | Z12: 1 | AA12: 1 | AB12: 1 | AC12: 1 | AD12: 3 | AE12: 3 | AF12: 1 | AG12: 1 | AH12: 1 | AI12: 1 | AJ12: 1 | AK12: 3 | AL12: 3 | AM12: 1 | AN12: 1 | AO12: 1 | AP12: 1 | AR12: 21 | AS12: 0 | AT12: 9 | AU12: 0 | AV12: 0 | AW12: 0 | AX12: 0 | AY12: 0 | AZ12: 0 | BA12: 30
A13: 12 | B13: 16481993-0 | C13: 16481993 | D13: GOLOTT | E13: VALDES | F13: MARIA JOSE IGNACIA | G13: CONDUCTOR CAMION RAMPA | I13: D | J13: F | K13: 5X2 | L13: 1740000002 | M13: 1 | N13: 1 | O13: 3 | P13: 3 | Q13: 3 | R13: 1 | S13: 1 | T13: 1 | U13: 1 | V13: 1 | W13: 3 | X13: 3 | Y13: 1 | Z13: 1 | AA13: 1 | AB13: 1 | AC13: 1 | AD13: 3 | AE13: 3 | AF13: 1 | AG13: 1 | AH13: 1 | AI13: 1 | AJ13: 1 | AK13: 3 | AL13: 3 | AM13: 1 | AN13: 1 | AO13: 1 | AP13: 1 | AR13: 21 | AS13: 0 | AT13: 9 | AU13: 0 | AV13: 0 | AW13: 0 | AX13: 0 | AY13: 0 | AZ13: 0 | BA13: 30
A14: 13 | B14: 16911975-9 | C14: 16911975 | D14: DIAZ | E14: GUAJARDO | F14: KATHRINE VALESKA | G14: ENCARGADA DOCUMENTAL DE DESPACHOS | I14: I | J14: F | K14: 5X2 | L14: 1720000002 | M14: 1 | N14: 1 | O14: 3 | P14: 3 | Q14: 3 | R14: 1 | S14: 1 | T14: 1 | U14: 1 | V14: 1 | W14: 3 | X14: 3 | Y14: 1 | Z14: 1 | AA14: 1 | AB14: 1 | AC14: 1 | AD14: 3 | AE14: 3 | AF14: 1 | AG14: 1 | AH14: 1 | AI14: 1 | AJ14: 1 | AK14: 3 | AL14: 3 | AM14: 1 | AN14: 1 | AO14: 1 | AP14: 1 | AR14: 21 | AS14: 0 | AT14: 9 | AU14: 0 | AV14: 0 | AW14: 0 | AX14: 0 | AY14: 0 | AZ14: 0 | BA14: 30
A15: 14 | B15: 17119888-7 | C15: 17119888 | D15: LABRA | E15: RAMIREZ | F15: JANITZA ANABAENA | G15: ENCARGADA DOCUMENTAL Y CONTROL DE GESTION | I15: I | J15: F | K15: 5X2 | L15: 1740000001 | M15: 1 | N15: 1 | O15: 3 | P15: 3 | Q15: 3 | R15: 1 | S15: 1 | T15: 1 | U15: 1 | V15: 1 | W15: 3 | X15: 3 | Y15: 1 | Z15: 1 | AA15: 1 | AB15: 1 | AC15: 1 | AD15: 3 | AE15: 3 | AF15: 1 | AG15: 1 | AH15: 1 | AI15: 1 | AJ15: 1 | AK15: 3 | AL15: 3 | AM15: 1 | AN15: 1 | AO15: 1 | AP15: 1 | AR15: 21 | AS15: 0 | AT15: 9 | AU15: 0 | AV15: 0 | AW15: 0 | AX15: 0 | AY15: 0 | AZ15: 0 | BA15: 30
A16: 15 | B16: 17164817-3 | C16: 17164817 | D16: HERRERA | E16: CARVALLO | F16: FANNY DENIS | G16: ENCARGADA SSOMAC | I16: I | J16: F | K16: 5X2 | L16: 1740000001 | M16: 1 | N16: 1 | O16: 3 | P16: 3 | Q16: 3 | R16: 1 | S16: 1 | T16: 4 | U16: 4 | V16: 4 | W16: 4 | X16: 4 | Y16: 4 | Z16: 4 | AA16: 4 | AB16: 4 | AC16: 4 | AD16: 4 | AE16: 4 | AF16: 4 | AG16: 4 | AH16: 4 | AI16: 1 | AJ16: 1 | AK16: 3 | AL16: 3 | AM16: 1 | AN16: 1 | AO16: 1 | AP16: 1 | AR16: 10 | AS16: 0 | AT16: 5 | AU16: 15 | AV16: 0 | AW16: 0 | AX16: 0 | AY16: 0 | AZ16: 0 | BA16: 15
A17: 16 | B17: 19445770-7 | C17: 19445770 | D17: ROJAS | E17: POBLETE | F17: KATIUSCA AYLEN | G17: GENERALISTA DE RRHH | I17: I | J17: F | K17: 5X2 | L17: 1770000002 | M17: 1 | N17: 1 | O17: 3 | P17: 3 | Q17: 3 | R17: 1 | S17: 1 | T17: 1 | U17: 1 | V17: 1 | W17: 3 | X17: 3 | Y17: 1 | Z17: 1 | AA17: 1 | AB17: 1 | AC17: 1 | AD17: 3 | AE17: 3 | AF17: 1 | AG17: 1 | AH17: 1 | AI17: 1 | AJ17: 1 | AK17: 3 | AL17: 3 | AM17: 1 | AN17: 1 | AO17: 1 | AP17: 1 | AR17: 21 | AS17: 0 | AT17: 9 | AU17: 0 | AV17: 0 | AW17: 0 | AX17: 0 | AY17: 0 | AZ17: 0 | BA17: 30
A18: 17 | B18: 24718250-0 | C18: 24718250 | D18: MOSQUERA | E18: VALDERRAMA | F18: GUILLERMO | G18: RECEPCIONISTA ADMINISTRATIVO | I18: I | J18: M | K18: 5X2 | L18: 1770000002 | M18: 1 | N18: 1 | O18: 3 | P18: 3 | Q18: 3 | R18: 1 | S18: 1 | T18: 1 | U18: 1 | V18: 1 | W18: 3 | X18: 3 | Y18: 1 | Z18: 1 | AA18: 1 | AB18: 1 | AC18: 1 | AD18: 3 | AE18: 3 | AF18: 1 | AG18: 1 | AH18: 1 | AI18: 1 | AJ18: 1 | AK18: 3 | AL18: 3 | AM18: 1 | AN18: 1 | AO18: 1 | AP18: 1 | AR18: 21 | AS18: 0 | AT18: 9 | AU18: 0 | AV18: 0 | AW18: 0 | AX18: 0 | AY18: 0 | AZ18: 0 | BA18: 30
A19: 18 | B19: 9717041-K | C19: 9717041 | D19: OLIVARES | E19: DIAZ | F19: GONZALO LUIS | G19: ENCARGADO DE COMPRAS Y ABASTECIMIENTO | I19: I | J19: M | K19: 5X2 | L19: 1790000088 | M19: 1 | N19: 1 | O19: 3 | P19: 3 | Q19: 3 | R19: 1 | S19: 1 | T19: 1 | U19: 1 | V19: 1 | W19: 3 | X19: 3 | Y19: 1 | Z19: 1 | AA19: 1 | AB19: 1 | AC19: 1 | AD19: 3 | AE19: 3 | AF19: 1 | AG19: 1 | AH19: 1 | AI19: 1 | AJ19: 1 | AK19: 3 | AL19: 3 | AM19: 1 | AN19: 1 | AO19: 1 | AP19: 1 | AR19: 21 | AS19: 0 | AT19: 9 | AU19: 0 | AV19: 0 | AW19: 0 | AX19: 0 | AY19: 0 | AZ19: 0 | BA19: 30 | BW19: 110000
A20: 19 | B20: 20091945-9 | C20: 20091945 | D20: JIMENEZ | E20: BUGUEÑO | F20: DENIS MARCELA | G20: ADMINISTRATIVO | I20: I | J20: F | K20: 5X2 | L20: 1790000091 | M20: 4 | N20: 4 | O20: 4 | P20: 4 | Q20: 4 | R20: 4 | S20: 4 | T20: 4 | U20: 4 | V20: 4 | W20: 4 | X20: 4 | Y20: 4 | Z20: 4 | AA20: 4 | AB20: 4 | AC20: 4 | AD20: 4 | AE20: 4 | AF20: 4 | AG20: 4 | AH20: 4 | AI20: 4 | AJ20: 4 | AK20: 4 | AL20: 4 | AM20: 4 | AN20: 4 | AO20: 4 | AP20: 4 | AR20: 0 | AS20: 0 | AT20: 0 | AU20: 30 | AV20: 0 | AW20: 0 | AX20: 0 | AY20: 0 | AZ20: 0 | BA20: 0
A21: 20 | B21: 11922653-8 | C21: 11922653 | D21: ANDRADE | E21: CASTRO | F21: LUIS BERNARDO | G21: ENCARGADO DE MANTENCION | I21: I | J21: M | K21: 5X2 | L21: 1790000088 | M21: 4 | N21: 4 | O21: 4 | P21: 4 | Q21: 4 | R21: 4 | S21: 1 | T21: 1 | U21: 1 | V21: 1 | W21: 3 | X21: 3 | Y21: 1 | Z21: 1 | AA21: 1 | AB21: 1 | AC21: 1 | AD21: 3 | AE21: 3 | AF21: 1 | AG21: 1 | AH21: 1 | AI21: 1 | AJ21: 1 | AK21: 3 | AL21: 3 | AM21: 1 | AN21: 1 | AO21: 1 | AP21: 1 | AR21: 18 | AS21: 0 | AT21: 6 | AU21: 6 | AV21: 0 | AW21: 0 | AX21: 0 | AY21: 0 | AZ21: 0 | BA21: 24
A22: 21 | B22: 13205525-4 | C22: 13205525 | D22: ORTIZ | E22: MEDEL | F22: SEBASTIAN DEL CARMEN | G22: CONDUCTOR CAMION RAMPA | H22: 44136 | I22: D | J22: M | K22: 5X2 | L22: 1790000088 | M22: 5 | N22: 5 | O22: 5 | P22: 5 | Q22: 5 | R22: 9 | S22: 9 | T22: 9 | U22: 9 | V22: 9 | W22: 9 | X22: 9 | Y22: 9 | Z22: 9 | AA22: 9 | AB22: 9 | AC22: 9 | AD22: 9 | AE22: 9 | AF22: 9 | AG22: 9 | AH22: 9 | AI22: 9 | AJ22: 9 | AK22: 9 | AL22: 9 | AM22: 9 | AN22: 9 | AO22: 9 | AP22: 9 | AR22: 0 | AS22: 0 | AT22: 0 | AU22: 0 | AV22: 5 | AW22: 0 | AX22: 0 | AY22: 0 | AZ22: 25 | BA22: 30
A23: 22 | B23: 9912965-4 | C23: 9912965 | D23: PEREZ | E23: OSSANDON | F23: ORIEL EDUARDO | G23: SUPERVISOR CONTROL CALIDAD | I23: I | J23: M | K23: 5X2 | L23: 1740000002 | M23: 9 | N23: 9 | O23: 9 | P23: 9 | Q23: 9 | R23: 9 | S23: 1 | T23: 1 | U23: 1 | V23: 1 | W23: 3 | X23: 3 | Y23: 9 | Z23: 9 | AA23: 9 | AB23: 9 | AC23: 9 | AD23: 9 | AE23: 9 | AF23: 9 | AG23: 9 | AH23: 9 | AI23: 9 | AJ23: 9 | AK23: 9 | AL23: 9 | AM23: 9 | AN23: 9 | AO23: 9 | AP23: 9 | AR23: 4 | AS23: 0 | AT23: 2 | AU23: 0 | AV23: 0 | AW23: 0 | AX23: 0 | AY23: 0 | AZ23: 24 | BA23: 30 | BE23: 519000 | BF23: Bono complemento sueldo | CH23: CENTRO DE COSTO (SIN FAENA)
A24: 23 | B24: 11876153-7 | C24: 11876153 | D24: HERNANDEZ | E24: DE LA FUENTE | F24: FERNANDO HIPOLITO | G24: SUPERVISRO VISITADOR E INSTRUCTOR | I24: I | J24: M | K24: 5X2 | L24: 1790000090 | M24: 1 | N24: 1 | O24: 3 | P24: 3 | Q24: 3 | R24: 1 | S24: 3 | T24: 3 | U24: 1 | V24: 1 | W24: 1 | X24: 1 | Y24: 1 | Z24: 3 | AA24: 3 | AB24: 1 | AC24: 1 | AD24: 1 | AE24: 1 | AF24: 1 | AG24: 3 | AH24: 3 | AI24: 1 | AJ24: 1 | AK24: 1 | AL24: 1 | AM24: 1 | AN24: 1 | AO24: 1 | AP24: 1 | AR24: 21 | AS24: 0 | AT24: 9 | AU24: 0 | AV24: 0 | AW24: 0 | AX24: 0 | AY24: 0 | AZ24: 0 | BA24: 30 | BW24: 110000 | CE24: 77281
A25: 24 | B25: 20051179-4 | C25: 20051179 | D25: HIDALGO | E25: SEGOVIA | F25: PATRICIO ANDRÉS | G25: TECNICO EN SISTEMA GEOMEMB | H25: 46113 | I25: D | J25: M | K25: 5X2 | L25: 1790000088 | M25: 1 | N25: 1 | O25: 3 | P25: 3 | Q25: 3 | R25: 1 | S25: 3 | T25: 3 | U25: 1 | V25: 1 | W25: 1 | X25: 1 | Y25: 1 | Z25: 3 | AA25: 3 | AB25: 1 | AC25: 1 | AD25: 1 | AE25: 1 | AF25: 1 | AG25: 3 | AH25: 3 | AI25: 1 | AJ25: 1 | AK25: 1 | AL25: 1 | AM25: 1 | AN25: 1 | AO25: 1 | AP25: 1 | AR25: 21 | AS25: 0 | AT25: 9 | AU25: 0 | AV25: 0 | AW25: 0 | AX25: 0 | AY25: 0 | AZ25: 0 | BA25: 30
A26: 25 | B26: 20308051-4 | C26: 20308051 | D26: RODRIGUEZ | E26: CORTES | F26: KEVIN ALEJANDRO | G26: TECNICO EN SISTEMA GEOMEMB | H26: 46113 | I26: D | J26: M | K26: 5X2 | L26: 1790000088 | M26: 1 | N26: 1 | O26: 3 | P26: 3 | Q26: 3 | R26: 1 | S26: 3 | T26: 3 | U26: 1 | V26: 1 | W26: 1 | X26: 1 | Y26: 1 | Z26: 3 | AA26: 3 | AB26: 1 | AC26: 1 | AD26: 1 | AE26: 1 | AF26: 1 | AG26: 3 | AH26: 3 | AI26: 1 | AJ26: 1 | AK26: 1 | AL26: 1 | AM26: 1 | AN26: 1 | AO26: 1 | AP26: 1 | AR26: 21 | AS26: 0 | AT26: 9 | AU26: 0 | AV26: 0 | AW26: 0 | AX26: 0 | AY26: 0 | AZ26: 0 | BA26: 30
A27: 26 | B27: 17659588-4 | C27: 17659588 | D27: FOURNIEL | E27: NAVARRO | F27: ALVARO RODRIGO | G27: ADMINISTRADOR DE CONTRATO | I27: I | J27: M | K27: 5X2 | L27: 1740000002 | AR27: 0 | AS27: 0 | AT27: 0 | AU27: 0 | AV27: 0 | AW27: 0 | AX27: 0 | AY27: 0 | AZ27: 0 | BA27: 0 | BB27: 2000000 | CH27: SOLO PAGAR BONO (LIQUIDO 1.6) - CENTRO COSTO SIN FAENA
A28: 27 | B28: 14016056-3 | C28: 14016056 | D28: VALDIVIA | E28: TORRES | F28: GONZALO EDUARDO | G28: GENERALISTA GESTION PERSONAS | H28: 46104 | I28: I | J28: M | K28: 5X2 | L28: 1720000001 | M28: 1 | N28: 1 | O28: 3 | P28: 3 | Q28: 3 | R28: 1 | S28: 3 | T28: 3 | U28: 1 | V28: 1 | W28: 1 | X28: 1 | Y28: 1 | Z28: 3 | AA28: 3 | AB28: 1 | AC28: 1 | AD28: 1 | AE28: 1 | AF28: 1 | AG28: 3 | AH28: 3 | AI28: 1 | AJ28: 1 | AK28: 1 | AL28: 1 | AM28: 1 | AN28: 1 | AO28: 1 | AP28: 1 | AR28: 21 | AS28: 0 | AT28: 9 | AU28: 0 | AV28: 0 | AW28: 0 | AX28: 0 | AY28: 0 | AZ28: 0 | BA28: 30
A29: 28 | B29: 13012039-3 | C29: 13012039 | D29: LOBOS | E29: PIZARRO | F29: JORGE HUMBERTO | G29: JEFE CONTROL DE CALIDAD | H29: 46118 | I29: I | J29: M | K29: 5X2 | L29: 1790000088 | R29: 1 | S29: 1 | T29: 1 | U29: 1 | V29: 1 | W29: 3 | X29: 3 | Y29: 1 | Z29: 1 | AA29: 1 | AB29: 1 | AC29: 1 | AD29: 3 | AE29: 3 | AF29: 1 | AG29: 1 | AH29: 1 | AI29: 1 | AJ29: 1 | AK29: 3 | AL29: 3 | AM29: 1 | AN29: 1 | AO29: 1 | AP29: 1 | AR29: 19 | AS29: 0 | AT29: 6 | AU29: 0 | AV29: 0 | AW29: 0 | AX29: 0 | AY29: 0 | AZ29: 0 | BA29: 25

Sheet 04_2026_Techint-RT
A1: Nº | B1: RUT (sin puntos y con guion) | C1: ID (rut sin puntos, sin guión ni digito vertificador) | D1: APELLIDO PATERNO | E1: APELLIDO MATERNO | F1: NOMBRES | G1: CARGO | H1: INICIO DE CONTRATO | I1: D/I | J1: GENERO M/F | K1: TURNO (5x2-4x3-14x14 -art22) | L1: CC | M1: 1 | N1: 2 | O1: 3 | P1: 4 | Q1: 5 | R1: 6 | S1: 7 | T1: 8 | U1: 9 | V1: 10 | W1: 11 | X1: 12 | Y1: 13 | Z1: 14 | AA1: 15 | AB1: 16 | AC1: 17 | AD1: 18 | AE1: 19 | AF1: 20 | AG1: 21 | AH1: 22 | AI1: 23 | AJ1: 24 | AK1: 25 | AL1: 26 | AM1: 27 | AN1: 28 | AO1: 29 | AP1: 30 | AQ1: 31 | AR1: (1) | AS1: (2) | AT1: (3) | AU1: (4) | AV1: (5) | AW1: (6) | AX1: (7) | AY1: (8) | AZ1: (9) | BA1: T.D.T. | BB1: 1033-Bono Gestión Variable | BC1: 1029-Bono Compensatorio descanso | BD1: Justificación Bono 10-29 (Compensatorio descanso) | BE1: 1034-Bono Incentivo variable | BF1: Justificación Bono 1034 (Incentivo variable) | BG1: 1140-Bono Responsabilidad 2 | BH1: Justificación 1140 (Bono Responsabilidad) | BI1: 1041-Bono Terreno (Exclusivo proyecto Techint-CMDIC) | BJ1: 1031-Bono Escolaridad I/T (Uso exclusivo Area de Compensaciones) | BK1: 1092-Diferencia de haber | BL1: Justificación Bono 1092 (Diferencia de Haber) | BM1: Cantidad de feriados del mes | BN1: 1082-Bono Compens. Feriado | BO1: 1020-Aguinaldo I/T | BP1: 1140-Bono de Permanencia (Plan de Beneficios) | BQ1: Bono Seguridad BESALCO-MEL | BR1: Bono Q1 (Exclusivo Collahuasi) | BS1: Bono Q2 (Exclusivo Collahuasi) | BT1: Bono Q3 (Exclusivo Collahuasi) | BU1: Bono Q4 (Exclusivo Collahuasi) | BV1: Bono RSA (Exclusivo Collahuasi) | BW1: 1044-Asignación Colación | BX1: Justificación Asignacion Colacion | BY1: 1165-Asignación Movilización 2 | BZ1: Justificación Asignación Movilización 2 | CA1: 1172-Viatico 2 | CB1: Justificación Viatico | CC1: 1073-Otras Asignaciones N/I (Beneficios) | CD1: Justificaciión de Asignación (Detalle del beneficio) | CE1: 1032-Bono Escolaridad N/I | CF1: 1124-Asignación familiar Retroactiva | CG1: Descuento por aporte voluntario | CH1: Observaciones generales | CI1: ACUERDO MARCO ACCIONA-CODELCO | CJ1: GRATIFICACION ACUERD MARCO ACCIONA-CODELCO2 | CK1: DIAS ADICIONALES CHIQUICAMATA | CL1: BONO PARTICIPACION CHIQUI
A2: 1 | B2: 9187205-6 | C2: 9187205 | D2: HERRERA | E2: VERA | F2: OSCAR CRISTIAN | G2: GERENTE DE PROYECTOS | H2: 45676 | I2: I | J2: M | K2: 4X3 | L2: 1790000088 | M2: 1 | N2: 1 | O2: 3 | P2: 3 | Q2: 3 | R2: 1 | S2: 1 | T2: 1 | U2: 1 | V2: 3 | W2: 3 | X2: 3 | Y2: 1 | Z2: 1 | AA2: 1 | AB2: 1 | AC2: 3 | AD2: 3 | AE2: 3 | AF2: 1 | AG2: 1 | AH2: 1 | AI2: 1 | AJ2: 3 | AK2: 3 | AL2: 3 | AM2: 1 | AN2: 1 | AO2: 1 | AP2: 1 | AR2: 18 | AS2: 0 | AT2: 12 | AU2: 0 | AV2: 0 | AW2: 0 | AX2: 0 | AY2: 0 | AZ2: 0 | BA2: 30 | BE2: 328000 | BF2: Bono para llegar a sueldo pactado | BM2: 0
A3: 2 | B3: 9460969-0 | C3: 9460969 | D3: ARANDA | E3: CAQUEO | F3: LUIS ALFONSO | G3: EXPEDITOR | H3: 45712 | I3: I | J3: M | K3: A | L3: 1790000088 | M3: 1 | N3: 3 | O3: 3 | P3: 3 | AR3: 1 | AS3: 0 | AT3: 3 | AU3: 0 | AV3: 0 | AW3: 0 | AX3: 0 | AY3: 0 | AZ3: 0 | BA3: 4 | BC3: 193599 | BD3: Corresponde a dia pend. Cambio jornada 4x3 transición. | BE3: 33333.333 | BF3: para ajustar sueldo pactado a 1.700.000.- | BM3: 0 | BP3: 75000
A4: 3 | B4: 10420797-9 | C4: 10420797 | D4: IRRIBARRA | E4: PEÑA | F4: HECTOR LEONIDAS | G4: JEFE RECURSOS HUMANOS PROYECTO | H4: 45704 | I4: I | J4: M | K4: 4X3 | L4: 1790000088 | M4: 1 | N4: 1 | O4: 3 | P4: 3 | Q4: 3 | R4: 1 | S4: 1 | T4: 1 | U4: 1 | V4: 3 | W4: 3 | X4: 3 | Y4: 1 | Z4: 1 | AA4: 1 | AB4: 1 | AC4: 3 | AD4: 3 | AE4: 3 | AF4: 1 | AG4: 1 | AH4: 1 | AI4: 1 | AJ4: 3 | AK4: 3 | AL4: 3 | AM4: 1 | AN4: 1 | AO4: 1 | AP4: 1 | AR4: 18 | AS4: 0 | AT4: 12 | AU4: 0 | AV4: 0 | AW4: 0 | AX4: 0 | AY4: 0 | AZ4: 0 | BA4: 30 | BC4: 230799 | BD4: 3 DIAS DESCANSO MAYO-26 | BM4: 0 | CA4: 72000 | CB4: PAGO TRASLADO ALIMENTACION DIC-ENERO-ESPAÑA A TOKY EN EFECTIVO
A5: 4 | B5: 10603186-K | C5: 10603186 | D5: LEON | E5: OLEA | F5: JAIME ANTONIO | G5: TECNICO RECURSOS HUMANOS PROYECTO | H5: 45748 | I5: I | J5: M | K5: A | L5: 1790000088 | M5: 1 | N5: 1 | O5: 3 | P5: 3 | Q5: 3 | R5: 1 | S5: 1 | T5: 1 | U5: 1 | V5: 3 | W5: 3 | X5: 3 | Y5: 1 | Z5: 1 | AA5: 1 | AB5: 1 | AC5: 3 | AD5: 3 | AE5: 3 | AF5: 1 | AG5: 1 | AH5: 1 | AI5: 1 | AJ5: 3 | AK5: 3 | AL5: 3 | AM5: 1 | AN5: 1 | AO5: 1 | AP5: 1 | AR5: 18 | AS5: 0 | AT5: 12 | AU5: 0 | AV5: 0 | AW5: 0 | AX5: 0 | AY5: 0 | AZ5: 0 | BA5: 30 | BC5: 614997 | BD5: 9 DIAS DESCANSO MAYO-26 | BE5: 500000 | BF5: Realizar actividades de ADMIN. CAMPAMENTO | BM5: 0
A6: 5 | B6: 10957493-7 | C6: 10957493 | D6: GONZALEZ | E6: QUINZACARA | F6: LUIS ARNOLDO | G6: CAPATAZ GEOSINTETICOS | H6: 45809 | I6: D | J6: M | K6: B | L6: 1790000088 | M6: 3 | N6: 3 | O6: 3 | P6: 3 | Q6: 3 | R6: 3 | S6: 1 | T6: 1 | U6: 2 | V6: 2 | W6: 2 | X6: 2 | Y6: 2 | Z6: 2 | AA6: 2 | AB6: 2 | AC6: 2 | AD6: 2 | AE6: 2 | AF6: 2 | AG6: 2 | AH6: 3 | AI6: 3 | AJ6: 3 | AK6: 3 | AL6: 3 | AM6: 3 | AN6: 3 | AO6: 3 | AP6: 3 | AR6: 2 | AS6: 13 | AT6: 15 | AU6: 0 | AV6: 0 | AW6: 0 | AX6: 0 | AY6: 0 | AZ6: 0 | BA6: 30 | BC6: 258335 | BD6: 5 DIAS DESCANSO MAYO-26 | BM6: 0 | BP6: 150000
A7: 6 | B7: 11265430-5 | C7: 11265430 | D7: FAUNDEZ | E7: ORTIZ | F7: CESAR HERNAN | G7: TOPÓGRAFO - NIVELADOR | H7: 45748 | I7: I | J7: M | K7: 4x3 | L7: 1790000088 | M7: 1 | N7: 1 | O7: 3 | P7: 3 | Q7: 3 | R7: 1 | S7: 1 | T7: 1 | U7: 1 | V7: 3 | W7: 3 | X7: 3 | Y7: 1 | Z7: 1 | AA7: 1 | AB7: 1 | AC7: 3 | AD7: 3 | AE7: 3 | AF7: 1 | AG7: 1 | AH7: 1 | AI7: 1 | AJ7: 3 | AK7: 3 | AL7: 3 | AM7: 1 | AN7: 1 | AO7: 1 | AP7: 1 | AR7: 18 | AS7: 0 | AT7: 12 | AU7: 0 | AV7: 0 | AW7: 0 | AX7: 0 | AY7: 0 | AZ7: 0 | BA7: 30 | BE7: 837000 | BF7: Bono asignacion de obra | BM7: 0
A8: 7 | B8: 11734191-7 | C8: 11734191 | D8: TORRES | E8: LOPEZ | F8: LUIS EDUARDO | G8: OPERADOR CAMIÓN PLUMA | H8: 45756 | I8: D | J8: M | K8: A | L8: 1790000088 | M8: 1 | N8: 1 | O8: 1 | P8: 1 | Q8: 1 | R8: 1 | S8: 1 | T8: 1 | U8: 1 | V8: 1 | W8: 1 | X8: 1 | Y8: 1 | Z8: 1 | AA8: 1 | AB8: 1 | AC8: 1 | AD8: 1 | AE8: 1 | AF8: 1 | AG8: 1 | AH8: 2 | AI8: 2 | AJ8: 2 | AK8: 2 | AL8: 2 | AM8: 2 | AN8: 2 | AO8: 2 | AP8: 2 | AR8: 21 | AS8: 9 | AT8: 0 | AU8: 0 | AV8: 0 | AW8: 0 | AX8: 0 | AY8: 0 | AZ8: 0 | BA8: 30 | BM8: 0
A9: 8 | B9: 12038137-7 | C9: 12038137 | D9: CORTES | E9: LÓPEZ | F9: MARCELO ANTONIO | G9: MAESTRO SEGUNDA GEOSINTETICOS | H9: 45924 | I9: D | J9: M | K9: B | L9: 1790000088 | M9: 1 | N9: 1 | O9: 1 | P9: 1 | Q9: 1 | R9: 1 | S9: 1 | T9: 1 | U9: 1 | V9: 1 | W9: 1 | AR9: 11 | AS9: 0 | AT9: 0 | AU9: 0 | AV9: 0 | AW9: 0 | AX9: 0 | AY9: 0 | AZ9: 0 | BA9: 11 | BM9: 0
A10: 9 | B10: 12612919-k | C10: 12612919 | D10: HERRERA | E10: CORTES | F10: JUVENAL HUMBERTO | G10: AYUDANTE GEOSINTETICOS | H10: 45858 | I10: D | J10: M | K10: A | L10: 1790000088 | M10: 2 | N10: 2 | O10: 8 | P10: 8 | Q10: 2 | R10: 2 | S10: 2 | T10: 3 | U10: 3 | V10: 3 | W10: 3 | X10: 3 | Y10: 3 | Z10: 3 | AA10: 3 | AB10: 3 | AC10: 3 | AD10: 3 | AE10: 3 | AF10: 3 | AG10: 3 | AH10: 2 | AI10: 2 | AJ10: 2 | AK10: 2 | AL10: 2 | AM10: 2 | AN10: 2 | AO10: 2 | AP10: 2 | AR10: 0 | AS10: 14 | AT10: 14 | AU10: 0 | AV10: 0 | AW10: 0 | AX10: 0 | AY10: 2 | AZ10: 0 | BA10: 30 | BC10: 223803 | BD10: 9 DIAS DESCANSO MAYO-26 | BM10: 2 | BN10: 149200 | BP10: 150000
A11: 10 | B11: 13076470-3 | C11: 13076470 | D11: REHBEIN | E11: GANTES | F11: ANTONIO ALEJANDRO | G11: JEFE DE TERRENO | H11: 45805 | I11: I | J11: M | K11: B | L11: 1790000088 | M11: 3 | N11: 3 | O11: 3 | P11: 3 | Q11: 3 | R11: 3 | S11: 3 | T11: 2 | U11: 2 | V11: 2 | W11: 2 | X11: 2 | Y11: 1 | Z11: 1 | AA11: 2 | AB11: 2 | AC11: 2 | AD11: 2 | AE11: 2 | AF11: 2 | AG11: 2 | AH11: 3 | AI11: 3 | AJ11: 3 | AK11: 3 | AL11: 3 | AM11: 3 | AN11: 3 | AO11: 3 | AP11: 3 | AR11: 2 | AS11: 12 | AT11: 16 | AU11: 0 | AV11: 0 | AW11: 0 | AX11: 0 | AY11: 0 | AZ11: 0 | BA11: 30 | BC11: 598335 | BD11: 5 DIAS DESCANSO MAYO-26 | BE11: 375000 | BF11: Bono ajuste salarial | BM11: 0
A12: 11 | B12: 13172993-6 | C12: 13172993 | D12: GODOY | E12: CORTES | F12: SANDRA ROSARIO | G12: ADMINISTRATIVO OFICINA TECNICA | H12: 45839 | I12: I | J12: F | K12: 4X3 | L12: 1790000088 | M12: 1 | N12: 3 | O12: 3 | P12: 3 | AR12: 1 | AS12: 0 | AT12: 3 | AU12: 0 | AV12: 0 | AW12: 0 | AX12: 0 | AY12: 0 | AZ12: 0 | BA12: 4 | BM12: 0
A13: 12 | B13: 13174740-3 | C13: 13174740 | D13: ROJAS | E13: GERALDO | F13: EUGENIO DAVID | G13: MAESTRO SEGUNDA GEOSINTETICOS | H13: 45846 | I13: D | J13: M | K13: B | L13: 1790000088 | M13: 3 | N13: 3 | O13: 3 | P13: 3 | Q13: 3 | R13: 3 | S13: 3 | T13: 2 | U13: 2 | V13: 2 | W13: 2 | X13: 2 | Y13: 2 | Z13: 2 | AA13: 2 | AB13: 2 | AC13: 2 | AD13: 2 | AE13: 2 | AF13: 2 | AG13: 2 | AH13: 3 | AI13: 3 | AJ13: 3 | AK13: 3 | AL13: 3 | AM13: 3 | AN13: 3 | AO13: 3 | AP13: 3 | AR13: 0 | AS13: 14 | AT13: 16 | AU13: 0 | AV13: 0 | AW13: 0 | AX13: 0 | AY13: 0 | AZ13: 0 | BA13: 30 | BC13: 141665 | BD13: 5 DIAS DESCANSO MAYO-26 | BM13: 0 | BP13: 150000
A14: 13 | B14: 13531208-8 | C14: 13531208 | D14: ARAYA | E14: REYES | F14: MARCO ANTONIO | G14: JEFE PREVENCIÓN DE RIESGOS | H14: 45689 | I14: I | J14: M | K14: 4X3 | L14: 1790000088 | M14: 1 | N14: 1 | O14: 3 | P14: 3 | Q14: 3 | R14: 1 | S14: 1 | T14: 1 | U14: 1 | V14: 3 | W14: 3 | X14: 3 | Y14: 1 | Z14: 1 | AA14: 1 | AB14: 1 | AC14: 3 | AD14: 3 | AE14: 3 | AF14: 1 | AG14: 1 | AH14: 1 | AI14: 1 | AJ14: 3 | AK14: 3 | AL14: 3 | AM14: 1 | AN14: 1 | AO14: 1 | AP14: 1 | AR14: 18 | AS14: 0 | AT14: 12 | AU14: 0 | AV14: 0 | AW14: 0 | AX14: 0 | AY14: 0 | AZ14: 0 | BA14: 30 | BE14: 1634000 | BF14: Bono para llegar a monto asignado | BM14: 0 | CE14: 77281
A15: 14 | B15: 13702938-3 | C15: 13702938 | D15: VEGA | E15: GUERRERO | F15: VICTOR ANDRES | G15: SUPERVISOR GEOSINTETICOS | H15: 45702 | I15: I | J15: M | K15: A | L15: 1790000088 | M15: 2 | N15: 2 | O15: 8 | P15: 8 | Q15: 2 | R15: 2 | S15: 2 | T15: 3 | U15: 3 | V15: 3 | W15: 3 | X15: 3 | Y15: 3 | Z15: 3 | AA15: 3 | AB15: 3 | AC15: 3 | AD15: 3 | AE15: 3 | AF15: 3 | AG15: 3 | AH15: 2 | AI15: 2 | AJ15: 2 | AK15: 2 | AL15: 2 | AM15: 2 | AN15: 2 | AO15: 2 | AP15: 2 | AR15: 0 | AS15: 14 | AT15: 14 | AU15: 0 | AV15: 0 | AW15: 0 | AX15: 0 | AY15: 2 | AZ15: 0 | BA15: 30 | BC15: 732303 | BD15: 9 DIAS DESCANSO MAYO-26 | BM15: 2 | BN15: 488018 | BP15: 150000
A16: 15 | B16: 15018611-0 | C16: 15018611 | D16: GUERRA | E16: YAPOR | F16: JORGE ANDRES | G16: SUBGERENTE CONTRATOS Y SERVICIOS | H16: 45689 | I16: I | J16: M | K16: 4X3 | L16: 1790000088 | M16: 1 | N16: 1 | O16: 3 | P16: 3 | Q16: 3 | R16: 1 | S16: 1 | T16: 1 | U16: 1 | V16: 3 | W16: 3 | X16: 3 | Y16: 1 | Z16: 1 | AA16: 1 | AB16: 1 | AC16: 3 | AD16: 3 | AE16: 3 | AF16: 1 | AG16: 1 | AH16: 1 | AI16: 1 | AJ16: 3 | AK16: 3 | AL16: 3 | AM16: 1 | AN16: 1 | AO16: 1 | AP16: 1 | AR16: 18 | AS16: 0 | AT16: 12 | AU16: 0 | AV16: 0 | AW16: 0 | AX16: 0 | AY16: 0 | AZ16: 0 | BA16: 30 | BB16: 1508437 | BM16: 0 | CA16: 180000 | CB16: Gastos aseo depa
A17: 16 | B17: 15036703-4 | C17: 15036703 | D17: RIVERA | E17: ROJAS | F17: JORGE NIBALDO | G17: JEFE DE TERRENO | H17: 45704 | I17: I | J17: M | K17: A | L17: 1790000088 | M17: 2 | N17: 2 | O17: 8 | P17: 8 | Q17: 2 | R17: 2 | S17: 2 | T17: 3 | U17: 3 | V17: 3 | W17: 3 | X17: 3 | Y17: 3 | Z17: 3 | AA17: 3 | AB17: 3 | AC17: 3 | AD17: 3 | AE17: 3 | AF17: 3 | AG17: 3 | AH17: 2 | AI17: 2 | AJ17: 2 | AK17: 2 | AL17: 2 | AM17: 2 | AN17: 2 | AO17: 2 | AP17: 2 | AR17: 0 | AS17: 14 | AT17: 14 | AU17: 0 | AV17: 0 | AW17: 0 | AX17: 0 | AY17: 2 | AZ17: 0 | BA17: 30 | BC17: 1077003 | BD17: 9 DIAS DESCANSO MAYO-26 | BM17: 2 | BN17: 717998
A18: 17 | B18: 15356694-1 | C18: 15356694 | D18: AYALA | E18: VENEGAS | F18: RAÚL EDUARDO | G18: RIGGER | H18: 45823 | I18: D | J18: M | K18: B | L18: 1790000088 | M18: 3 | N18: 3 | O18: 3 | P18: 3 | Q18: 3 | R18: 3 | S18: 3 | T18: 1 | U18: 1 | V18: 1 | W18: 1 | X18: 1 | Y18: 1 | Z18: 1 | AA18: 1 | AB18: 1 | AC18: 1 | AD18: 1 | AE18: 1 | AF18: 1 | AG18: 1 | AH18: 3 | AI18: 3 | AJ18: 3 | AK18: 3 | AL18: 3 | AM18: 3 | AN18: 3 | AO18: 3 | AP18: 3 | AR18: 14 | AS18: 0 | AT18: 16 | AU18: 0 | AV18: 0 | AW18: 0 | AX18: 0 | AY18: 0 | AZ18: 0 | BA18: 30 | BM18: 0 | BP18: 150000
A19: 18 | B19: 15684747-k | C19: 15684747 | D19: GONZALEZ | E19: TAPIA | F19: SARA NOEMI | G19: JEFE DE CALIDAD | H19: 45748 | I19: I | J19: F | K19: 4X3 | L19: 1790000088 | M19: 1 | N19: 1 | O19: 3 | P19: 3 | Q19: 3 | R19: 1 | S19: 1 | T19: 1 | U19: 1 | V19: 3 | W19: 3 | X19: 3 | Y19: 1 | Z19: 1 | AA19: 1 | AB19: 1 | AC19: 8 | AD19: 3 | AE19: 3 | AF19: 1 | AG19: 1 | AH19: 1 | AI19: 1 | AJ19: 3 | AK19: 3 | AL19: 3 | AM19: 1 | AN19: 1 | AO19: 1 | AP19: 1 | AR19: 18 | AS19: 0 | AT19: 11 | AU19: 0 | AV19: 0 | AW19: 0 | AX19: 0 | AY19: 1 | AZ19: 0 | BA19: 30 | BE19: 1634000 | BF19: Bono para llegar a monto asignado | BM19: 1 | BN19: 171299 | CE19: 77281
A20: 19 | B20: 15969632-4 | C20: 15969632 | D20: ARROUCH | E20: MOLINA | F20: EDUARDO ANDRES | G20: OPERADOR CAMIÓN PLUMA | H20: 45824 | I20: D | J20: M | K20: B | L20: 1790000088 | M20: 3 | N20: 3 | O20: 3 | P20: 3 | Q20: 3 | R20: 3 | S20: 3 | T20: 1 | U20: 1 | V20: 1 | W20: 1 | X20: 1 | Y20: 1 | Z20: 1 | AA20: 1 | AB20: 1 | AC20: 1 | AD20: 1 | AE20: 1 | AF20: 1 | AG20: 1 | AH20: 3 | AI20: 3 | AJ20: 3 | AK20: 3 | AL20: 3 | AM20: 3 | AN20: 3 | AO20: 3 | AP20: 3 | AR20: 14 | AS20: 0 | AT20: 16 | AU20: 0 | AV20: 0 | AW20: 0 | AX20: 0 | AY20: 0 | AZ20: 0 | BA20: 30 | BM20: 0 | BP20: 150000
A21: 20 | B21: 15980010-5 | C21: 15980010 | D21: CORTES | E21: SOTO | F21: MARIO HERNAN | G21: SUPERVISOR CONTROL CALIDAD | H21: 45704 | I21: I | J21: M | K21: A | L21: 1790000088 | M21: 2 | N21: 2 | O21: 8 | P21: 8 | Q21: 2 | R21: 2 | S21: 2 | T21: 3 | U21: 3 | V21: 3 | W21: 3 | X21: 3 | Y21: 3 | Z21: 3 | AA21: 3 | AB21: 3 | AC21: 3 | AD21: 3 | AE21: 3 | AF21: 3 | AG21: 3 | AH21: 2 | AI21: 2 | AJ21: 2 | AK21: 2 | AL21: 2 | AM21: 2 | AN21: 2 | AO21: 2 | AP21: 2 | AR21: 0 | AS21: 14 | AT21: 14 | AU21: 0 | AV21: 0 | AW21: 0 | AX21: 0 | AY21: 2 | AZ21: 0 | BA21: 30 | BC21: 692397 | BD21: 9 DIAS DESCANSO MAYO-26 | BM21: 2 | BN21: 461598
A22: 21 | B22: 16054274-8 | C22: 16054274 | D22: MAYORGA | E22: ARCOS | F22: CARLOS MANUEL | G22: TECNICO CONTROL CALIDAD | H22: 45889 | I22: D | J22: M | K22: B | L22: 1790000088 | M22: 3 | N22: 3 | O22: 3 | P22: 3 | Q22: 3 | R22: 3 | S22: 3 | T22: 2 | U22: 2 | V22: 2 | W22: 2 | X22: 2 | Y22: 2 | Z22: 2 | AA22: 2 | AB22: 2 | AC22: 2 | AD22: 2 | AE22: 2 | AF22: 2 | AG22: 2 | AH22: 3 | AI22: 3 | AJ22: 3 | AK22: 3 | AL22: 3 | AM22: 3 | AN22: 3 | AO22: 3 | AP22: 3 | AR22: 0 | AS22: 14 | AT22: 16 | AU22: 0 | AV22: 0 | AW22: 0 | AX22: 0 | AY22: 0 | AZ22: 0 | BA22: 30 | BC22: 219165 | BD22: 5 DIAS DESCANSO MAYO-26 | BM22: 0 | BP22: 150000
A23: 22 | B23: 16055086-4 | C23: 16055086 | D23: CÁCERES | E23: OGALDE | F23: SEBASTIAN LORENZO | G23: TECNICO INSPECTOR Y DETECTOR DE FUGAS | H23: 45820 | I23: D | J23: M | K23: A | L23: 1790000088 | M23: 2 | N23: 2 | O23: 8 | P23: 8 | Q23: 2 | R23: 2 | S23: 1 | T23: 3 | U23: 3 | V23: 3 | W23: 3 | X23: 3 | Y23: 3 | Z23: 3 | AA23: 3 | AB23: 3 | AC23: 3 | AD23: 3 | AE23: 3 | AF23: 3 | AG23: 3 | AH23: 2 | AI23: 2 | AJ23: 2 | AK23: 2 | AL23: 2 | AM23: 2 | AN23: 2 | AO23: 2 | AP23: 2 | AR23: 1 | AS23: 13 | AT23: 14 | AU23: 0 | AV23: 0 | AW23: 0 | AX23: 0 | AY23: 2 | AZ23: 0 | BA23: 30 | BC23: 394497 | BD23: 9 DIAS DESCANSO MAYO-26 | BM23: 2 | BN23: 170000 | BP23: 150000
A24: 23 | B24: 16352344-2 | C24: 16352344 | D24: MUÑOZ | E24: ABARCA | F24: JIMMY ALEJANDRO | G24: MAESTRO SEGUNDA GEOSINTETICOS | H24: 45839 | I24: D | J24: M | K24: A | L24: 1790000088 | M24: 2 | N24: 2 | O24: 8 | P24: 8 | Q24: 2 | R24: 2 | S24: 2 | T24: 3 | U24: 3 | V24: 3 | W24: 3 | X24: 3 | Y24: 3 | Z24: 3 | AA24: 3 | AB24: 3 | AC24: 3 | AD24: 3 | AE24: 3 | AF24: 3 | AG24: 3 | AH24: 2 | AI24: 2 | AJ24: 2 | AK24: 2 | AL24: 2 | AM24: 2 | AN24: 2 | AO24: 2 | AP24: 2 | AR24: 0 | AS24: 14 | AT24: 14 | AU24: 0 | AV24: 0 | AW24: 0 | AX24: 0 | AY24: 2 | AZ24: 0 | BA24: 30 | BC24: 254997 | BD24: 9 DIAS DESCANSO MAYO-26 | BM24: 2 | BN24: 170000 | BP24: 150000
A25: 24 | B25: 16401293-k | C25: 16401293 | D25: ABARCA | E25: TUDESCA | F25: LEANDRO ISAAC | G25: MAESTRO PRIMERA GEOSINTETICOS | H25: 45846 | I25: D | J25: M | K25: B | L25: 1790000088 | M25: 3 | N25: 3 | O25: 3 | P25: 3 | Q25: 3 | R25: 3 | S25: 3 | T25: 2 | U25: 2 | V25: 2 | W25: 2 | X25: 2 | Y25: 2 | Z25: 2 | AA25: 2 | AB25: 2 | AC25: 2 | AD25: 2 | AE25: 2 | AF25: 2 | AG25: 2 | AH25: 3 | AI25: 3 | AJ25: 3 | AK25: 3 | AL25: 3 | AM25: 3 | AN25: 3 | AO25: 3 | AP25: 3 | AR25: 0 | AS25: 14 | AT25: 16 | AU25: 0 | AV25: 0 | AW25: 0 | AX25: 0 | AY25: 0 | AZ25: 0 | BA25: 30 | BC25: 219165 | BD25: 5 DIAS DESCANSO MAYO-26 | BM25: 0 | BP25: 150000
A26: 25 | B26: 16407359-9 | C26: 16407359 | D26: GARRIDO | E26: ARRATIA | F26: JONATHAN VICTOR | G26: AYUDANTE GEOSINTETICOS | H26: 45846 | I26: D | J26: M | K26: B | L26: 1790000088 | M26: 1 | N26: 1 | O26: 1 | P26: 1 | Q26: 1 | R26: 1 | S26: 1 | T26: 1 | U26: 1 | V26: 1 | W26: 1 | AR26: 11 | AS26: 0 | AT26: 0 | AU26: 0 | AV26: 0 | AW26: 0 | AX26: 0 | AY26: 0 | AZ26: 0 | BA26: 11 | BM26: 0
A27: 26 | B27: 16971879-2 | C27: 16971879 | D27: MESSINA | E27: TRAIPE | F27: EDUARD NASKY | G27: AYUDANTE CONTROL CALIDAD | H27: 45880 | I27: D | J27: M | K27: B | L27: 1790000088 | M27: 3 | N27: 3 | O27: 3 | P27: 3 | Q27: 3 | R27: 3 | S27: 3 | T27: 2 | U27: 2 | V27: 2 | W27: 2 | X27: 2 | Y27: 2 | Z27: 2 | AA27: 2 | AB27: 2 | AC27: 2 | AD27: 2 | AE27: 2 | AF27: 2 | AG27: 2 | AH27: 3 | AI27: 3 | AJ27: 3 | AK27: 3 | AL27: 3 | AM27: 3 | AN27: 3 | AO27: 3 | AP27: 3 | AR27: 0 | AS27: 14 | AT27: 16 | AU27: 0 | AV27: 0 | AW27: 0 | AX27: 0 | AY27: 0 | AZ27: 0 | BA27: 30 | BC27: 141665 | BD27: 5 DIAS DESCANSO MAYO-26 | BE27: 250000 | BF27: bono innovacheck( correo) | BM27: 0 | BP27: 150000
A28: 27 | B28: 17003626-3 | C28: 17003626 | D28: MANSILLA | E28: MANSILLA | F28: GONZALO ANTONIO | G28: TECNICO CONTROL CALIDAD | H28: 45839 | I28: D | J28: M | K28: A | L28: 1790000088 | M28: 2 | N28: 2 | O28: 8 | P28: 8 | Q28: 2 | R28: 2 | S28: 2 | T28: 3 | U28: 3 | V28: 3 | W28: 3 | X28: 3 | Y28: 3 | Z28: 3 | AA28: 3 | AB28: 3 | AC28: 3 | AD28: 3 | AE28: 3 | AF28: 3 | AG28: 3 | AH28: 2 | AI28: 2 | AJ28: 2 | AK28: 2 | AL28: 2 | AM28: 2 | AN28: 2 | AO28: 2 | AP28: 2 | AR28: 0 | AS28: 14 | AT28: 14 | AU28: 0 | AV28: 0 | AW28: 0 | AX28: 0 | AY28: 2 | AZ28: 0 | BA28: 30 | BC28: 394497 | BD28: 9 DIAS DESCANSO MAYO-26 | BM28: 2 | BN28: 262998 | BP28: 150000
A29: 28 | B29: 17028472-0 | C29: 17028472 | D29: CAMPOS | E29: MORA | F29: MAURICIO ANDRES | G29: CAPATAZ INSPECCION Y DETECCION DE FUGAS | H29: 45820 | I29: D | J29: M | K29: 4X3 | L29: 1790000088 | M29: 1 | N29: 1 | O29: 3 | P29: 3 | Q29: 3 | R29: 1 | S29: 1 | T29: 1 | U29: 1 | V29: 3 | W29: 3 | X29: 3 | Y29: 1 | Z29: 1 | AA29: 1 | AB29: 1 | AC29: 3 | AD29: 3 | AE29: 3 | AF29: 1 | AG29: 1 | AH29: 1 | AI29: 1 | AJ29: 3 | AK29: 3 | AL29: 3 | AM29: 1 | AN29: 1 | AO29: 1 | AP29: 1 | AR29: 18 | AS29: 0 | AT29: 12 | AU29: 0 | AV29: 0 | AW29: 0 | AX29: 0 | AY29: 0 | AZ29: 0 | BA29: 30 | BC29: 155001 | BD29: 3 DIAS DESCANSO MAYO-26 | BM29: 0 | BP29: 150000
A30: 29 | B30: 17193572-5 | C30: 17193572 | D30: PEREZ | E30: PEREZ | F30: INGRID TAMARA | G30: ASESOR EN PREVENCIÓN DE RIESGOS | H30: 46047 | I30: I | J30: F | K30: B | L30: 1790000088 | M30: 3 | N30: 3 | O30: 3 | P30: 3 | Q30: 3 | R30: 3 | S30: 3 | T30: 2 | U30: 2 | V30: 2 | W30: 2 | X30: 2 | Y30: 2 | Z30: 2 | AA30: 2 | AB30: 2 | AC30: 2 | AD30: 2 | AE30: 2 | AF30: 2 | AG30: 2 | AH30: 3 | AI30: 3 | AJ30: 3 | AK30: 3 | AL30: 3 | AM30: 3 | AN30: 3 | AO30: 3 | AP30: 3 | AR30: 0 | AS30: 14 | AT30: 16 | AU30: 0 | AV30: 0 | AW30: 0 | AX30: 0 | AY30: 0 | AZ30: 0 | BA30: 30 | BC30: 373835 | BD30: 5 DIAS DESCANSO MAYO-26 | BM30: 0
A31: 30 | B31: 17331556-2 | C31: 17331556 | D31: AVILÉS | E31: MATCOVICH | F31: CLAUDIO FAVIÁN | G31: SUPERVISOR CONTROL CALIDAD | H31: 45798 | I31: I | J31: M | K31: B | L31: 1790000088 | M31: 3 | N31: 3 | O31: 3 | P31: 3 | Q31: 3 | R31: 3 | S31: 1 | T31: 2 | U31: 2 | V31: 2 | W31: 2 | X31: 2 | Y31: 2 | Z31: 2 | AA31: 2 | AB31: 2 | AC31: 2 | AD31: 2 | AE31: 2 | AF31: 2 | AG31: 2 | AH31: 3 | AI31: 3 | AJ31: 3 | AK31: 3 | AL31: 3 | AM31: 3 | AN31: 3 | AO31: 3 | AP31: 3 | AR31: 1 | AS31: 14 | AT31: 15 | AU31: 0 | AV31: 0 | AW31: 0 | AX31: 0 | AY31: 0 | AZ31: 0 | BA31: 30 | BC31: 384665 | BD31: 5 DIAS DESCANSO MAYO-26 | BM31: 0
A32: 31 | B32: 17499645-8 | C32: 17499645 | D32: ALVAREZ | E32: VEAS | F32: RODRIGO EBENEZER | G32: TECNICO CONTROL DOCUMENTOS | H32: 45689 | I32: I | J32: M | K32: 4X3 | L32: 1790000088 | M32: 1 | N32: 1 | O32: 3 | P32: 3 | Q32: 3 | R32: 1 | S32: 1 | T32: 1 | U32: 1 | V32: 3 | W32: 3 | X32: 3 | Y32: 1 | Z32: 1 | AA32: 1 | AB32: 1 | AC32: 3 | AD32: 3 | AE32: 3 | AF32: 1 | AG32: 1 | AH32: 1 | AI32: 1 | AJ32: 3 | AK32: 3 | AL32: 3 | AM32: 1 | AN32: 1 | AO32: 1 | AP32: 1 | AR32: 18 | AS32: 0 | AT32: 12 | AU32: 0 | AV32: 0 | AW32: 0 | AX32: 0 | AY32: 0 | AZ32: 0 | BA32: 30 | BE32: 338000 | BF32: Bono por asignacion de obra | BG32: 312500 | BH32: Bono por liderar Geomemb | BM32: 0
A33: 32 | B33: 17641049-3 | C33: 17641049 | D33: IRRIBARRA | E33: TRONCOSO | F33: CRISTOPHER ANDRES | G33: CONDUCTOR DE SERVICIO | H33: 45815 | I33: I | J33: M | K33: A | L33: 1790000088 | M33: 1 | N33: 1 | O33: 1 | P33: 1 | Q33: 1 | R33: 1 | S33: 1 | T33: 1 | U33: 1 | V33: 1 | W33: 1 | X33: 1 | Y33: 1 | Z33: 1 | AA33: 1 | AB33: 1 | AC33: 1 | AD33: 1 | AE33: 1 | AF33: 1 | AG33: 1 | AH33: 2 | AI33: 2 | AJ33: 2 | AK33: 2 | AL33: 2 | AM33: 2 | AN33: 2 | AO33: 2 | AP33: 2 | AR33: 21 | AS33: 9 | AT33: 0 | AU33: 0 | AV33: 0 | AW33: 0 | AX33: 0 | AY33: 0 | AZ33: 0 | BA33: 30 | BC33: 370197 | BD33: 9 DIAS DESCANSO MAYO-26 | BM33: 0 | BP33: 75000
A34: 33 | B34: 17773864-6 | C34: 17773864 | D34: CARVAJAL | E34: CISTERNAS | F34: CLAUDIO ANDRES | G34: SUPERVISOR GEOSINTETICOS | H34: 45931 | I34: I | J34: M | K34: B | L34: 1790000088 | M34: 3 | N34: 3 | O34: 3 | P34: 3 | Q34: 3 | R34: 3 | S34: 1 | T34: 1 | U34: 2 | V34: 2 | W34: 2 | X34: 2 | Y34: 2 | Z34: 2 | AA34: 2 | AB34: 2 | AC34: 2 | AD34: 2 | AE34: 2 | AF34: 2 | AG34: 2 | AH34: 3 | AI34: 3 | AJ34: 3 | AK34: 3 | AL34: 3 | AM34: 3 | AN34: 3 | AO34: 3 | AP34: 3 | AR34: 2 | AS34: 13 | AT34: 15 | AU34: 0 | AV34: 0 | AW34: 0 | AX34: 0 | AY34: 0 | AZ34: 0 | BA34: 30 | BC34: 406835 | BD34: 5 DIAS DESCANSO MAYO-26 | BM34: 0 | CE34: 117625
A35: 34 | B35: 18055189-1 | C35: 18055189 | D35: ESPINOZA | E35: MEDINA | F35: RICARDO IGNACIO | G35: CAPATAZ INSPECCION Y DETECCION DE FUGAS | H35: 45824 | I35: D | J35: M | K35: 4X3 | L35: 1790000088 | M35: 2 | N35: 2 | O35: 8 | P35: 8 | Q35: 2 | R35: 2 | S35: 2 | T35: 3 | U35: 3 | V35: 3 | W35: 3 | X35: 3 | Y35: 3 | Z35: 3 | AA35: 3 | AB35: 3 | AC35: 3 | AD35: 3 | AE35: 3 | AF35: 3 | AG35: 3 | AH35: 2 | AI35: 2 | AJ35: 2 | AK35: 2 | AL35: 2 | AM35: 2 | AN35: 2 | AO35: 2 | AP35: 2 | AR35: 0 | AS35: 14 | AT35: 14 | AU35: 0 | AV35: 0 | AW35: 0 | AX35: 0 | AY35: 2 | AZ35: 0 | BA35: 30 | BC35: 394497 | BD35: 9 DIAS DESCANSO MAYO-26 | BM35: 2 | BN35: 309998 | BP35: 150000
A36: 35 | B36: 18255837-0 | C36: 18255837 | D36: ABARCA | E36: TUDESCA | F36: CHRISTIAN DAVID | G36: CAPATAZ GEOSINTETICOS | H36: 45758 | I36: D | J36: M | K36: A | L36: 1790000088 | M36: 2 | N36: 2 | O36: 8 | P36: 8 | Q36: 2 | R36: 2 | S36: 2 | T36: 3 | U36: 3 | V36: 3 | W36: 3 | X36: 3 | Y36: 3 | Z36: 3 | AA36: 3 | AB36: 3 | AC36: 3 | AD36: 3 | AE36: 3 | AF36: 3 | AG36: 3 | AH36: 2 | AI36: 2 | AJ36: 2 | AK36: 2 | AL36: 2 | AM36: 2 | AN36: 2 | AO36: 2 | AP36: 2 | AR36: 0 | AS36: 14 | AT36: 14 | AU36: 0 | AV36: 0 | AW36: 0 | AX36: 0 | AY36: 2 | AZ36: 0 | BA36: 30 | BC36: 465003 | BD36: 9 DIAS DESCANSO MAYO-26 | BM36: 2 | BN36: 309998 | BP36: 150000
A37: 36 | B37: 18317023-6 | C37: 18317023 | D37: ROJAS | E37: ZEPEDA | F37: FELIPE ALEJANDRO | G37: AYUDANTE GEOSINTETICOS | H37: 45962 | I37: D | J37: M | K37: B | L37: 1790000088 | M37: 3 | N37: 3 | O37: 3 | P37: 3 | Q37: 3 | R37: 3 | S37: 3 | T37: 2 | U37: 2 | V37: 2 | W37: 2 | X37: 2 | Y37: 2 | Z37: 2 | AA37: 2 | AB37: 2 | AC37: 2 | AD37: 2 | AE37: 2 | AF37: 2 | AG37: 2 | AH37: 3 | AI37: 3 | AJ37: 3 | AK37: 3 | AL37: 3 | AM37: 3 | AN37: 3 | AO37: 3 | AP37: 3 | AR37: 0 | AS37: 14 | AT37: 16 | AU37: 0 | AV37: 0 | AW37: 0 | AX37: 0 | AY37: 0 | AZ37: 0 | BA37: 30 | BC37: 124335 | BD37: 5 DIAS DESCANSO MAYO-26 | BM37: 0 | BP37: 150000
A38: 37 | B38: 18840949-0 | C38: 18840949 | D38: SANDOVAL | E38: MONTERO | F38: MAXIMILIANO ANDRES | G38: OPERADOR MANIPULADOR TELESCOPICO | H38: 45962 | I38: D | J38: M | K38: B | L38: 1790000088 | M38: 1 | N38: 1 | O38: 1 | P38: 1 | AR38: 4 | AS38: 0 | AT38: 0 | AU38: 0 | AV38: 0 | AW38: 0 | AX38: 0 | AY38: 0 | AZ38: 0 | BA38: 4 | BM38: 0
A39: 38 | B39: 19099785-5 | C39: 19099785 | D39: CARVAJAL | E39: POBLETE | F39: CRISTIAN EZEQUIEL | G39: INGENIERO PMO | H39: 45754 | I39: I | J39: M | K39: 4X3 | L39: 1790000088 | M39: 1 | N39: 1 | O39: 3 | P39: 3 | Q39: 3 | R39: 1 | S39: 1 | T39: 1 | U39: 1 | V39: 3 | W39: 3 | X39: 3 | Y39: 1 | Z39: 1 | AA39: 1 | AB39: 1 | AC39: 3 | AD39: 3 | AE39: 3 | AF39: 1 | AG39: 1 | AH39: 1 | AI39: 1 | AJ39: 3 | AK39: 3 | AL39: 3 | AM39: 1 | AN39: 1 | AO39: 1 | AP39: 1 | AR39: 18 | AS39: 0 | AT39: 12 | AU39: 0 | AV39: 0 | AW39: 0 | AX39: 0 | AY39: 0 | AZ39: 0 | BA39: 30 | BM39: 0
A40: 39 | B40: 19206550-K | C40: 19206550 | D40: SALVATIERRA | E40: ALCAINO | F40: NICOLAS IGNACIO | G40: JEFE OFICINA TECNICA | H40: 45880 | I40: I | J40: M | K40: 4X3 | L40: 1790000088 | M40: 1 | N40: 3 | O40: 3 | P40: 3 | AR40: 1 | AS40: 0 | AT40: 3 | AU40: 0 | AV40: 0 | AW40: 0 | AX40: 0 | AY40: 0 | AZ40: 0 | BA40: 4 | BM40: 0
A41: 40 | B41: 19398564-5 | C41: 19398564 | D41: GIJON | E41: TELLO | F41: JAVIERA YASMINA | G41: ASESOR EN PREVENCIÓN DE RIESGOS | H41: 45712 | I41: I | J41: F | K41: A | L41: 1790000088 | M41: 2 | N41: 2 | O41: 8 | P41: 8 | Q41: 2 | R41: 2 | S41: 2 | T41: 3 | U41: 3 | V41: 3 | W41: 3 | X41: 3 | Y41: 3 | Z41: 3 | AA41: 3 | AB41: 3 | AC41: 3 | AD41: 3 | AE41: 3 | AF41: 3 | AG41: 3 | AH41: 2 | AI41: 2 | AJ41: 2 | AK41: 2 | AL41: 2 | AM41: 2 | AN41: 2 | AO41: 2 | AP41: 2 | AR41: 0 | AS41: 14 | AT41: 14 | AU41: 0 | AV41: 0 | AW41: 0 | AX41: 0 | AY41: 2 | AZ41: 0 | BA41: 30 | BC41: 614997 | BD41: 9 DIAS DESCANSO MAYO-26 | BM41: 2 | BN41: 448598
A42: 41 | B42: 19551679-0 | C42: 19551679 | D42: FLORES | E42: ARAYA | F42: MARCO ANDRES | G42: PROGRAMACION Y CONTROL | H42: 45839 | I42: I | J42: M | K42: 4X3 | L42: 1790000088 | M42: 1 | N42: 3 | O42: 3 | P42: 3 | AR42: 1 | AS42: 0 | AT42: 3 | AU42: 0 | AV42: 0 | AW42: 0 | AX42: 0 | AY42: 0 | AZ42: 0 | BA42: 4 | BM42: 0
A43: 42 | B43: 19663706-0 | C43: 19663706 | D43: CHACANA | E43: ARANGUE | F43: ESTEBAN ANDRÉS | G43: AYUDANTE GEOSINTETICOS | H43: 45820 | I43: D | J43: M | K43: A | L43: 1790000088 | M43: 1 | N43: 1 | O43: 1 | P43: 1 | Q43: 1 | R43: 1 | S43: 1 | T43: 1 | U43: 1 | V43: 1 | W43: 1 | AR43: 11 | AS43: 0 | AT43: 0 | AU43: 0 | AV43: 0 | AW43: 0 | AX43: 0 | AY43: 0 | AZ43: 0 | BA43: 11 | BM43: 0
A44: 43 | B44: 19924867-7 | C44: 19924867 | D44: REYES | E44: CASTRO | F44: JOSE IGNACIO | G44: TECNICO INSPECTOR Y DETECTOR DE FUGAS | H44: 45839 | I44: D | J44: M | K44: B | L44: 1790000088 | M44: 3 | N44: 3 | O44: 3 | P44: 3 | Q44: 3 | R44: 2 | S44: 2 | T44: 2 | U44: 2 | V44: 2 | W44: 2 | X44: 2 | Y44: 2 | Z44: 2 | AA44: 2 | AB44: 2 | AC44: 2 | AD44: 2 | AE44: 2 | AF44: 2 | AG44: 2 | AH44: 3 | AI44: 3 | AJ44: 3 | AK44: 3 | AL44: 3 | AM44: 3 | AN44: 3 | AO44: 3 | AP44: 3 | AR44: 0 | AS44: 16 | AT44: 14 | AU44: 0 | AV44: 0 | AW44: 0 | AX44: 0 | AY44: 0 | AZ44: 0 | BA44: 30 | BC44: 219165 | BD44: 5 DIAS DESCANSO MAYO-26 | BM44: 0 | BP44: 150000
A45: 44 | B45: 19967782-9 | C45: 19967782 | D45: RIVERA | E45: ARAYA | F45: IGNACIO ANDRES | G45: ALARIFE | H45: 45820 | I45: D | J45: M | K45: 4x3 | L45: 1790000088 | M45: 1 | AR45: 1 | AS45: 0 | AT45: 0 | AU45: 0 | AV45: 0 | AW45: 0 | AX45: 0 | AY45: 0 | AZ45: 0 | BA45: 1 | BM45: 0
A46: 45 | B46: 20952696-4 | C46: 20952696 | D46: CASTILLO | E46: VILLEJAS | F46: FRANCO IGNACIO PALMENIO | G46: TECNICO INSPECTOR Y DETECTOR DE FUGAS | H46: 45824 | I46: D | J46: M | K46: B | L46: 1790000088 | M46: 1 | N46: 1 | O46: 1 | P46: 1 | Q46: 1 | R46: 1 | S46: 1 | T46: 3 | U46: 3 | V46: 3 | W46: 3 | X46: 3 | Y46: 3 | Z46: 3 | AA46: 3 | AB46: 3 | AC46: 3 | AD46: 3 | AE46: 3 | AF46: 3 | AG46: 3 | AH46: 1 | AI46: 1 | AJ46: 1 | AK46: 1 | AL46: 1 | AM46: 1 | AN46: 1 | AO46: 1 | AP46: 1 | AR46: 16 | AS46: 0 | AT46: 14 | AU46: 0 | AV46: 0 | AW46: 0 | AX46: 0 | AY46: 0 | AZ46: 0 | BA46: 30 | BM46: 0 | BP46: 150000
A47: 46 | B47: 26084510-1 | C47: 26084510 | D47: MENDOZA | E47: ALTAMIRANO | F47: ALEXANDER | G47: MAESTRO PRIMERA GEOSINTETICOS | H47: 45839 | I47: D | J47: M | K47: A | L47: 1790000088 | M47: 2 | N47: 2 | O47: 8 | P47: 8 | Q47: 2 | R47: 2 | S47: 2 | T47: 3 | U47: 3 | V47: 3 | W47: 3 | X47: 3 | Y47: 3 | Z47: 3 | AA47: 3 | AB47: 3 | AC47: 3 | AD47: 3 | AE47: 3 | AF47: 3 | AG47: 3 | AH47: 2 | AI47: 2 | AJ47: 2 | AK47: 2 | AL47: 2 | AM47: 2 | AN47: 2 | AO47: 2 | AP47: 2 | AR47: 0 | AS47: 14 | AT47: 14 | AU47: 0 | AV47: 0 | AW47: 0 | AX47: 0 | AY47: 2 | AZ47: 0 | BA47: 30 | BC47: 394497 | BD47: 9 DIAS DESCANSO MAYO-26 | BM47: 2 | BN47: 262998 | BP47: 150000

Sheet 04_2026_Caserones
A1: Nº | B1: RUT (sin puntos y con guion) | C1: ID (rut sin puntos, sin guión ni digito vertificador) | D1: APELLIDO PATERNO | E1: APELLIDO MATERNO | F1: NOMBRES | G1: CARGO | H1: INICIO DE CONTRATO | I1: D/I | J1: GENERO M/F | K1: TURNO (5x2-4x3-14x14 -art22) | L1: CC | M1: 1 | N1: 2 | O1: 3 | P1: 4 | Q1: 5 | R1: 6 | S1: 7 | T1: 8 | U1: 9 | V1: 10 | W1: 11 | X1: 12 | Y1: 13 | Z1: 14 | AA1: 15 | AB1: 16 | AC1: 17 | AD1: 18 | AE1: 19 | AF1: 20 | AG1: 21 | AH1: 22 | AI1: 23 | AJ1: 24 | AK1: 25 | AL1: 26 | AM1: 27 | AN1: 28 | AO1: 29 | AP1: 30 | AQ1: 31 | AR1: (1) | AS1: (2) | AT1: (3) | AU1: (4) | AV1: (5) | AW1: (6) | AX1: (7) | AY1: (8) | AZ1: (9) | BA1: T.D.T. | BB1: 1033-Bono Gestión Variable | BC1: 1029-Bono Compensatorio descanso | BD1: Justificación Bono 10-29 (Compensatorio descanso) | BE1: 1034-Bono Incentivo variable | BF1: Justificación Bono 1034 (Incentivo variable) | BG1: 1140-Bono Responsabilidad 2 | BH1: Justificación 1140 (Bono Responsabilidad) | BI1: 1041-Bono Terreno (Exclusivo proyecto Techint-CMDIC) | BJ1: 1031-Bono Escolaridad I/T (Uso exclusivo Area de Compensaciones) | BK1: 1092-Diferencia de haber | BL1: Justificación Bono 1092 (Diferencia de Haber) | BM1: Cantidad de feriados del mes | BN1: 1082-Bono Compens. Feriado | BO1: 1020-Aguinaldo I/T | BP1: 1140-Bono de Permanencia (Plan de Beneficios) | BQ1: Bono Seguridad BESALCO-MEL | BR1: Bono Q1 (Exclusivo Collahuasi) | BS1: Bono Q2 (Exclusivo Collahuasi) | BT1: Bono Q3 (Exclusivo Collahuasi) | BU1: Bono Q4 (Exclusivo Collahuasi) | BV1: Bono RSA (Exclusivo Collahuasi) | BW1: 1044-Asignación Colación | BX1: Justificación Asignacion Colacion | BY1: 1165-Asignación Movilización 2 | BZ1: Justificación Asignación Movilización 2 | CA1: 1172-Viatico 2 | CB1: Justificación Viatico | CC1: 1073-Otras Asignaciones N/I (Beneficios) | CD1: Justificaciión de Asignación (Detalle del beneficio) | CE1: 1032-Bono Escolaridad N/I | CF1: 1124-Asignación familiar Retroactiva | CG1: Descuento por aporte voluntario | CH1: Observaciones generales | CI1: ACUERDO MARCO ACCIONA-CODELCO | CJ1: GRATIFICACION ACUERD MARCO ACCIONA-CODELCO2 | CK1: DIAS ADICIONALES CHIQUICAMATA | CL1: BONO PARTICIPACION CHIQUI
A2: 1 | B2: 14296775-8 | C2: 14296775 | D2: CORTES | E2: HINAREJO | F2: ALEXIS RODRIGO | G2: JEFE DE TERRENO | H2: 46054 | I2: I | J2: M | K2: 7X7 | L2: 1790000091 | M2: 3 | N2: 3 | O2: 3 | P2: 3 | Q2: 3 | R2: 3 | S2: 3 | T2: 2 | U2: 2 | V2: 2 | W2: 2 | X2: 2 | Y2: 2 | Z2: 2 | AA2: 3 | AB2: 3 | AC2: 3 | AD2: 3 | AE2: 3 | AF2: 3 | AG2: 3 | AH2: 2 | AI2: 2 | AJ2: 2 | AK2: 2 | AL2: 2 | AM2: 2 | AN2: 2 | AO2: 3 | AP2: 3 | AR2: 0 | AS2: 14 | AT2: 16 | AU2: 0 | AV2: 0 | AW2: 0 | AX2: 0 | AY2: 0 | AZ2: 0 | BA2: 30 | BE2: 1644000 | BF2: Bono asignación de obra | CE2: 77281
A3: 2 | B3: 17712341-2 | C3: 17712341 | D3: ARAYA | E3: ARAYA | F3: PATRICIO ESTEBAN | G3: SUPERVISOR DE CONTROL DE CALIDAD | H3: 46054 | I3: I | J3: M | K3: 7X7 | L3: 1790000091 | M3: 3 | N3: 3 | O3: 3 | P3: 3 | Q3: 3 | R3: 3 | S3: 3 | T3: 2 | U3: 2 | V3: 2 | W3: 2 | X3: 2 | Y3: 2 | Z3: 2 | AA3: 3 | AB3: 3 | AC3: 3 | AD3: 3 | AE3: 3 | AF3: 3 | AG3: 3 | AH3: 2 | AI3: 2 | AJ3: 2 | AK3: 2 | AL3: 2 | AM3: 2 | AN3: 2 | AO3: 3 | AP3: 3 | AR3: 0 | AS3: 14 | AT3: 16 | AU3: 0 | AV3: 0 | AW3: 0 | AX3: 0 | AY3: 0 | AZ3: 0 | BA3: 30 | CE3: 74406
A4: 3 | B4: 15164558-5 | C4: 15164558 | D4: SEPULVEDA | E4: VARGAS | F4: ESTEBAN ANDRES | G4: TECNICO RRHH PROYECTO | H4: 46054 | I4: I | J4: M | K4: 7X7 | L4: 1790000091 | M4: 3 | N4: 3 | O4: 8 | P4: 3 | Q4: 3 | R4: 3 | S4: 3 | T4: 2 | U4: 2 | V4: 2 | W4: 2 | X4: 2 | Y4: 2 | Z4: 2 | AA4: 3 | AB4: 3 | AC4: 3 | AD4: 3 | AE4: 3 | AF4: 3 | AG4: 3 | AH4: 2 | AI4: 2 | AJ4: 2 | AK4: 2 | AL4: 2 | AM4: 2 | AN4: 2 | AO4: 3 | AP4: 3 | AR4: 0 | AS4: 14 | AT4: 15 | AU4: 0 | AV4: 0 | AW4: 0 | AX4: 0 | AY4: 1 | AZ4: 0 | BA4: 30 | BM4: 1 | BN4: 243000
A5: 4 | B5: 18318148-3 | C5: 18318148 | D5: ROJAS | E5: ROJAS | F5: ALVARO SEBASTIAN | G5: CAPATAZ GEOSINTETICOS | H5: 46054 | I5: D | J5: M | K5: 7X7 | L5: 1790000091 | M5: 3 | N5: 3 | O5: 3 | P5: 3 | Q5: 3 | R5: 3 | S5: 3 | T5: 2 | U5: 2 | V5: 2 | W5: 2 | X5: 2 | Y5: 2 | Z5: 2 | AA5: 3 | AB5: 3 | AC5: 3 | AD5: 3 | AE5: 3 | AF5: 3 | AG5: 3 | AH5: 2 | AI5: 2 | AJ5: 2 | AK5: 2 | AL5: 2 | AM5: 2 | AN5: 2 | AO5: 3 | AP5: 3 | AR5: 0 | AS5: 14 | AT5: 16 | AU5: 0 | AV5: 0 | AW5: 0 | AX5: 0 | AY5: 0 | AZ5: 0 | BA5: 30
A6: 5 | B6: 20600125-9 | C6: 20600125 | D6: RODRIGUEZ | E6: OLATE | F6: FELIPE ANDRES | G6: MAESTRO PRIMERA GEOSINTETICO | H6: 46068 | I6: D | J6: M | K6: 7X7 | L6: 1790000091 | M6: 3 | N6: 3 | O6: 3 | P6: 3 | Q6: 3 | R6: 3 | S6: 3 | T6: 2 | U6: 2 | V6: 2 | W6: 2 | X6: 2 | Y6: 2 | Z6: 2 | AA6: 3 | AB6: 3 | AC6: 3 | AD6: 3 | AE6: 3 | AF6: 3 | AG6: 3 | AH6: 2 | AI6: 2 | AJ6: 2 | AK6: 2 | AL6: 2 | AM6: 2 | AN6: 2 | AO6: 3 | AP6: 3 | AR6: 0 | AS6: 14 | AT6: 16 | AU6: 0 | AV6: 0 | AW6: 0 | AX6: 0 | AY6: 0 | AZ6: 0 | BA6: 30
A7: 6 | B7: 17131650-2 | C7: 17131650 | D7: BRIZUELA | E7: FUENTE | F7: FRANCISCO EDUARDO | G7: AYUDANTE GEOSINTETICOS | H7: 46068 | I7: D | J7: M | K7: 7X7 | L7: 1790000091 | M7: 3 | N7: 3 | O7: 3 | P7: 3 | Q7: 3 | R7: 3 | S7: 3 | T7: 2 | U7: 2 | V7: 2 | W7: 2 | X7: 2 | Y7: 2 | Z7: 2 | AA7: 3 | AB7: 3 | AC7: 3 | AD7: 3 | AE7: 3 | AF7: 3 | AG7: 3 | AH7: 2 | AI7: 2 | AJ7: 2 | AK7: 2 | AL7: 2 | AM7: 2 | AN7: 2 | AO7: 3 | AP7: 3 | AR7: 0 | AS7: 14 | AT7: 16 | AU7: 0 | AV7: 0 | AW7: 0 | AX7: 0 | AY7: 0 | AZ7: 0 | BA7: 30
A8: 7 | B8: 16110209-1 | C8: 16110209 | D8: GUAJARDO | E8: SALAS | F8: CRISTIAN LENIER | G8: OPERADOR CAMION PLUMA | H8: 46063 | I8: D | J8: M | K8: 7X7 | L8: 1790000091 | M8: 3 | N8: 3 | O8: 3 | P8: 3 | Q8: 3 | R8: 3 | S8: 3 | T8: 2 | U8: 2 | V8: 2 | W8: 2 | X8: 2 | Y8: 2 | Z8: 2 | AA8: 3 | AB8: 3 | AC8: 3 | AD8: 3 | AE8: 3 | AF8: 3 | AG8: 3 | AH8: 2 | AI8: 2 | AJ8: 2 | AK8: 2 | AL8: 2 | AM8: 2 | AN8: 2 | AO8: 3 | AP8: 3 | AR8: 0 | AS8: 14 | AT8: 16 | AU8: 0 | AV8: 0 | AW8: 0 | AX8: 0 | AY8: 0 | AZ8: 0 | BA8: 30
A9: 8 | B9: 17363318-1 | C9: 17363318 | D9: CARVAJAL | E9: TORREJON | F9: DIEGO ALFONSO | G9: RIGGER | H9: 46054 | I9: D | J9: M | K9: 7X7 | L9: 1790000091 | M9: 3 | N9: 3 | O9: 3 | P9: 3 | Q9: 3 | R9: 3 | S9: 3 | T9: 2 | U9: 2 | V9: 2 | W9: 2 | X9: 2 | Y9: 2 | Z9: 2 | AA9: 3 | AB9: 3 | AC9: 3 | AD9: 3 | AE9: 3 | AF9: 3 | AG9: 3 | AH9: 2 | AI9: 2 | AJ9: 2 | AK9: 2 | AL9: 2 | AM9: 2 | AN9: 2 | AO9: 3 | AP9: 3 | AR9: 0 | AS9: 14 | AT9: 16 | AU9: 0 | AV9: 0 | AW9: 0 | AX9: 0 | AY9: 0 | AZ9: 0 | BA9: 30
A10: 9 | B10: 19302584-6 | C10: 19302584 | D10: CASTILLO | E10: RODRIGUEZ | F10: JONATHAN ALEXANDER | G10: ELECTROMECÁNICO MANTENCIÓN | H10: 46054 | I10: I | J10: M | K10: 7X7 | L10: 1790000091 | M10: 3 | N10: 3 | O10: 3 | P10: 3 | Q10: 3 | R10: 3 | S10: 3 | T10: 2 | U10: 2 | V10: 2 | W10: 2 | X10: 2 | Y10: 2 | Z10: 2 | AA10: 3 | AB10: 3 | AC10: 3 | AD10: 3 | AE10: 3 | AF10: 3 | AG10: 3 | AH10: 2 | AI10: 2 | AJ10: 2 | AK10: 2 | AL10: 2 | AM10: 2 | AN10: 2 | AO10: 3 | AP10: 3 | AR10: 0 | AS10: 14 | AT10: 16 | AU10: 0 | AV10: 0 | AW10: 0 | AX10: 0 | AY10: 0 | AZ10: 0 | BA10: 30
A11: 10 | B11: 16443686-1 | C11: 16443686 | D11: ESQUIVEL | E11: OPAZO | F11: JUAN HERMAN ULIESES OPAZO | G11: ASESOR PREVENCION DE RIESGOS | H11: 46054 | I11: I | J11: M | K11: 7X7 | L11: 1790000091 | M11: 3 | N11: 3 | O11: 3 | P11: 3 | Q11: 3 | R11: 3 | S11: 3 | T11: 2 | U11: 2 | V11: 2 | W11: 2 | X11: 2 | Y11: 2 | Z11: 2 | AA11: 3 | AB11: 3 | AC11: 3 | AD11: 3 | AE11: 3 | AF11: 3 | AG11: 3 | AH11: 2 | AI11: 2 | AJ11: 2 | AK11: 2 | AL11: 2 | AM11: 2 | AN11: 2 | AO11: 3 | AP11: 3 | AR11: 0 | AS11: 14 | AT11: 16 | AU11: 0 | AV11: 0 | AW11: 0 | AX11: 0 | AY11: 0 | AZ11: 0 | BA11: 30
A12: 11 | B12: 13327527-4 | C12: 13327527 | D12: POBLETE | E12: GALLARDO | F12: VICTOR ANTONIO | G12: SUPERVISOR GEOSINTETICOS | H12: 46054 | I12: I | J12: M | K12: 7X7 | L12: 1790000091 | M12: 3 | N12: 3 | O12: 3 | P12: 3 | Q12: 3 | R12: 3 | S12: 3 | T12: 2 | U12: 2 | V12: 2 | W12: 2 | X12: 2 | Y12: 2 | Z12: 2 | AA12: 3 | AB12: 3 | AC12: 3 | AD12: 3 | AE12: 3 | AF12: 3 | AG12: 3 | AH12: 2 | AI12: 2 | AJ12: 2 | AK12: 2 | AL12: 2 | AM12: 2 | AN12: 2 | AO12: 3 | AP12: 3 | AR12: 0 | AS12: 14 | AT12: 16 | AU12: 0 | AV12: 0 | AW12: 0 | AX12: 0 | AY12: 0 | AZ12: 0 | BA12: 30 | BE12: 646000 | BF12: Bono asignación de obra
A13: 12 | B13: 10742396-6 | C13: 10742396 | D13: ALFARO | E13: CAMPUSANO | F13: EDUARDO ENRIQUE | G13: AYUDANTE GEOSINTETICOS | H13: 46068 | I13: D | J13: M | K13: 7X7 | L13: 1790000091 | M13: 3 | N13: 3 | O13: 3 | P13: 3 | Q13: 3 | R13: 3 | S13: 3 | T13: 2 | U13: 2 | V13: 2 | W13: 2 | X13: 2 | Y13: 2 | Z13: 2 | AA13: 3 | AB13: 3 | AC13: 3 | AD13: 3 | AE13: 3 | AF13: 3 | AG13: 3 | AH13: 2 | AI13: 2 | AJ13: 2 | AK13: 2 | AL13: 2 | AM13: 2 | AN13: 2 | AO13: 3 | AP13: 3 | AR13: 0 | AS13: 14 | AT13: 16 | AU13: 0 | AV13: 0 | AW13: 0 | AX13: 0 | AY13: 0 | AZ13: 0 | BA13: 30
A14: 13 | B14: 17714007-4 | C14: 17714007 | D14: ALFARO | E14: DUBO | F14: MARCO ANTONIO | G14: MAESTRO SEGUNDA GEOSINTETICOS | H14: 46068 | I14: D | J14: M | K14: 7X7 | L14: 1790000091 | M14: 3 | N14: 3 | O14: 3 | P14: 3 | Q14: 3 | R14: 3 | S14: 3 | T14: 2 | U14: 2 | V14: 2 | W14: 2 | X14: 2 | Y14: 2 | Z14: 2 | AA14: 3 | AB14: 3 | AC14: 3 | AD14: 3 | AE14: 3 | AF14: 3 | AG14: 3 | AH14: 2 | AI14: 2 | AJ14: 2 | AK14: 2 | AL14: 2 | AM14: 2 | AN14: 2 | AO14: 3 | AP14: 3 | AR14: 0 | AS14: 14 | AT14: 16 | AU14: 0 | AV14: 0 | AW14: 0 | AX14: 0 | AY14: 0 | AZ14: 0 | BA14: 30
A15: 14 | B15: 15441205-0 | C15: 15441205 | D15: ROBLES | E15: CUEVAS | F15: RONALD ROLF | G15: TECNICO CONTROL CALIDAD | H15: 46078 | I15: D | J15: M | K15: 7X7 | L15: 1790000091 | M15: 3 | N15: 3 | O15: 3 | P15: 3 | Q15: 3 | R15: 3 | S15: 3 | T15: 2 | U15: 2 | V15: 2 | W15: 2 | X15: 2 | Y15: 2 | Z15: 2 | AA15: 3 | AB15: 3 | AC15: 3 | AD15: 3 | AE15: 3 | AF15: 3 | AG15: 3 | AH15: 2 | AI15: 2 | AJ15: 2 | AK15: 2 | AL15: 2 | AM15: 2 | AN15: 2 | AO15: 3 | AP15: 3 | AR15: 0 | AS15: 14 | AT15: 16 | AU15: 0 | AV15: 0 | AW15: 0 | AX15: 0 | AY15: 0 | AZ15: 0 | BA15: 30
A16: 15 | B16: 28459164-K | C16: 28459164 | D16: DURAN | E16: MENDOZA | F16: ROLANDO DURAN MENDOZA | G16: AYUDANTE GEOSINTETICOS | H16: 46096 | I16: D | J16: M | K16: 7X7 | L16: 1790000091 | M16: 3 | N16: 3 | O16: 3 | P16: 3 | Q16: 3 | R16: 3 | S16: 3 | T16: 2 | U16: 2 | V16: 2 | W16: 2 | X16: 2 | Y16: 2 | Z16: 2 | AA16: 3 | AB16: 3 | AC16: 3 | AD16: 3 | AE16: 3 | AF16: 3 | AG16: 3 | AH16: 2 | AI16: 2 | AJ16: 2 | AK16: 2 | AL16: 2 | AM16: 2 | AN16: 2 | AO16: 3 | AP16: 3 | AR16: 0 | AS16: 14 | AT16: 16 | AU16: 0 | AV16: 0 | AW16: 0 | AX16: 0 | AY16: 0 | AZ16: 0 | BA16: 30
A17: 16 | B17: 20728107-7 | C17: 20728107 | D17: ARAYA | E17: VILLALOBOS | F17: JOSE IGNACIO | G17: AYUDANTE GEOSINTETICOS | H17: 46096 | I17: D | J17: M | K17: 7X7 | L17: 1790000091 | M17: 3 | N17: 3 | O17: 3 | P17: 3 | Q17: 3 | R17: 3 | S17: 3 | T17: 2 | U17: 2 | V17: 2 | W17: 2 | X17: 2 | Y17: 2 | Z17: 2 | AA17: 3 | AB17: 3 | AC17: 3 | AD17: 3 | AE17: 3 | AF17: 3 | AG17: 3 | AH17: 2 | AI17: 2 | AJ17: 2 | AK17: 2 | AL17: 2 | AM17: 2 | AN17: 2 | AO17: 3 | AP17: 3 | AR17: 0 | AS17: 14 | AT17: 16 | AU17: 0 | AV17: 0 | AW17: 0 | AX17: 0 | AY17: 0 | AZ17: 0 | BA17: 30
A18: 17 | B18: 9809267-6 | C18: 9809267 | D18: ANGEL | E18: GOMEZ | F18: SERGIO ERNESTO | G18: AYUDANTE GEOSINTETICOS | H18: 46096 | I18: D | J18: M | K18: 7X7 | L18: 1790000091 | M18: 3 | N18: 3 | O18: 3 | P18: 3 | Q18: 3 | R18: 3 | S18: 3 | T18: 2 | U18: 2 | V18: 2 | W18: 2 | X18: 2 | Y18: 2 | Z18: 2 | AA18: 3 | AB18: 3 | AC18: 3 | AD18: 3 | AE18: 3 | AF18: 3 | AG18: 3 | AH18: 2 | AI18: 2 | AJ18: 2 | AK18: 2 | AL18: 2 | AM18: 2 | AN18: 2 | AO18: 3 | AP18: 3 | AR18: 0 | AS18: 14 | AT18: 16 | AU18: 0 | AV18: 0 | AW18: 0 | AX18: 0 | AY18: 0 | AZ18: 0 | BA18: 30
A19: 18 | B19: 10192082-8 | C19: 10192082 | D19: GUERRERO | E19: GOMEZ | F19: LUIS HUMBERTO | G19: AYUDANTE GEOSINTETICOS | H19: 46096 | I19: D | J19: M | K19: 7X7 | L19: 1790000091 | M19: 3 | N19: 3 | O19: 3 | P19: 3 | Q19: 3 | R19: 3 | S19: 3 | T19: 2 | U19: 2 | V19: 2 | W19: 2 | X19: 2 | Y19: 2 | Z19: 2 | AA19: 3 | AB19: 3 | AC19: 3 | AD19: 3 | AE19: 3 | AF19: 3 | AG19: 3 | AH19: 2 | AI19: 2 | AJ19: 2 | AK19: 2 | AL19: 2 | AM19: 2 | AN19: 2 | AO19: 3 | AP19: 3 | AR19: 0 | AS19: 14 | AT19: 16 | AU19: 0 | AV19: 0 | AW19: 0 | AX19: 0 | AY19: 0 | AZ19: 0 | BA19: 30
A20: 19 | B20: 21743583-8 | C20: 21743583 | D20: TAPIA | E20: CONTRERAS | F20: MILOVAN EUGENIO | G20: MAESTRO SEGUNDA GEOSINTETICOS | H20: 46096 | I20: D | J20: M | K20: 7X7 | L20: 1790000091 | M20: 3 | N20: 3 | O20: 3 | P20: 3 | Q20: 3 | R20: 3 | S20: 3 | T20: 2 | U20: 2 | V20: 2 | W20: 2 | X20: 2 | Y20: 2 | Z20: 2 | AA20: 3 | AB20: 3 | AC20: 3 | AD20: 3 | AE20: 3 | AF20: 3 | AG20: 3 | AH20: 2 | AI20: 2 | AJ20: 2 | AK20: 2 | AL20: 2 | AM20: 2 | AN20: 2 | AO20: 3 | AP20: 3 | AR20: 0 | AS20: 14 | AT20: 16 | AU20: 0 | AV20: 0 | AW20: 0 | AX20: 0 | AY20: 0 | AZ20: 0 | BA20: 30
A21: 20 | B21: 20248225-2 | C21: 20248225 | D21: ESPINOZA | E21: PAREDES | F21: VICTOR MATIAS | G21: AYUDANTE GEOSINTETICOS | H21: 46096 | I21: D | J21: M | K21: 7X7 | L21: 1790000091 | M21: 3 | N21: 3 | O21: 3 | P21: 3 | Q21: 3 | R21: 3 | S21: 3 | T21: 2 | U21: 2 | V21: 2 | W21: 2 | X21: 2 | Y21: 2 | Z21: 2 | AA21: 3 | AB21: 3 | AC21: 3 | AD21: 3 | AE21: 3 | AF21: 3 | AG21: 3 | AH21: 2 | AI21: 2 | AJ21: 2 | AK21: 2 | AL21: 2 | AM21: 2 | AN21: 2 | AO21: 3 | AP21: 3 | AR21: 0 | AS21: 14 | AT21: 16 | AU21: 0 | AV21: 0 | AW21: 0 | AX21: 0 | AY21: 0 | AZ21: 0 | BA21: 30
A22: 21 | B22: 17112456-5 | C22: 17112456 | D22: CORTES | E22: AVILES | F22: IVAN ALEJANDRO | G22: MAESTRO PRIMERA GEOSINTETICO | H22: 46096 | I22: D | J22: M | K22: 7X7 | L22: 1790000091 | M22: 3 | N22: 3 | O22: 3 | P22: 3 | Q22: 3 | R22: 3 | S22: 3 | T22: 2 | U22: 2 | V22: 2 | W22: 2 | X22: 2 | Y22: 2 | Z22: 2 | AA22: 3 | AB22: 3 | AC22: 3 | AD22: 3 | AE22: 3 | AF22: 3 | AG22: 3 | AH22: 2 | AI22: 2 | AJ22: 2 | AK22: 2 | AL22: 2 | AM22: 2 | AN22: 2 | AO22: 3 | AP22: 3 | AR22: 0 | AS22: 14 | AT22: 16 | AU22: 0 | AV22: 0 | AW22: 0 | AX22: 0 | AY22: 0 | AZ22: 0 | BA22: 30
A23: 22 | B23: 20262451-0 | C23: 20262451 | D23: MIRANDA | E23: IRIBARREN | F23: SEBASTIAN LEE OSCAR | G23: BODEGUERO | H23: 46096 | I23: D | J23: M | K23: 7X7 | L23: 1790000091 | M23: 3 | N23: 3 | O23: 3 | P23: 3 | Q23: 3 | R23: 3 | S23: 3 | T23: 2 | U23: 2 | V23: 2 | W23: 2 | X23: 2 | Y23: 2 | Z23: 2 | AA23: 3 | AB23: 3 | AC23: 3 | AD23: 3 | AE23: 3 | AF23: 3 | AG23: 3 | AH23: 2 | AI23: 2 | AJ23: 2 | AK23: 2 | AL23: 2 | AM23: 2 | AN23: 2 | AO23: 3 | AP23: 3 | AR23: 0 | AS23: 14 | AT23: 16 | AU23: 0 | AV23: 0 | AW23: 0 | AX23: 0 | AY23: 0 | AZ23: 0 | BA23: 30
A24: 23 | B24: 18984688-6 | C24: 18984688 | D24: SEGOVIA | E24: CASTILLO | F24: RICARDO ENRIQUE | G24: MAESTRO SEGUNDA GEOSINTETICOS | H24: 46096 | I24: D | J24: M | K24: 7X7 | L24: 1790000091 | M24: 3 | N24: 3 | O24: 3 | P24: 3 | Q24: 3 | R24: 3 | S24: 3 | T24: 2 | U24: 2 | V24: 2 | W24: 2 | X24: 2 | Y24: 2 | Z24: 2 | AA24: 3 | AB24: 3 | AC24: 3 | AD24: 3 | AE24: 3 | AF24: 3 | AG24: 3 | AH24: 2 | AI24: 2 | AJ24: 2 | AK24: 2 | AL24: 2 | AM24: 2 | AN24: 2 | AO24: 3 | AP24: 3 | AR24: 0 | AS24: 14 | AT24: 16 | AU24: 0 | AV24: 0 | AW24: 0 | AX24: 0 | AY24: 0 | AZ24: 0 | BA24: 30
... A29: 28 | B29: 19206550-K | C29: 19206550 | D29: SALVATIERRA | E29: ALCAINO | F29: NICOLAS IGNACIO | G29: JEFE OFICINA TECNICA | H29: 46113 | I29: I | J29: M | K29: 7X7 | L29: 1790000091 | M29: 3 | N29: 3 | O29: 3 | P29: 3 | Q29: 3 | R29: 3 | S29: 3 | T29: 2 | U29: 2 | V29: 2 | W29: 2 | X29: 2 | Y29: 2 | Z29: 2 | AA29: 3 | AB29: 3 | AC29: 3 | AD29: 3 | AE29: 3 | AF29: 3 | AG29: 3 | AH29: 2 | AI29: 2 | AJ29: 2 | AK29: 2 | AL29: 2 | AM29: 2 | AN29: 2 | AO29: 3 | AP29: 3 | AR29: 0 | AS29: 14 | AT29: 16 | AU29: 0 | AV29: 0 | AW29: 0 | AX29: 0 | AY29: 0 | AZ29: 0 | BA29: 30

Sheet 04_2026_Acciona
A1: Nº | B1: RUT (sin puntos y con guion) | C1: ID (rut sin puntos, sin guión ni digito vertificador) | D1: APELLIDO PATERNO | E1: APELLIDO MATERNO | F1: NOMBRES | G1: CARGO | H1: INICIO DE CONTRATO | I1: D/I | J1: GENERO M/F | K1: TURNO (5x2-4x3-14x14 -art22) | L1: CC | M1: 1 | N1: 2 | O1: 3 | P1: 4 | Q1: 5 | R1: 6 | S1: 7 | T1: 8 | U1: 9 | V1: 10 | W1: 11 | X1: 12 | Y1: 13 | Z1: 14 | AA1: 15 | AB1: 16 | AC1: 17 | AD1: 18 | AE1: 19 | AF1: 20 | AG1: 21 | AH1: 22 | AI1: 23 | AJ1: 24 | AK1: 25 | AL1: 26 | AM1: 27 | AN1: 28 | AO1: 29 | AP1: 30 | AQ1: 31 | AR1: (1) | AS1: (2) | AT1: (3) | AU1: (4) | AV1: (5) | AW1: (6) | AX1: (7) | AY1: (8) | AZ1: (9) | BA1: T.D.T. | BB1: 1033-Bono Gestión Variable | BC1: 1029-Bono Compensatorio descanso | BD1: Justificación Bono 10-29 (Compensatorio descanso) | BE1: 1034-Bono Incentivo variable | BF1: Justificación Bono 1034 (Incentivo variable) | BG1: 1140-Bono Responsabilidad 2 | BH1: Justificación 1140 (Bono Responsabilidad) | BI1: 1041-Bono Terreno (Exclusivo proyecto Techint-CMDIC) | BJ1: 1031-Bono Escolaridad I/T (Uso exclusivo Area de Compensaciones) | BK1: 1092-Diferencia de haber | BL1: Justificación Bono 1092 (Diferencia de Haber) | BM1: Cantidad de feriados del mes | BN1: 1082-Bono Compens. Feriado | BO1: 1020-Aguinaldo I/T | BP1: 1140-Bono de Permanencia (Plan de Beneficios) | BQ1: Bono Seguridad BESALCO-MEL | BR1: Bono Q1 (Exclusivo Collahuasi) | BS1: Bono Q2 (Exclusivo Collahuasi) | BT1: Bono Q3 (Exclusivo Collahuasi) | BU1: Bono Q4 (Exclusivo Collahuasi) | BV1: Bono RSA (Exclusivo Collahuasi) | BW1: 1044-Asignación Colación | BX1: Justificación Asignacion Colacion | BY1: 1165-Asignación Movilización 2 | BZ1: Justificación Asignación Movilización 2 | CA1: 1172-Viatico 2 | CB1: Justificación Viatico | CC1: 1073-Otras Asignaciones N/I (Beneficios) | CD1: Justificaciión de Asignación (Detalle del beneficio) | CE1: 1032-Bono Escolaridad N/I | CF1: 1124-Asignación familiar Retroactiva | CG1: Descuento por aporte voluntario | CH1: Observaciones generales | CI1: ACUERDO MARCO ACCIONA-CODELCO | CJ1: GRATIFICACION ACUERD MARCO ACCIONA-CODELCO2 | CK1: DIAS ADICIONALES CHIQUICAMATA | CL1: BONO PARTICIPACION CHIQUI
A2: 1 | B2: 14309302-6 | C2: 14309302 | D2: CASTRO | E2: GARAY | F2: IVAN DARIO | G2: EXPEDITOR | H2: 46031 | I2: I | J2: M | K2: 14x14 D | L2: 1790000090 | M2: 2 | N2: 2 | O2: 3 | P2: 3 | Q2: 3 | R2: 2 | S2: 2 | T2: 2 | U2: 2 | V2: 3 | W2: 3 | X2: 3 | Y2: 3 | Z2: 3 | AA2: 2 | AB2: 2 | AC2: 2 | AD2: 2 | AE2: 2 | AF2: 2 | AG2: 2 | AH2: 2 | AI2: 2 | AJ2: 2 | AK2: 2 | AL2: 2 | AM2: 2 | AN2: 2 | AO2: 3 | AP2: 3 | AR2: 0 | AS2: 20 | AT2: 10 | AU2: 0 | AV2: 0 | AW2: 0 | AX2: 0 | AY2: 0 | AZ2: 0 | BA2: 30 | BC2: 674400 | BD2: DESCANSO PENDIENTE POR CIERRE LABORAL AL 30-04-2026 | BK2: 168600 | BL2: 1 DIA ADICIONAL POR APOYO EN DESMOVILIZACION | BP2: 75000 | CI2: 473333
A3: 2 | B3: 18008213-1 | C3: 18008213 | D3: GUTIERREZ | E3: ESCUDERO | F3: ALEJANDRO HERNAN | G3: JEFE DE TERRENO | H3: 45962 | I3: I | J3: M | K3: 14x14 B | L3: 1790000090 | M3: 3 | N3: 3 | O3: 3 | P3: 3 | Q3: 3 | R3: 3 | S3: 3 | T3: 2 | U3: 2 | V3: 2 | W3: 2 | X3: 2 | Y3: 2 | Z3: 2 | AA3: 2 | AB3: 2 | AC3: 2 | AD3: 2 | AE3: 2 | AF3: 2 | AG3: 2 | AH3: 3 | AI3: 3 | AJ3: 3 | AK3: 3 | AL3: 3 | AM3: 3 | AN3: 3 | AO3: 3 | AP3: 3 | AR3: 0 | AS3: 14 | AT3: 16 | AU3: 0 | AV3: 0 | AW3: 0 | AX3: 0 | AY3: 0 | AZ3: 0 | BA3: 30 | BC3: 598333 | BD3: DESCANSO PENDIENTE POR CIERRE LABORAL AL 30-04-2026 | BE3: 1350000 | BF3: Bono acuerdo salarial | BK3: 359000 | BL3: 1 DIA ADICIONAL POR COUCHING EN ANTOFAGASTA | CI3: 473333
A4: 3 | B4: 11820207-4 | C4: 11820207 | D4: MIRANDA | E4: CACERES | F4: HECTOR ANTONIO | G4: CAPATAZ GEOSINTETICOS | H4: 46092 | I4: D | J4: M | K4: 14X14 B | L4: 1790000090 | M4: 3 | N4: 3 | O4: 3 | P4: 3 | Q4: 3 | R4: 3 | S4: 3 | T4: 2 | U4: 2 | V4: 2 | W4: 2 | X4: 2 | Y4: 2 | Z4: 2 | AA4: 2 | AB4: 2 | AC4: 2 | AD4: 2 | AE4: 2 | AF4: 2 | AG4: 2 | AH4: 3 | AI4: 3 | AJ4: 3 | AK4: 3 | AL4: 3 | AM4: 3 | AN4: 3 | AO4: 3 | AP4: 3 | AR4: 0 | AS4: 14 | AT4: 16 | AU4: 0 | AV4: 0 | AW4: 0 | AX4: 0 | AY4: 0 | AZ4: 0 | BA4: 30 | BC4: 266667 | BD4: DESCANSO PENDIENTE POR CIERRE LABORAL AL 30-04-2026 | BK4: 160000 | BL4: 1 DIA ADICIONAL POR COUCHING EN ANTOFAGASTA | BP4: 75000 | CI4: 157778
A5: 4 | B5: 17722078-7 | C5: 17722078 | D5: ROJAS | E5: CAIMANQUE | F5: JOSE CARLOS | G5: SUPERVISOR CONTROL CALIDAD | H5: 45967 | I5: I | J5: M | K5: 14x14 B | L5: 1790000090 | M5: 3 | N5: 3 | O5: 3 | P5: 3 | Q5: 3 | R5: 3 | S5: 3 | T5: 2 | U5: 2 | V5: 2 | W5: 2 | X5: 2 | Y5: 2 | Z5: 2 | AA5: 2 | AB5: 2 | AC5: 2 | AD5: 2 | AE5: 2 | AF5: 2 | AG5: 2 | AH5: 3 | AI5: 3 | AJ5: 3 | AK5: 3 | AL5: 3 | AM5: 3 | AN5: 3 | AO5: 3 | AP5: 3 | AR5: 0 | AS5: 14 | AT5: 16 | AU5: 0 | AV5: 0 | AW5: 0 | AX5: 0 | AY5: 0 | AZ5: 0 | BA5: 30 | BC5: 427500 | BD5: DESCANSO PENDIENTE POR CIERRE LABORAL AL 30-04-2026 | BK5: 256500 | BL5: 1 DIA ADICIONAL POR COUCHING EN ANTOFAGASTA | CI5: 473333
A6: 5 | B6: 12943659-K | C6: 12943659 | D6: SANTANDER | E6: SANTANDER | F6: CARLOS LUIS | G6: SUPERVISOR GEOSINTETICOS | H6: 45992 | I6: I | J6: M | K6: 14x14 B | L6: 1790000090 | M6: 3 | N6: 3 | O6: 3 | P6: 3 | Q6: 3 | R6: 3 | S6: 3 | T6: 2 | U6: 2 | V6: 2 | W6: 2 | X6: 2 | Y6: 2 | Z6: 2 | AA6: 2 | AB6: 2 | AC6: 2 | AD6: 2 | AE6: 2 | AF6: 2 | AG6: 2 | AH6: 3 | AI6: 3 | AJ6: 3 | AK6: 3 | AL6: 3 | AM6: 3 | AN6: 3 | AO6: 3 | AP6: 3 | AR6: 0 | AS6: 14 | AT6: 16 | AU6: 0 | AV6: 0 | AW6: 0 | AX6: 0 | AY6: 0 | AZ6: 0 | BA6: 30 | BC6: 428833 | BD6: DESCANSO PENDIENTE POR CIERRE LABORAL AL 30-04-2026 | BE6: 860000 | BF6: Bono acuerdo salarial | BK6: 257300 | BL6: 1 DIA ADICIONAL POR COUCHING EN ANTOFAGASTA | CE6: 77281 | CI6: 473333
A7: 6 | B7: 15033526-4 | C7: 15033526 | D7: VILLEGAS | E7: SANTIBAÑEZ | F7: HERMAN ALEXIS | G7: CAPATAZ GEOSINTETICOS | H7: 46056 | I7: D | J7: M | K7: 14X14 B | L7: 1790000090 | M7: 3 | N7: 3 | O7: 3 | P7: 3 | Q7: 3 | R7: 3 | S7: 3 | T7: 2 | U7: 2 | V7: 2 | W7: 2 | X7: 2 | Y7: 2 | Z7: 2 | AA7: 2 | AB7: 2 | AC7: 2 | AD7: 2 | AE7: 2 | AF7: 2 | AG7: 2 | AH7: 3 | AI7: 3 | AJ7: 3 | AK7: 3 | AL7: 3 | AM7: 3 | AN7: 3 | AO7: 3 | AP7: 3 | AR7: 0 | AS7: 14 | AT7: 16 | AU7: 0 | AV7: 0 | AW7: 0 | AX7: 0 | AY7: 0 | AZ7: 0 | BA7: 30 | BC7: 266667 | BD7: DESCANSO PENDIENTE POR CIERRE LABORAL AL 30-04-2026 | BK7: 160000 | BL7: 1 DIA ADICIONAL POR COUCHING EN ANTOFAGASTA | BP7: 75000 | CI7: 315556
A8: 7 | B8: 27928346-5 | C8: 27928346 | D8: ARTETA | E8: CHARRIS | F8: DARIELA ANDREA | G8: PROGRAMADOR Y CONTROL | H8: 46113 | I8: I | J8: F | K8: 14X14 B | L8: 1790000090 | M8: 1 | N8: 1 | O8: 1 | P8: 1 | Q8: 1 | R8: 1 | S8: 1 | T8: 2 | U8: 2 | V8: 2 | W8: 2 | X8: 2 | Y8: 2 | Z8: 2 | AA8: 2 | AB8: 2 | AC8: 2 | AD8: 2 | AE8: 2 | AF8: 2 | AG8: 2 | AH8: 3 | AI8: 3 | AJ8: 3 | AK8: 3 | AL8: 3 | AM8: 3 | AN8: 3 | AO8: 3 | AP8: 3 | AR8: 7 | AS8: 14 | AT8: 9 | AU8: 0 | AV8: 0 | AW8: 0 | AX8: 0 | AY8: 0 | AZ8: 0 | BA8: 30 | BC8: 343333 | BD8: DESCANSO PENDIENTE POR CIERRE LABORAL AL 30-04-2026 | BE8: 270000 | BF8: Bono acuerdo salarial | BK8: 68667 | BL8: 1 DIA NORMAL CURSO INDUCCION SSO | CI8: 157778
A9: 8 | B9: 19507107-1 | C9: 19507107 | D9: ARAYA | E9: PEREZ | F9: SEBASTIAN IGNACIO | G9: AYUDANTE GEOSINTETICOS | H9: 46003 | I9: D | J9: M | K9: 14X14 B | L9: 1790000090 | M9: 3 | N9: 3 | O9: 3 | P9: 3 | Q9: 3 | R9: 3 | S9: 3 | T9: 2 | U9: 2 | V9: 2 | W9: 2 | X9: 2 | Y9: 2 | Z9: 2 | AA9: 2 | AB9: 2 | AC9: 2 | AD9: 2 | AE9: 2 | AF9: 2 | AG9: 2 | AH9: 3 | AI9: 3 | AJ9: 3 | AK9: 3 | AL9: 3 | AM9: 3 | AN9: 3 | AO9: 3 | AP9: 3 | AR9: 0 | AS9: 14 | AT9: 16 | AU9: 0 | AV9: 0 | AW9: 0 | AX9: 0 | AY9: 0 | AZ9: 0 | BA9: 30 | BC9: 130833 | BD9: DESCANSO PENDIENTE POR CIERRE LABORAL AL 30-04-2026 | BK9: 150000 | BL9: BONOS PERMANENCIA NO PAGADO EN PROCESO ANTERIOR | BP9: 75000 | CI9: 473333 | CJ9: 213354
A10: 9 | B10: 14456911-3 | C10: 14456911 | D10: ACEVEDO | E10: ZAMBRANO | F10: LUIS MARCELINO | G10: EXPEDITOR | H10: 45992 | I10: I | J10: M | K10: 4x3 | L10: 1790000090 | M10: 2 | N10: 2 | O10: 3 | P10: 3 | Q10: 3 | R10: 2 | S10: 2 | T10: 2 | U10: 2 | V10: 3 | W10: 3 | X10: 3 | Y10: 2 | Z10: 2 | AA10: 2 | AB10: 2 | AC10: 3 | AD10: 3 | AE10: 3 | AF10: 2 | AG10: 2 | AH10: 2 | AI10: 2 | AJ10: 3 | AK10: 3 | AL10: 3 | AR10: 0 | AS10: 14 | AT10: 12 | AU10: 0 | AV10: 0 | AW10: 0 | AX10: 0 | AY10: 0 | AZ10: 0 | BA10: 26 | BW10: 110000 | BX10: Acurdo departamento
A11: 10 | B11: 15975698-k | C11: 15975698 | D11: ACEVEDO | E11: ARANCIBIA | F11: JORGE ALEJANDRO | G11: BODEGUERO | H11: 46003 | I11: I | J11: M | K11: 14X14 B | L11: 1790000090 | M11: 3 | N11: 3 | O11: 3 | P11: 3 | Q11: 3 | R11: 3 | S11: 3 | T11: 2 | U11: 2 | V11: 2 | W11: 2 | X11: 2 | Y11: 2 | Z11: 2 | AA11: 2 | AB11: 2 | AC11: 2 | AD11: 2 | AE11: 2 | AF11: 2 | AG11: 2 | AH11: 3 | AI11: 3 | AJ11: 3 | AK11: 3 | AL11: 3 | AM11: 3 | AN11: 3 | AO11: 3 | AP11: 3 | AR11: 0 | AS11: 14 | AT11: 16 | AU11: 0 | AV11: 0 | AW11: 0 | AX11: 0 | AY11: 0 | AZ11: 0 | BA11: 30 | BC11: 182167 | BD11: DESCANSO PENDIENTE POR CIERRE LABORAL AL 30-04-2026 | BP11: 75000 | CI11: 473333
A12: 11 | B12: 15494232-7 | C12: 15494242 | D12: AGUILERA | E12: ROJAS | F12: OSCAR ALEXI | G12: MAESTRO PRIMERA GEOSINTETICOS | H12: 45997 | I12: D | J12: M | K12: 14x14 B | L12: 1790000090 | M12: 3 | N12: 3 | O12: 3 | P12: 3 | Q12: 3 | R12: 3 | S12: 3 | T12: 2 | U12: 2 | V12: 2 | W12: 2 | X12: 2 | Y12: 2 | Z12: 2 | AA12: 2 | AB12: 2 | AC12: 2 | AD12: 2 | AE12: 2 | AF12: 2 | AG12: 2 | AH12: 3 | AI12: 3 | AJ12: 3 | AK12: 3 | AL12: 3 | AM12: 3 | AN12: 3 | AO12: 3 | AP12: 3 | AR12: 0 | AS12: 14 | AT12: 16 | AU12: 0 | AV12: 0 | AW12: 0 | AX12: 0 | AY12: 0 | AZ12: 0 | BA12: 30 | BC12: 235333 | BD12: DESCANSO PENDIENTE POR CIERRE LABORAL AL 30-04-2026 | BP12: 75000 | CI12: 473333
A13: 12 | B13: 20601023-1 | C13: 20601023 | D13: ALFARO | E13: ARANCIBIA | F13: ALEJANDRO MARCELO | G13: TECNICO CONTROL CALIDAD | H13: 46003 | I13: D | J13: M | K13: 14X14 B | L13: 1790000090 | M13: 3 | N13: 3 | O13: 3 | P13: 3 | Q13: 3 | R13: 3 | S13: 3 | T13: 2 | U13: 2 | V13: 2 | W13: 2 | X13: 2 | Y13: 2 | Z13: 2 | AA13: 2 | AB13: 2 | AC13: 2 | AD13: 2 | AE13: 2 | AF13: 2 | AG13: 2 | AH13: 3 | AI13: 3 | AJ13: 3 | AK13: 3 | AL13: 3 | AM13: 3 | AN13: 3 | AO13: 3 | AP13: 3 | AR13: 0 | AS13: 14 | AT13: 16 | AU13: 0 | AV13: 0 | AW13: 0 | AX13: 0 | AY13: 0 | AZ13: 0 | BA13: 30 | BC13: 235333 | BD13: DESCANSO PENDIENTE POR CIERRE LABORAL AL 30-04-2026 | BP13: 75000 | CI13: 473333
A14: 13 | B14: 20945942-6 | C14: 20945942 | D14: ALFARO | E14: DIAZ | F14: AXCEL ESTEBAN | G14: MAESTRO SEGUNDA GEOSINTETICOS | H14: 46023 | I14: D | J14: M | K14: 14x14 A | L14: 1790000090 | M14: 2 | N14: 2 | O14: 8 | P14: 8 | Q14: 2 | R14: 2 | S14: 2 | T14: 3 | U14: 3 | V14: 3 | W14: 3 | X14: 3 | Y14: 3 | Z14: 3 | AA14: 3 | AB14: 3 | AC14: 3 | AD14: 3 | AE14: 3 | AF14: 3 | AG14: 3 | AH14: 2 | AI14: 2 | AJ14: 2 | AK14: 2 | AL14: 2 | AM14: 2 | AN14: 2 | AO14: 2 | AP14: 2 | AR14: 0 | AS14: 14 | AT14: 14 | AU14: 0 | AV14: 0 | AW14: 0 | AX14: 0 | AY14: 2 | AZ14: 0 | BA14: 30 | BM14: 2 | BN14: 180000 | BP14: 75000 | CI14: 473333 | CK14: 810000 | CL14: 100000
A15: 14 | B15: 18182792-0 | C15: 18182792 | D15: ANZA | E15: COLOMAR | F15: JOSE RODRIGO | G15: AYUDANTE GEOSINTETICOS | H15: 46023 | I15: D | J15: M | K15: 14x14 B | L15: 1790000090 | M15: 3 | N15: 3 | O15: 3 | P15: 3 | Q15: 3 | R15: 3 | S15: 3 | T15: 2 | U15: 2 | V15: 2 | W15: 2 | X15: 2 | Y15: 2 | Z15: 2 | AA15: 2 | AB15: 2 | AC15: 2 | AD15: 2 | AE15: 2 | AF15: 2 | AG15: 2 | AH15: 3 | AI15: 3 | AJ15: 3 | AK15: 3 | AL15: 3 | AM15: 3 | AN15: 3 | AO15: 3 | AP15: 3 | AR15: 0 | AS15: 14 | AT15: 16 | AU15: 0 | AV15: 0 | AW15: 0 | AX15: 0 | AY15: 0 | AZ15: 0 | BA15: 30 | BC15: 130833 | BD15: DESCANSO PENDIENTE POR CIERRE LABORAL AL 30-04-2026 | BP15: 75000 | CI15: 473333 | CJ15: 213354
A16: 15 | B16: 9850740-k | C16: 9850740 | D16: ARAYA | E16: TELLO | F16: JABIEL NICANOR | G16: MAESTRO PRIMERA GEOSINTETICOS | H16: 45992 | I16: D | J16: M | K16: 14X14 B | L16: 1790000090 | M16: 3 | N16: 3 | O16: 3 | P16: 3 | Q16: 3 | R16: 3 | S16: 3 | T16: 2 | U16: 2 | V16: 2 | W16: 2 | X16: 2 | Y16: 2 | Z16: 2 | AA16: 2 | AB16: 2 | AC16: 2 | AD16: 2 | AE16: 2 | AF16: 2 | AG16: 2 | AH16: 3 | AI16: 3 | AJ16: 3 | AK16: 3 | AL16: 3 | AM16: 3 | AN16: 3 | AO16: 3 | AP16: 3 | AR16: 0 | AS16: 14 | AT16: 16 | AU16: 0 | AV16: 0 | AW16: 0 | AX16: 0 | AY16: 0 | AZ16: 0 | BA16: 30 | BC16: 235333 | BD16: DESCANSO PENDIENTE POR CIERRE LABORAL AL 30-04-2026 | BP16: 75000 | CI16: 473333
A17: 16 | B17: 15494188-6 | C17: 15494188 | D17: ARAYA | E17: GALLEGUILLOS | F17: CARLOS ALBERTO | G17: JEFE OFICINA TECNICA | H17: 46064 | I17: I | J17: M | K17: 4X3 | L17: 1790000090 | M17: 2 | N17: 2 | O17: 3 | P17: 3 | Q17: 3 | R17: 2 | S17: 2 | T17: 2 | U17: 2 | V17: 3 | W17: 3 | X17: 3 | Y17: 2 | Z17: 2 | AA17: 2 | AB17: 2 | AC17: 3 | AD17: 3 | AE17: 3 | AF17: 2 | AG17: 2 | AH17: 2 | AI17: 2 | AJ17: 3 | AK17: 3 | AL17: 3 | AM17: 2 | AN17: 2 | AO17: 2 | AP17: 2 | AR17: 0 | AS17: 18 | AT17: 12 | AU17: 0 | AV17: 0 | AW17: 0 | AX17: 0 | AY17: 0 | AZ17: 0 | BA17: 30 | CI17: 315556
A18: 17 | B18: 19712640-K | C18: 19712640 | D18: ARAYA | E18: SIERRA | F18: JOSE LUIS | G18: BODEGUERO | H18: 45995 | I18: I | J18: M | K18: 14X14 A | L18: 1790000090 | M18: 4 | N18: 4 | O18: 4 | P18: 4 | Q18: 4 | R18: 4 | S18: 4 | T18: 3 | U18: 3 | V18: 3 | W18: 3 | X18: 3 | Y18: 3 | Z18: 3 | AA18: 3 | AB18: 3 | AC18: 3 | AD18: 3 | AE18: 3 | AF18: 3 | AG18: 3 | AH18: 2 | AI18: 2 | AJ18: 2 | AK18: 2 | AL18: 2 | AM18: 2 | AN18: 2 | AO18: 2 | AP18: 2 | AR18: 0 | AS18: 9 | AT18: 14 | AU18: 7 | AV18: 0 | AW18: 0 | AX18: 0 | AY18: 0 | AZ18: 0 | BA18: 23 | CI18: 473333
A19: 18 | B19: 12953191-6 | C19: 12953191 | D19: ARELLANO | E19: ARRIAZA | F19: MARCO ANTONIO | G19: TECNICO RRHH PROYECTO | H19: 45971 | I19: D | J19: M | K19: 14x14 D | L19: 1790000090 | M19: 3 | N19: 3 | O19: 3 | P19: 3 | Q19: 3 | R19: 3 | S19: 3 | T19: 3 | U19: 3 | V19: 3 | W19: 3 | X19: 3 | Y19: 3 | Z19: 3 | AA19: 2 | AB19: 2 | AC19: 2 | AD19: 2 | AE19: 2 | AF19: 2 | AG19: 2 | AH19: 2 | AI19: 2 | AJ19: 2 | AK19: 2 | AL19: 2 | AM19: 2 | AN19: 2 | AO19: 3 | AP19: 3 | AR19: 0 | AS19: 14 | AT19: 16 | AU19: 0 | AV19: 0 | AW19: 0 | AX19: 0 | AY19: 0 | AZ19: 0 | BA19: 30 | BC19: 620000 | BD19: DESCANSO PENDIENTE POR CIERRE LABORAL AL 30-04-2026 | BP19: 75000 | CI19: 473333
A20: 19 | B20: 15802017-3 | C20: 15802017 | D20: ARGANDOÑA | E20: IBACACHE | F20: PABLO CÉSAR | G20: MAESTRO PRIMERA GEOSINTETICOS | H20: 45974 | I20: D | J20: M | K20: 14x14 A | L20: 1790000090 | M20: 2 | N20: 2 | O20: 8 | P20: 8 | Q20: 2 | R20: 2 | S20: 2 | T20: 3 | U20: 3 | V20: 3 | W20: 3 | X20: 3 | Y20: 3 | Z20: 3 | AA20: 3 | AB20: 3 | AC20: 3 | AD20: 3 | AE20: 3 | AF20: 3 | AG20: 3 | AH20: 2 | AI20: 2 | AJ20: 2 | AK20: 2 | AL20: 2 | AM20: 2 | AN20: 2 | AO20: 2 | AP20: 2 | AR20: 0 | AS20: 14 | AT20: 14 | AU20: 0 | AV20: 0 | AW20: 0 | AX20: 0 | AY20: 2 | AZ20: 0 | BA20: 30 | BM20: 2 | BN20: 282400 | BP20: 75000 | CI20: 473333
A21: 20 | B21: 11511458-1 | C21: 11511458 | D21: ASTUDILLO | E21: FRE | F21: JUAN LUIS | G21: MAESTRO SEGUNDA GEOSINTETICOS | H21: 45992 | I21: D | J21: M | K21: 14x14 A | L21: 1790000090 | M21: 2 | N21: 2 | O21: 8 | P21: 8 | Q21: 2 | R21: 2 | S21: 2 | T21: 3 | U21: 3 | V21: 3 | W21: 3 | X21: 3 | Y21: 3 | Z21: 3 | AA21: 3 | AB21: 3 | AC21: 3 | AD21: 3 | AE21: 3 | AF21: 3 | AG21: 3 | AR21: 0 | AS21: 5 | AT21: 14 | AU21: 0 | AV21: 0 | AW21: 0 | AX21: 0 | AY21: 2 | AZ21: 0 | BA21: 21 | BM21: 2 | BN21: 180000 | BP21: 52500 | CI21: 315555
A22: 21 | B22: 17175261-2 | C22: 17175261 | D22: ASTUDILLO | E22: ANDRADE | F22: CESAR ANTONIO | G22: TECNICO CONTROL CALIDAD | H22: 46054 | I22: D | J22: M | K22: 14X14 A | L22: 1790000090 | M22: 2 | N22: 2 | O22: 8 | P22: 8 | Q22: 2 | R22: 2 | S22: 2 | T22: 3 | U22: 3 | V22: 3 | W22: 3 | X22: 3 | Y22: 3 | Z22: 3 | AA22: 3 | AB22: 3 | AC22: 3 | AD22: 3 | AE22: 3 | AF22: 3 | AG22: 3 | AH22: 2 | AI22: 2 | AJ22: 2 | AK22: 2 | AL22: 2 | AM22: 2 | AN22: 2 | AO22: 2 | AP22: 2 | AR22: 0 | AS22: 14 | AT22: 14 | AU22: 0 | AV22: 0 | AW22: 0 | AX22: 0 | AY22: 2 | AZ22: 0 | BA22: 30 | BM22: 2 | BN22: 282400 | BP22: 75000 | CI22: 473333 | CK22: 1270799 | CL22: 100000
A23: 22 | B23: 12543039-2 | C23: 12543039 | D23: AVILA | E23: LINEROS | F23: AUDIAS ABDENEGO | G23: AYUDANTE GEOSINTETICOS | H23: 45995 | I23: D | J23: M | K23: 14X14 B | L23: 1790000090 | M23: 3 | N23: 3 | O23: 3 | P23: 3 | Q23: 3 | R23: 3 | S23: 3 | T23: 2 | U23: 2 | V23: 2 | W23: 2 | X23: 2 | Y23: 2 | Z23: 2 | AA23: 2 | AB23: 2 | AC23: 2 | AD23: 2 | AE23: 2 | AF23: 2 | AG23: 2 | AH23: 3 | AI23: 3 | AJ23: 3 | AK23: 3 | AL23: 3 | AM23: 3 | AN23: 3 | AO23: 3 | AP23: 3 | AR23: 0 | AS23: 14 | AT23: 16 | AU23: 0 | AV23: 0 | AW23: 0 | AX23: 0 | AY23: 0 | AZ23: 0 | BA23: 30 | BC23: 130833 | BD23: DESCANSO PENDIENTE POR CIERRE LABORAL AL 30-04-2026 | BP23: 75000 | CI23: 473333 | CJ23: 213354
A24: 23 | B24: 21016873-7 | C24: 21016873 | D24: AVILA | E24: GAJARDO | F24: FRANCISCO OSIEL | G24: MAESTRO PRIMERA GEOSINTETICOS | H24: 45987 | I24: D | J24: M | K24: 14x14 A | L24: 1790000090 | M24: 2 | N24: 2 | O24: 8 | P24: 8 | Q24: 2 | R24: 2 | S24: 2 | T24: 3 | U24: 3 | V24: 3 | W24: 3 | X24: 3 | Y24: 3 | Z24: 3 | AA24: 3 | AB24: 3 | AC24: 3 | AD24: 3 | AE24: 3 | AF24: 3 | AG24: 3 | AR24: 0 | AS24: 5 | AT24: 14 | AU24: 0 | AV24: 0 | AW24: 0 | AX24: 0 | AY24: 2 | AZ24: 0 | BA24: 21 | BM24: 2 | BN24: 282400 | BP24: 52500 | CI24: 315555
A25: 24 | B25: 24457802-0 | C25: 24457802 | D25: BEYUMA | E25: VIRUEZ | F25: DONNY | G25: AYUDANTE GEOSINTETICOS | H25: 46054 | I25: D | J25: M | K25: 14X14 B | L25: 1790000090 | M25: 3 | N25: 3 | O25: 3 | P25: 3 | Q25: 3 | R25: 3 | S25: 3 | T25: 2 | U25: 2 | V25: 2 | W25: 2 | X25: 2 | Y25: 2 | Z25: 2 | AA25: 2 | AB25: 2 | AC25: 2 | AD25: 2 | AE25: 2 | AF25: 2 | AG25: 2 | AH25: 3 | AI25: 3 | AJ25: 3 | AK25: 3 | AL25: 3 | AM25: 3 | AN25: 3 | AO25: 3 | AP25: 3 | AR25: 0 | AS25: 14 | AT25: 16 | AU25: 0 | AV25: 0 | AW25: 0 | AX25: 0 | AY25: 0 | AZ25: 0 | BA25: 30 | BC25: 130833 | BD25: DESCANSO PENDIENTE POR CIERRE LABORAL AL 30-04-2026 | BP25: 75000 | CI25: 473333 | CJ25: 213354
A26: 25 | B26: 13975512-k | C26: 13975512 | D26: BRUNA | E26: MUÑOZ | F26: EDUARDO ENRIQUE | G26: MAESTRO PRIMERA GEOSINTETICOS | H26: 46041 | I26: D | J26: M | K26: 14X14 B | L26: 1790000090 | M26: 3 | N26: 3 | O26: 3 | P26: 3 | Q26: 3 | R26: 3 | S26: 3 | T26: 2 | U26: 2 | V26: 2 | W26: 2 | X26: 2 | Y26: 2 | Z26: 2 | AA26: 2 | AB26: 2 | AC26: 2 | AD26: 2 | AE26: 2 | AF26: 2 | AG26: 2 | AH26: 3 | AI26: 3 | AJ26: 3 | AK26: 3 | AL26: 3 | AM26: 3 | AN26: 3 | AO26: 3 | AP26: 3 | AR26: 0 | AS26: 14 | AT26: 16 | AU26: 0 | AV26: 0 | AW26: 0 | AX26: 0 | AY26: 0 | AZ26: 0 | BA26: 30 | BC26: 235333 | BD26: DESCANSO PENDIENTE POR CIERRE LABORAL AL 30-04-2026 | BP26: 75000 | CI26: 473333
A27: 26 | B27: 20308932-5 | C27: 20308932 | D27: BUGUEÑO | E27: CARVAJAL | F27: VICTOR EDUARDO | G27: MAESTRO SEGUNDA GEOSINTETICOS | H27: 45987 | I27: D | J27: M | K27: 14x14 A | L27: 1790000090 | M27: 2 | N27: 2 | O27: 8 | P27: 8 | Q27: 2 | R27: 2 | S27: 2 | T27: 3 | U27: 3 | V27: 3 | W27: 3 | X27: 3 | Y27: 3 | Z27: 3 | AA27: 3 | AB27: 3 | AC27: 3 | AD27: 3 | AE27: 3 | AF27: 3 | AG27: 3 | AH27: 2 | AI27: 2 | AJ27: 2 | AK27: 2 | AL27: 2 | AM27: 2 | AN27: 2 | AO27: 2 | AP27: 2 | AR27: 0 | AS27: 14 | AT27: 14 | AU27: 0 | AV27: 0 | AW27: 0 | AX27: 0 | AY27: 2 | AZ27: 0 | BA27: 30 | BM27: 2 | BN27: 180000 | BP27: 75000 | CI27: 473333
A28: 27 | B28: 19809697-0 | C28: 19809697 | D28: BUSTAMANTE | E28: PACHECO | F28: MARYORIE CECILIA | G28: PROGRAMADOR Y CONTROL | H28: 45962 | I28: I | J28: F | K28: 14x14 B | L28: 1790000090 | M28: 4 | N28: 4 | O28: 4 | P28: 4 | Q28: 4 | R28: 4 | S28: 4 | T28: 4 | U28: 4 | V28: 4 | W28: 4 | X28: 4 | Y28: 4 | Z28: 4 | AA28: 4 | AB28: 4 | AC28: 4 | AD28: 4 | AE28: 4 | AF28: 4 | AG28: 4 | AH28: 3 | AR28: 0 | AS28: 0 | AT28: 1 | AU28: 21 | AV28: 0 | AW28: 0 | AX28: 0 | AY28: 0 | AZ28: 0 | BA28: 1 | BE28: 17000 | BF28: Bono acuerdo salarial | CI28: 473333
A29: 28 | B29: 13640892-5 | C29: 13640892 | D29: CACERES | E29: MUÑOZ | F29: ANIBAL JOSE | G29: JEFE RRHH PROYECTO | H29: 45962 | I29: I | J29: M | K29: 4X3 | L29: 1790000090 | M29: 2 | N29: 2 | O29: 3 | P29: 3 | Q29: 3 | R29: 2 | S29: 2 | T29: 2 | U29: 2 | V29: 3 | W29: 3 | X29: 3 | Y29: 2 | Z29: 2 | AA29: 2 | AB29: 2 | AC29: 3 | AD29: 3 | AE29: 3 | AF29: 2 | AG29: 2 | AH29: 2 | AI29: 2 | AJ29: 3 | AK29: 3 | AL29: 3 | AM29: 2 | AN29: 2 | AO29: 2 | AP29: 2 | AR29: 0 | AS29: 18 | AT29: 12 | AU29: 0 | AV29: 0 | AW29: 0 | AX29: 0 | AY29: 0 | AZ29: 0 | BA29: 30 | BC29: 269600 | BD29: 1 DIA ADICIONAL POR TRABAJOS DE AUDITORIA Y CIERRE MES FUERA TURNO | CI29: 473333
A30: 29 | B30: 18193913-3 | C30: 18193913 | D30: CALDERON | E30: ALVAREZ | F30: JOSE MIGUEL | G30: MAESTRO PRIMERA GEOSINTETICOS | H30: 46001 | I30: D | J30: M | K30: 14X14 B | L30: 1790000090 | M30: 3 | N30: 3 | O30: 3 | P30: 3 | Q30: 3 | R30: 3 | S30: 3 | T30: 2 | U30: 2 | V30: 2 | W30: 2 | X30: 2 | Y30: 2 | Z30: 2 | AA30: 2 | AB30: 2 | AC30: 2 | AD30: 2 | AE30: 2 | AF30: 2 | AG30: 2 | AH30: 3 | AI30: 3 | AJ30: 3 | AK30: 3 | AL30: 3 | AM30: 3 | AN30: 3 | AO30: 3 | AP30: 3 | AR30: 0 | AS30: 14 | AT30: 16 | AU30: 0 | AV30: 0 | AW30: 0 | AX30: 0 | AY30: 0 | AZ30: 0 | BA30: 30 | BC30: 235333 | BD30: DESCANSO PENDIENTE POR CIERRE LABORAL AL 30-04-2026 | BP30: 75000 | CI30: 473333
A31: 30 | B31: 20747827-K | C31: 20747827 | D31: CAMPOS | E31: ARAYA | F31: JAIRO LEANDRO | G31: MAESTRO SEGUNDA GEOSINTETICOS | H31: 46003 | I31: D | J31: M | K31: 14x14 B | L31: 1790000090 | M31: 3 | N31: 3 | O31: 3 | P31: 3 | Q31: 3 | R31: 3 | S31: 3 | T31: 2 | U31: 2 | V31: 2 | W31: 2 | X31: 2 | Y31: 2 | Z31: 2 | AA31: 2 | AB31: 2 | AC31: 2 | AD31: 2 | AE31: 2 | AF31: 2 | AG31: 2 | AH31: 3 | AI31: 3 | AJ31: 3 | AK31: 3 | AL31: 3 | AM31: 3 | AN31: 3 | AO31: 3 | AP31: 3 | AR31: 0 | AS31: 14 | AT31: 16 | AU31: 0 | AV31: 0 | AW31: 0 | AX31: 0 | AY31: 0 | AZ31: 0 | BA31: 30 | BC31: 150000 | BD31: DESCANSO PENDIENTE POR CIERRE LABORAL AL 30-04-2026 | BP31: 75000 | CI31: 473333
A32: 31 | B32: 18632489-7 | C32: 18632489 | D32: CAMPUSANO | E32: VEGA | F32: PATRICIO HERNAN | G32: MAESTRO SEGUNDA GEOSINTETICOS | H32: 46054 | I32: D | J32: M | K32: 14X14 A | L32: 1790000090 | M32: 2 | N32: 2 | O32: 8 | P32: 8 | Q32: 2 | R32: 2 | S32: 2 | T32: 3 | U32: 3 | V32: 3 | W32: 3 | X32: 3 | Y32: 3 | Z32: 3 | AA32: 3 | AB32: 3 | AC32: 3 | AD32: 3 | AE32: 3 | AF32: 3 | AG32: 3 | AR32: 0 | AS32: 5 | AT32: 14 | AU32: 0 | AV32: 0 | AW32: 0 | AX32: 0 | AY32: 2 | AZ32: 0 | BA32: 21 | BM32: 2 | BN32: 180000 | BP32: 52500 | CI32: 315555
A33: 32 | B33: 20006272-8 | C33: 20006272 | D33: CARMONA | E33: ALZAMORA | F33: GABRIEL MATIAS | G33: MAESTRO SEGUNDA GEOSINTETICOS | H33: 46004 | I33: D | J33: M | K33: 14X14 A | L33: 1790000090 | M33: 2 | N33: 2 | O33: 8 | P33: 8 | Q33: 2 | R33: 2 | S33: 2 | T33: 3 | U33: 3 | V33: 3 | W33: 3 | X33: 3 | Y33: 3 | Z33: 3 | AA33: 3 | AB33: 3 | AC33: 3 | AD33: 3 | AE33: 3 | AF33: 3 | AG33: 3 | AH33: 2 | AI33: 2 | AJ33: 2 | AK33: 2 | AL33: 2 | AM33: 2 | AN33: 2 | AO33: 2 | AP33: 2 | AR33: 0 | AS33: 14 | AT33: 14 | AU33: 0 | AV33: 0 | AW33: 0 | AX33: 0 | AY33: 2 | AZ33: 0 | BA33: 30 | BM33: 2 | BN33: 180000 | BP33: 75000 | CI33: 473333 | CK33: 810000 | CL33: 100000
A34: 33 | B34: 15757199-0 | C34: 15757199 | D34: CARRASCO | E34: HERMOSILLA | F34: WILLIAMS ALEX | G34: AYUDANTE GEOSINTETICOS | H34: 46023 | I34: D | J34: M | K34: 14x14 A | L34: 1790000090 | M34: 2 | N34: 2 | O34: 8 | P34: 8 | Q34: 2 | R34: 2 | S34: 2 | T34: 3 | U34: 3 | V34: 3 | W34: 3 | X34: 3 | Y34: 3 | Z34: 3 | AA34: 3 | AB34: 3 | AC34: 3 | AD34: 3 | AE34: 3 | AF34: 3 | AG34: 3 | AR34: 0 | AS34: 5 | AT34: 14 | AU34: 0 | AV34: 0 | AW34: 0 | AX34: 0 | AY34: 2 | AZ34: 0 | BA34: 21 | BM34: 2 | BN34: 157000 | BP34: 52500 | CI34: 315555
A35: 34 | B35: 19155427-2 | C35: 19155427 | D35: CASTRO | E35: IRIARTE | F35: CRISTOFFER MANUEL | G35: RIGGER | H35: 45987 | I35: D | J35: M | K35: 14x14 A | L35: 1790000090 | M35: 2 | N35: 2 | O35: 8 | P35: 8 | Q35: 2 | R35: 2 | S35: 2 | T35: 3 | U35: 3 | V35: 3 | W35: 3 | X35: 3 | Y35: 3 | Z35: 3 | AA35: 3 | AB35: 3 | AC35: 3 | AD35: 3 | AE35: 3 | AF35: 3 | AG35: 3 | AH35: 2 | AI35: 2 | AJ35: 2 | AK35: 2 | AL35: 2 | AM35: 2 | AN35: 2 | AO35: 2 | AP35: 2 | AR35: 0 | AS35: 14 | AT35: 14 | AU35: 0 | AV35: 0 | AW35: 0 | AX35: 0 | AY35: 2 | AZ35: 0 | BA35: 30 | BM35: 2 | BN35: 282400 | BP35: 75000 | CI35: 473333 | CK35: 1270799 | CL35: 100000
A36: 35 | B36: 18125043-7 | C36: 18125043 | D36: CISTERNAS | E36: IGOR | F36: LUKAS SERGEI | G36: MAESTRO SEGUNDA CONTROL CALIDAD | H36: 46069 | I36: D | J36: M | K36: 14X14 B | L36: 1790000090 | M36: 3 | N36: 3 | O36: 3 | P36: 3 | Q36: 3 | R36: 3 | S36: 3 | T36: 2 | U36: 2 | V36: 2 | W36: 2 | X36: 2 | Y36: 2 | Z36: 2 | AA36: 2 | AB36: 2 | AC36: 2 | AD36: 2 | AE36: 2 | AF36: 2 | AG36: 2 | AH36: 3 | AI36: 3 | AJ36: 3 | AK36: 3 | AL36: 3 | AM36: 3 | AN36: 3 | AO36: 3 | AP36: 3 | AR36: 0 | AS36: 14 | AT36: 16 | AU36: 0 | AV36: 0 | AW36: 0 | AX36: 0 | AY36: 0 | AZ36: 0 | BA36: 30 | BC36: 150000 | BD36: DESCANSO PENDIENTE POR CIERRE LABORAL AL 30-04-2026 | BP36: 75000 | CI36: 315556
A37: 36 | B37: 13632515-9 | C37: 13632515 | D37: CLARK | E37: ALFARO | F37: MAURICIO ANDRES | G37: JEFE DE TERRENO | H37: 45962 | I37: D | J37: M | K37: 14x14 A | L37: 1790000090 | M37: 2 | N37: 2 | O37: 8 | P37: 8 | Q37: 2 | R37: 2 | S37: 2 | T37: 3 | U37: 3 | V37: 3 | W37: 3 | X37: 3 | Y37: 3 | Z37: 3 | AA37: 3 | AB37: 3 | AC37: 3 | AD37: 3 | AE37: 3 | AF37: 3 | AG37: 3 | AH37: 2 | AI37: 2 | AJ37: 2 | AK37: 2 | AL37: 2 | AM37: 2 | AN37: 2 | AO37: 2 | AP37: 2 | AR37: 0 | AS37: 14 | AT37: 14 | AU37: 0 | AV37: 0 | AW37: 0 | AX37: 0 | AY37: 2 | AZ37: 0 | BA37: 30 | BE37: 1877000 | BF37: Bono acuerdo salarial | BM37: 2 | BN37: 718000 | CE37: 77281 | CI37: 473333 | CK37: 3230999 | CL37: 100000
A38: 37 | B38: 15050650-6 | C38: 15050650 | D38: CODOCEO | E38: ORMEÑO | F38: JOEL ALEXANDER | G38: OPERADOR CAMION PLUMA | H38: 45985 | I38: D | J38: M | K38: 14x14 A | L38: 1790000090 | M38: 2 | N38: 2 | O38: 8 | P38: 8 | Q38: 2 | R38: 2 | S38: 2 | T38: 3 | U38: 3 | V38: 3 | W38: 3 | X38: 3 | Y38: 3 | Z38: 3 | AA38: 3 | AB38: 3 | AC38: 3 | AD38: 3 | AE38: 3 | AF38: 3 | AG38: 3 | AH38: 2 | AI38: 2 | AJ38: 2 | AK38: 2 | AL38: 2 | AM38: 2 | AN38: 2 | AO38: 2 | AP38: 2 | AR38: 0 | AS38: 14 | AT38: 14 | AU38: 0 | AV38: 0 | AW38: 0 | AX38: 0 | AY38: 2 | AZ38: 0 | BA38: 30 | BM38: 2 | BN38: 337200 | BP38: 75000 | CI38: 473333 | CK38: 1517399 | CL38: 100000
A39: 38 | B39: 19815369-9 | C39: 19815369 | D39: COLLA | E39: CORTES | F39: ALEXANDER IGNACIO | G39: MAESTRO PRIMERA GEOSINTETICOS | H39: 46041 | I39: D | J39: M | K39: 14X14 B | L39: 1790000090 | M39: 3 | N39: 3 | O39: 3 | P39: 3 | Q39: 3 | R39: 3 | S39: 3 | T39: 2 | U39: 2 | V39: 2 | W39: 2 | X39: 2 | Y39: 2 | Z39: 2 | AA39: 2 | AB39: 2 | AC39: 2 | AD39: 2 | AE39: 2 | AF39: 2 | AG39: 2 | AH39: 3 | AI39: 3 | AJ39: 3 | AK39: 3 | AL39: 3 | AM39: 3 | AN39: 3 | AO39: 3 | AP39: 3 | AR39: 0 | AS39: 14 | AT39: 16 | AU39: 0 | AV39: 0 | AW39: 0 | AX39: 0 | AY39: 0 | AZ39: 0 | BA39: 30 | BC39: 235333 | BD39: DESCANSO PENDIENTE POR CIERRE LABORAL AL 30-04-2026 | BP39: 75000 | CI39: 473333
A40: 39 | B40: 18352650-2 | C40: 18352650 | D40: COLLAO | E40: ARAYA | F40: PAULINA ALEXANDRA | G40: ADMINISTRATIVO PREVENCION DE RIESGOS | H40: 45985 | I40: I | J40: F | K40: 14x14 C | L40: 1790000090 | M40: 2 | N40: 2 | O40: 8 | P40: 8 | Q40: 2 | R40: 2 | S40: 2 | T40: 2 | U40: 2 | V40: 2 | W40: 2 | X40: 2 | Y40: 2 | Z40: 2 | AA40: 3 | AB40: 3 | AC40: 3 | AD40: 3 | AE40: 3 | AF40: 3 | AG40: 3 | AH40: 3 | AI40: 3 | AJ40: 3 | AK40: 3 | AL40: 3 | AM40: 3 | AN40: 3 | AO40: 2 | AP40: 3 | AR40: 0 | AS40: 13 | AT40: 15 | AU40: 0 | AV40: 0 | AW40: 0 | AX40: 0 | AY40: 2 | AZ40: 0 | BA40: 30 | BM40: 2 | BN40: 232000 | BP40: 75000 | CI40: 473333
A41: 40 | B41: 24847465-3 | C41: 24847465 | D41: CONDORI | E41: CHOQUE | F41: ADALID | G41: AYUDANTE GEOSINTETICOS | H41: 46034 | I41: D | J41: M | K41: 14X14 A | L41: 1790000090 | M41: 2 | N41: 2 | O41: 8 | P41: 8 | Q41: 2 | R41: 2 | S41: 2 | T41: 3 | U41: 3 | V41: 3 | W41: 3 | X41: 3 | Y41: 3 | Z41: 3 | AA41: 3 | AB41: 3 | AC41: 3 | AD41: 3 | AE41: 3 | AF41: 3 | AG41: 3 | AH41: 2 | AI41: 2 | AJ41: 2 | AK41: 2 | AL41: 2 | AM41: 2 | AN41: 2 | AO41: 2 | AP41: 2 | AR41: 0 | AS41: 14 | AT41: 14 | AU41: 0 | AV41: 0 | AW41: 0 | AX41: 0 | AY41: 2 | AZ41: 0 | BA41: 30 | BM41: 2 | BN41: 157000 | BP41: 75000 | CI41: 473333
A42: 41 | B42: 19588589-3 | C42: 19588589 | D42: CORNEJO | E42: PADILLA | F42: TOMAS PABLO | G42: PROGRAMADOR Y CONTROL | H42: 45967 | I42: I | J42: M | K42: 14x14 A | L42: 1790000090 | M42: 2 | N42: 2 | O42: 8 | P42: 8 | Q42: 2 | R42: 2 | S42: 2 | T42: 3 | U42: 3 | V42: 3 | W42: 3 | X42: 3 | Y42: 3 | Z42: 3 | AA42: 3 | AB42: 3 | AC42: 3 | AD42: 3 | AE42: 3 | AF42: 3 | AG42: 3 | AH42: 2 | AI42: 2 | AJ42: 2 | AK42: 2 | AL42: 2 | AM42: 2 | AN42: 2 | AO42: 2 | AP42: 2 | AR42: 0 | AS42: 14 | AT42: 14 | AU42: 0 | AV42: 0 | AW42: 0 | AX42: 0 | AY42: 2 | AZ42: 0 | BA42: 30 | BC42: 1670666 | BD42: 14 DIAS ADICIONALES FRACCIONADOS POR REEMPLAZO DE CONTRATURNO CON LICENCIA (3-3) | BM42: 2 | BN42: 358000 | CI42: 473333
A43: 42 | B43: 12807347-7 | C43: 12807347 | D43: CORTES | E43: MONARDES | F43: PABLO ANTONIO | G43: MAESTRO SEGUNDA GEOSINTETICOS | H43: 46003 | I43: D | J43: M | K43: 14X14 B | L43: 1790000090 | M43: 3 | N43: 3 | O43: 3 | P43: 3 | Q43: 3 | R43: 3 | S43: 3 | T43: 2 | U43: 2 | V43: 2 | W43: 2 | X43: 2 | Y43: 2 | Z43: 2 | AA43: 2 | AB43: 2 | AC43: 2 | AD43: 2 | AE43: 2 | AF43: 2 | AG43: 2 | AH43: 3 | AI43: 3 | AJ43: 3 | AK43: 3 | AL43: 3 | AM43: 3 | AN43: 3 | AO43: 3 | AP43: 3 | AR43: 0 | AS43: 14 | AT43: 16 | AU43: 0 | AV43: 0 | AW43: 0 | AX43: 0 | AY43: 0 | AZ43: 0 | BA43: 30 | BC43: 150000 | BD43: DESCANSO PENDIENTE POR CIERRE LABORAL AL 30-04-2026 | BP43: 75000 | CI43: 473333
A44: 43 | B44: 17364721-2 | C44: 17364721 | D44: CORTES | E44: LEDEZMA | F44: HERNAN EDUARDO | G44: TECNICO CONTROL CALIDAD | H44: 46003 | I44: D | J44: M | K44: 14X14 B | L44: 1790000090 | M44: 3 | N44: 3 | O44: 3 | P44: 3 | Q44: 3 | R44: 3 | S44: 3 | T44: 2 | U44: 2 | V44: 2 | W44: 2 | X44: 2 | Y44: 2 | Z44: 2 | AA44: 2 | AB44: 2 | AC44: 2 | AD44: 2 | AE44: 2 | AF44: 2 | AG44: 2 | AH44: 3 | AI44: 3 | AJ44: 3 | AK44: 3 | AL44: 3 | AM44: 3 | AN44: 3 | AO44: 3 | AP44: 3 | AR44: 0 | AS44: 14 | AT44: 16 | AU44: 0 | AV44: 0 | AW44: 0 | AX44: 0 | AY44: 0 | AZ44: 0 | BA44: 30 | BC44: 235333 | BD44: DESCANSO PENDIENTE POR CIERRE LABORAL AL 30-04-2026 | BP44: 75000 | CI44: 473333
A45: 44 | B45: 19123828-1 | C45: 19123828 | D45: ESPARZA | E45: COLLA | F45: GIOVANNI ANTONIO | G45: MAESTRO PRIMERA GEOSINTETICOS | H45: 45992 | I45: D | J45: M | K45: 14x14 A | L45: 1790000090 | M45: 2 | N45: 2 | O45: 8 | P45: 8 | Q45: 2 | R45: 2 | S45: 2 | T45: 3 | U45: 3 | V45: 3 | W45: 3 | X45: 3 | Y45: 3 | Z45: 3 | AA45: 3 | AB45: 3 | AC45: 3 | AD45: 3 | AE45: 3 | AF45: 3 | AG45: 3 | AR45: 0 | AS45: 5 | AT45: 14 | AU45: 0 | AV45: 0 | AW45: 0 | AX45: 0 | AY45: 2 | AZ45: 0 | BA45: 21 | BM45: 2 | BN45: 282400 | BP45: 52500 | CI45: 315555
A46: 45 | B46: 15802541-8 | C46: 15802541 | D46: GALLARDO | E46: ROJAS | F46: JAIME RODRIGO | G46: MAESTRO SEGUNDA GEOSINTETICOS | H46: 46006 | I46: D | J46: M | K46: 14X14 B | L46: 1790000090 | M46: 3 | N46: 3 | O46: 3 | P46: 3 | Q46: 3 | R46: 3 | S46: 3 | T46: 2 | U46: 2 | V46: 2 | W46: 2 | X46: 2 | Y46: 2 | Z46: 2 | AA46: 2 | AB46: 2 | AC46: 2 | AD46: 2 | AE46: 2 | AF46: 2 | AG46: 2 | AH46: 3 | AI46: 3 | AJ46: 3 | AK46: 3 | AL46: 3 | AM46: 3 | AN46: 3 | AO46: 3 | AP46: 3 | AR46: 0 | AS46: 14 | AT46: 16 | AU46: 0 | AV46: 0 | AW46: 0 | AX46: 0 | AY46: 0 | AZ46: 0 | BA46: 30 | BC46: 150000 | BD46: DESCANSO PENDIENTE POR CIERRE LABORAL AL 30-04-2026 | BP46: 75000 | CI46: 473333
A47: 46 | B47: 19104534-3 | C47: 19104534 | D47: GARCIA | E47: TRUJILLO | F47: JOSE GUILLERMO | G47: AYUDANTE GEOSINTETICOS | H47: 45987 | I47: D | J47: M | K47: 14x14 A | L47: 1790000090 | M47: 2 | N47: 2 | O47: 6 | P47: 6 | Q47: 6 | R47: 6 | S47: 6 | T47: 3 | U47: 3 | V47: 3 | W47: 3 | X47: 3 | Y47: 3 | Z47: 3 | AA47: 3 | AB47: 3 | AC47: 3 | AD47: 3 | AE47: 3 | AF47: 3 | AG47: 3 | AR47: 0 | AS47: 2 | AT47: 14 | AU47: 0 | AV47: 0 | AW47: 5 | AX47: 0 | AY47: 0 | AZ47: 0 | BA47: 16 | CI47: 315555
A48: 47 | B48: 25247969-4 | C48: 25247969 | D48: GARCIA | E48: BIBISCUS | F48: KAROL TATIANA | G48: TECNICO RRHH PROYECTO | H48: 45978 | I48: I | J48: F | K48: 14x14 C | L48: 1790000090 | M48: 3 | N48: 2 | O48: 8 | P48: 8 | Q48: 2 | R48: 2 | S48: 2 | T48: 2 | U48: 2 | V48: 2 | W48: 2 | X48: 2 | Y48: 2 | Z48: 2 | AA48: 3 | AB48: 3 | AC48: 3 | AD48: 3 | AE48: 3 | AF48: 3 | AG48: 3 | AH48: 3 | AI48: 3 | AJ48: 3 | AK48: 3 | AL48: 3 | AM48: 3 | AN48: 3 | AO48: 2 | AP48: 3 | AR48: 0 | AS48: 12 | AT48: 16 | AU48: 0 | AV48: 0 | AW48: 0 | AX48: 0 | AY48: 2 | AZ48: 0 | BA48: 30 | BM48: 2 | BN48: 310000 | BP48: 75000 | CI48: 473333
A49: 48 | B49: 19049850-6 | C49: 19049850 | D49: GONZALEZ | E49: VEGA | F49: ISRAEL ARON | G49: SUPERVISOR CONTROL CALIDAD | H49: 45992 | I49: I | J49: M | K49: 14x14 A | L49: 1790000090 | M49: 2 | N49: 2 | O49: 8 | P49: 8 | Q49: 2 | R49: 2 | S49: 2 | T49: 3 | U49: 3 | V49: 3 | W49: 3 | X49: 3 | Y49: 3 | Z49: 3 | AA49: 3 | AB49: 3 | AC49: 3 | AD49: 3 | AE49: 3 | AF49: 3 | AG49: 3 | AH49: 2 | AI49: 2 | AJ49: 2 | AK49: 2 | AL49: 2 | AM49: 2 | AN49: 2 | AO49: 2 | AP49: 2 | AR49: 0 | AS49: 14 | AT49: 14 | AU49: 0 | AV49: 0 | AW49: 0 | AX49: 0 | AY49: 2 | AZ49: 0 | BA49: 30 | BM49: 2 | BN49: 513000 | CI49: 473333 | CK49: 2308499 | CL49: 100000
A50: 49 | B50: 13179077-5 | C50: 13179077 | D50: GUERRERO | E50: GARCÍA | F50: PEDRO FREDDY | G50: JEFE PREVENCION DE RIESGOS | H50: 45957 | I50: I | J50: M | K50: 4X3 | L50: 1790000090 | M50: 2 | N50: 2 | O50: 3 | P50: 3 | Q50: 3 | R50: 2 | S50: 2 | T50: 2 | U50: 2 | V50: 3 | W50: 3 | X50: 3 | Y50: 2 | Z50: 2 | AA50: 2 | AB50: 2 | AC50: 3 | AD50: 3 | AE50: 3 | AF50: 2 | AG50: 2 | AH50: 2 | AI50: 2 | AJ50: 3 | AK50: 3 | AL50: 3 | AM50: 2 | AN50: 2 | AO50: 2 | AP50: 2 | AR50: 0 | AS50: 18 | AT50: 12 | AU50: 0 | AV50: 0 | AW50: 0 | AX50: 0 | AY50: 0 | AZ50: 0 | BA50: 30 | BC50: 333600 | BD50: DIA ADICIONAL PENDIENTE POR REEMPLAZO DE APR (M. IBARRA) | CI50: 473333 | CK50: 1000800 | CL50: 100000
A51: 50 | B51: 21022831-4 | C51: 21022831 | D51: HIDALGO | E51: OLIVARES | F51: CLEMENTE RAFAEL | G51: MAESTRO SEGUNDA GEOSINTETICOS | H51: 46003 | I51: D | J51: M | K51: 14X14 B | L51: 1790000090 | M51: 3 | N51: 3 | O51: 3 | P51: 3 | Q51: 3 | R51: 3 | S51: 3 | T51: 2 | U51: 2 | V51: 2 | W51: 2 | X51: 2 | Y51: 2 | Z51: 2 | AA51: 2 | AB51: 2 | AC51: 2 | AD51: 2 | AE51: 2 | AF51: 2 | AG51: 2 | AH51: 3 | AI51: 3 | AJ51: 3 | AK51: 3 | AL51: 3 | AM51: 3 | AN51: 3 | AO51: 3 | AP51: 3 | AR51: 0 | AS51: 14 | AT51: 16 | AU51: 0 | AV51: 0 | AW51: 0 | AX51: 0 | AY51: 0 | AZ51: 0 | BA51: 30 | BC51: 150000 | BD51: DESCANSO PENDIENTE POR CIERRE LABORAL AL 30-04-2026 | BP51: 75000 | CI51: 473333
A52: 51 | B52: 20684339-K | C52: 20684339 | D52: JESIOTR | E52: DIAZ | F52: JOSÉ CARLOS | G52: MAESTRO SEGUNDA CONTROL CALIDAD | H52: 45987 | I52: D | J52: M | K52: 14x14 A | L52: 1790000090 | M52: 2 | N52: 2 | O52: 8 | P52: 8 | Q52: 2 | R52: 2 | S52: 2 | T52: 3 | U52: 3 | V52: 3 | W52: 3 | X52: 3 | Y52: 3 | Z52: 3 | AA52: 3 | AB52: 3 | AC52: 3 | AD52: 3 | AE52: 3 | AF52: 3 | AG52: 3 | AR52: 0 | AS52: 5 | AT52: 14 | AU52: 0 | AV52: 0 | AW52: 0 | AX52: 0 | AY52: 2 | AZ52: 0 | BA52: 21 | BM52: 2 | BN52: 180000 | BP52: 52500 | CI52: 315555
A53: 52 | B53: 17712833-3 | C53: 17712833 | D53: JIMENEZ | E53: GAMBOA | F53: LUIS EDUARDO | G53: MAESTRO PRIMERA GEOSINTETICOS | H53: 46041 | I53: D | J53: M | K53: 14X14 B | L53: 1790000090 | M53: 3 | N53: 3 | O53: 3 | P53: 3 | Q53: 3 | R53: 3 | S53: 3 | T53: 2 | U53: 2 | V53: 2 | W53: 2 | X53: 2 | Y53: 2 | Z53: 2 | AA53: 2 | AB53: 2 | AC53: 2 | AD53: 2 | AE53: 2 | AF53: 2 | AG53: 2 | AH53: 3 | AI53: 3 | AJ53: 3 | AK53: 3 | AL53: 3 | AM53: 3 | AN53: 3 | AO53: 3 | AP53: 3 | AR53: 0 | AS53: 14 | AT53: 16 | AU53: 0 | AV53: 0 | AW53: 0 | AX53: 0 | AY53: 0 | AZ53: 0 | BA53: 30 | BC53: 235333 | BD53: DESCANSO PENDIENTE POR CIERRE LABORAL AL 30-04-2026 | BP53: 75000 | CI53: 473333
A54: 53 | B54: 18687714-4 | C54: 18687714 | D54: JIMENEZ | E54: ROCO | F54: PEDRO DANIEL | G54: MAESTRO PRIMERA GEOSINTETICOS | H54: 46054 | I54: D | J54: M | K54: 14X14 A | L54: 1790000090 | M54: 2 | N54: 2 | O54: 8 | P54: 8 | Q54: 2 | R54: 2 | S54: 2 | T54: 3 | U54: 3 | V54: 3 | W54: 3 | X54: 3 | Y54: 3 | Z54: 3 | AA54: 3 | AB54: 3 | AC54: 3 | AD54: 3 | AE54: 3 | AF54: 3 | AG54: 3 | AR54: 0 | AS54: 5 | AT54: 14 | AU54: 0 | AV54: 0 | AW54: 0 | AX54: 0 | AY54: 2 | AZ54: 0 | BA54: 21 | BM54: 2 | BN54: 282400 | BP54: 52500 | CI54: 315555
A55: 54 | B55: 19355560-8 | C55: 19355560 | D55: JIMENEZ | E55: DIAZ | F55: EDUARDO SERGIO | G55: AYUDANTE GEOSINTETICOS | H55: 45987 | I55: D | J55: M | K55: 14x14 A | L55: 1790000090 | M55: 2 | N55: 2 | O55: 8 | P55: 8 | Q55: 2 | R55: 2 | S55: 2 | T55: 3 | U55: 3 | V55: 3 | W55: 3 | X55: 3 | Y55: 3 | Z55: 3 | AA55: 3 | AB55: 3 | AC55: 3 | AD55: 3 | AE55: 3 | AF55: 3 | AG55: 3 | AH55: 2 | AI55: 2 | AJ55: 2 | AK55: 2 | AL55: 2 | AM55: 2 | AN55: 2 | AO55: 2 | AP55: 2 | AR55: 0 | AS55: 14 | AT55: 14 | AU55: 0 | AV55: 0 | AW55: 0 | AX55: 0 | AY55: 2 | AZ55: 0 | BA55: 30 | BM55: 2 | BN55: 157000 | BP55: 75000 | CI55: 473333 | CK55: 706500 | CL55: 100000
A56: 55 | B56: 18353271-5 | C56: 18353271 | D56: JOFRE | E56: JOFRE | F56: DIEGO EDUARDO | G56: TECNICO CONTROL CALIDAD | H56: 45992 | I56: D | J56: M | K56: 14x14 A | L56: 1790000090 | M56: 2 | N56: 2 | O56: 8 | P56: 8 | Q56: 2 | R56: 2 | S56: 2 | T56: 3 | U56: 3 | V56: 3 | W56: 3 | X56: 3 | Y56: 3 | Z56: 3 | AA56: 3 | AB56: 3 | AC56: 3 | AD56: 3 | AE56: 3 | AF56: 3 | AG56: 3 | AH56: 2 | AI56: 2 | AJ56: 2 | AK56: 2 | AL56: 2 | AM56: 2 | AN56: 2 | AO56: 2 | AP56: 2 | AR56: 0 | AS56: 14 | AT56: 14 | AU56: 0 | AV56: 0 | AW56: 0 | AX56: 0 | AY56: 2 | AZ56: 0 | BA56: 30 | BM56: 2 | BN56: 282400 | BP56: 75000 | CI56: 473333 | CK56: 1270799 | CL56: 100000
A57: 56 | B57: 11387365-5 | C57: 11387365 | D57: JOHNSON | E57: SUAZO | F57: CRISTIAN BENJAMIN | G57: CONDUCTOR SERVICIO | H57: 46082 | I57: I | J57: M | K57: 14X14 B | L57: 1790000090 | M57: 3 | N57: 3 | O57: 3 | P57: 3 | Q57: 3 | R57: 3 | S57: 3 | T57: 2 | U57: 2 | V57: 2 | W57: 2 | X57: 2 | Y57: 2 | Z57: 2 | AA57: 2 | AB57: 2 | AC57: 2 | AD57: 2 | AE57: 2 | AF57: 2 | AG57: 2 | AH57: 3 | AI57: 3 | AJ57: 3 | AK57: 3 | AL57: 3 | AM57: 3 | AN57: 3 | AO57: 3 | AP57: 3 | AR57: 0 | AS57: 14 | AT57: 16 | AU57: 0 | AV57: 0 | AW57: 0 | AX57: 0 | AY57: 0 | AZ57: 0 | BA57: 30 | BC57: 215000 | BD57: DESCANSO PENDIENTE POR CIERRE LABORAL AL 30-04-2026 | BP57: 75000 | CI57: 315556
A58: 57 | B58: 15575503-2 | C58: 15575503 | D58: JULIO | E58: TAPIA | F58: MANUEL ALEJANDRO | G58: MAESTRO SEGUNDA GEOSINTETICOS | H58: 46104 | I58: D | J58: M | K58: 14x14 A | L58: 1790000090 | M58: 1 | N58: 1 | O58: 1 | P58: 1 | Q58: 1 | R58: 1 | S58: 1 | T58: 3 | U58: 3 | V58: 3 | W58: 3 | X58: 3 | Y58: 3 | Z58: 3 | AA58: 3 | AB58: 3 | AR58: 7 | AS58: 0 | AT58: 9 | AU58: 0 | AV58: 0 | AW58: 0 | AX58: 0 | AY58: 0 | AZ58: 0 | BA58: 16 | CI58: 0
A59: 58 | B59: 19260480-K | C59: 19260480 | D59: LEIVA | E59: GONZALEZ | F59: CLAUDIO ANDRES | G59: ELECTROMECANICO MANTENCION | H59: 45988 | I59: I | J59: M | K59: 14x14 A | L59: 1790000090 | M59: 2 | N59: 2 | O59: 8 | P59: 8 | Q59: 2 | R59: 2 | S59: 2 | T59: 3 | U59: 3 | V59: 3 | W59: 3 | X59: 3 | Y59: 3 | Z59: 3 | AA59: 3 | AB59: 3 | AC59: 3 | AD59: 3 | AE59: 3 | AF59: 3 | AG59: 3 | AH59: 2 | AI59: 2 | AJ59: 2 | AK59: 2 | AL59: 2 | AM59: 2 | AN59: 2 | AO59: 2 | AP59: 2 | AR59: 0 | AS59: 14 | AT59: 14 | AU59: 0 | AV59: 0 | AW59: 0 | AX59: 0 | AY59: 2 | AZ59: 0 | BA59: 30 | BM59: 2 | BN59: 282400 | BP59: 75000 | CI59: 473333
A60: 59 | B60: 25179180-5 | C60: 25179180 | D60: LENIS | E60: CASTRILLON | F60: JHON FREDY | G60: TECNICO CONTROL DOCUMENTOS | H60: 45993 | I60: I | J60: M | K60: 4X3 | L60: 1790000090 | M60: 2 | N60: 2 | O60: 3 | P60: 3 | Q60: 3 | R60: 2 | S60: 2 | T60: 2 | U60: 2 | V60: 3 | W60: 3 | X60: 3 | Y60: 2 | Z60: 2 | AA60: 2 | AB60: 2 | AC60: 3 | AD60: 3 | AE60: 3 | AF60: 2 | AG60: 2 | AH60: 2 | AI60: 2 | AJ60: 3 | AK60: 3 | AL60: 3 | AM60: 2 | AN60: 2 | AO60: 2 | AP60: 2 | AR60: 0 | AS60: 18 | AT60: 12 | AU60: 0 | AV60: 0 | AW60: 0 | AX60: 0 | AY60: 0 | AZ60: 0 | BA60: 30 | BP60: 75000 | CI60: 473333
A61: 60 | B61: 15834377-0 | C61: 15834377 | D61: LEON | E61: PLAZA | F61: WILLIAMS NELSON | G61: MAESTRO SEGUNDA GEOSINTETICOS | H61: 46054 | I61: D | J61: M | K61: 14X14 A | L61: 1790000090 | M61: 2 | N61: 2 | O61: 8 | P61: 8 | Q61: 2 | R61: 2 | S61: 2 | T61: 3 | U61: 3 | V61: 3 | W61: 3 | X61: 3 | Y61: 3 | Z61: 3 | AA61: 3 | AB61: 3 | AC61: 3 | AD61: 3 | AE61: 3 | AF61: 3 | AG61: 3 | AR61: 0 | AS61: 5 | AT61: 14 | AU61: 0 | AV61: 0 | AW61: 0 | AX61: 0 | AY61: 2 | AZ61: 0 | BA61: 21 | BM61: 2 | BN61: 180000 | BP61: 52500 | CI61: 315555
A62: 61 | B62: 18316953-k | C62: 18316953 | D62: LEYTON | E62: LLANOS | F62: VICTOR MANUEL | G62: AYUDANTE GEOSINTETICOS/VIENTERO | H62: 45992 | I62: D | J62: M | K62: 14x14 A | L62: 1790000090 | M62: 2 | N62: 2 | O62: 8 | P62: 8 | Q62: 2 | R62: 2 | S62: 2 | T62: 3 | U62: 3 | V62: 3 | W62: 3 | X62: 3 | Y62: 3 | Z62: 3 | AA62: 3 | AB62: 3 | AC62: 3 | AD62: 3 | AE62: 3 | AF62: 3 | AG62: 3 | AH62: 2 | AI62: 2 | AJ62: 2 | AK62: 2 | AL62: 2 | AM62: 2 | AN62: 2 | AO62: 2 | AP62: 2 | AR62: 0 | AS62: 14 | AT62: 14 | AU62: 0 | AV62: 0 | AW62: 0 | AX62: 0 | AY62: 2 | AZ62: 0 | BA62: 30 | BE62: 62500 | BF62: Labores de Vientero | BM62: 2 | BN62: 169500 | BP62: 75000 | CI62: 473333
A63: 62 | B63: 24231740-8 | C63: 24231740 | D63: MALDONADO | E63: ANDRADE | F63: LUIS ALBERTO | G63: ASESOR PREVENCION DE RIESGOS | H63: 46041 | I63: I | J63: M | K63: 14X14 A | L63: 1790000090 | M63: 2 | N63: 2 | O63: 8 | P63: 8 | Q63: 2 | R63: 2 | S63: 2 | T63: 3 | U63: 3 | V63: 3 | W63: 3 | X63: 3 | Y63: 3 | Z63: 3 | AA63: 3 | AB63: 3 | AC63: 3 | AD63: 3 | AE63: 3 | AF63: 3 | AG63: 3 | AH63: 2 | AI63: 2 | AJ63: 2 | AK63: 2 | AL63: 2 | AM63: 2 | AN63: 2 | AO63: 2 | AP63: 2 | AR63: 0 | AS63: 14 | AT63: 14 | AU63: 0 | AV63: 0 | AW63: 0 | AX63: 0 | AY63: 2 | AZ63: 0 | BA63: 30 | BM63: 2 | BN63: 461600 | CI63: 473333
A64: 63 | B64: 17902748-8 | C64: 17902748 | D64: MARIN | E64: TRIVIÑO | F64: JOSE ANTONIO | G64: AYUDANTE GEOSINTETICOS | H64: 46035 | I64: D | J64: M | K64: 14x14 A | L64: 1790000090 | M64: 6 | N64: 6 | O64: 6 | P64: 6 | Q64: 6 | R64: 6 | S64: 6 | T64: 3 | U64: 3 | V64: 3 | W64: 3 | X64: 3 | Y64: 3 | Z64: 3 | AA64: 3 | AB64: 3 | AC64: 3 | AD64: 3 | AE64: 3 | AF64: 3 | AG64: 3 | AR64: 0 | AS64: 0 | AT64: 14 | AU64: 0 | AV64: 0 | AW64: 7 | AX64: 0 | AY64: 0 | AZ64: 0 | BA64: 14 | CI64: 315555
A65: 64 | B65: 13419327-1 | C65: 13419327 | D65: MIRANDA | E65: MERCADO | F65: MARCO ANTONIO | G65: SUPERVISOR GEOSINTETICOS | H65: 45962 | I65: I | J65: M | K65: 14x14 A | L65: 1790000090 | M65: 2 | N65: 2 | O65: 8 | P65: 8 | Q65: 2 | R65: 2 | S65: 2 | T65: 3 | U65: 3 | V65: 3 | W65: 3 | X65: 3 | Y65: 3 | Z65: 3 | AA65: 3 | AB65: 3 | AC65: 3 | AD65: 3 | AE65: 3 | AF65: 3 | AG65: 3 | AH65: 2 | AI65: 2 | AJ65: 2 | AK65: 2 | AL65: 2 | AM65: 2 | AN65: 2 | AO65: 2 | AP65: 2 | AR65: 0 | AS65: 14 | AT65: 14 | AU65: 0 | AV65: 0 | AW65: 0 | AX65: 0 | AY65: 2 | AZ65: 0 | BA65: 30 | BE65: 792000 | BF65: Bono acuerdo salarial | BM65: 2 | BN65: 512000 | CI65: 473333
A66: 65 | B66: 15043532-3 | C66: 15043532 | D66: MUÑOZ | E66: BUGUEÑO | F66: AGUSTIN EDGARD | G66: MAESTRO PRIMERA GEOSINTETICOS | H66: 46082 | I66: D | J66: M | K66: 14X14 A | L66: 1790000090 | M66: 2 | N66: 2 | O66: 8 | P66: 8 | Q66: 2 | R66: 2 | S66: 2 | T66: 3 | U66: 3 | V66: 3 | W66: 3 | X66: 3 | Y66: 3 | Z66: 3 | AA66: 3 | AB66: 3 | AC66: 3 | AD66: 3 | AE66: 3 | AF66: 3 | AG66: 3 | AH66: 2 | AI66: 2 | AJ66: 2 | AK66: 2 | AL66: 2 | AM66: 2 | AN66: 2 | AO66: 2 | AP66: 2 | AR66: 0 | AS66: 14 | AT66: 14 | AU66: 0 | AV66: 0 | AW66: 0 | AX66: 0 | AY66: 2 | AZ66: 0 | BA66: 30 | BM66: 2 | BN66: 282400 | BP66: 75000 | CI66: 315556 | CK66: 1270799 | CL66: 100000
A67: 66 | B67: 21463925-4 | C67: 21463925 | D67: NUÑEZ | E67: DELGADO | F67: MAICOL ANDRES | G67: MAESTRO SEGUNDA GEOSINTETICOS | H67: 46006 | I67: D | J67: M | K67: 14X14 B | L67: 1790000090 | M67: 3 | N67: 3 | O67: 3 | P67: 3 | Q67: 3 | R67: 3 | S67: 3 | T67: 2 | U67: 2 | V67: 2 | W67: 2 | X67: 2 | Y67: 2 | Z67: 2 | AA67: 2 | AB67: 2 | AC67: 2 | AD67: 2 | AE67: 2 | AF67: 2 | AG67: 2 | AH67: 3 | AI67: 3 | AJ67: 3 | AK67: 3 | AL67: 3 | AM67: 3 | AN67: 3 | AO67: 3 | AP67: 3 | AR67: 0 | AS67: 14 | AT67: 16 | AU67: 0 | AV67: 0 | AW67: 0 | AX67: 0 | AY67: 0 | AZ67: 0 | BA67: 30 | BC67: 150000 | BD67: DESCANSO PENDIENTE POR CIERRE LABORAL AL 30-04-2026 | BP67: 75000 | CI67: 473333
A68: 67 | B68: 18353767-9 | C68: 18353767 | D68: OCHOA | E68: ADAROS | F68: CAMILA ISABEL | G68: ASESOR PREVENCION DE RIESGOS | H68: 45992 | I68: I | J68: F | K68: 14x14 B | L68: 1790000090 | M68: 3 | N68: 3 | O68: 3 | P68: 3 | Q68: 3 | R68: 3 | S68: 3 | T68: 2 | U68: 2 | V68: 2 | W68: 2 | X68: 2 | Y68: 2 | Z68: 2 | AA68: 2 | AB68: 2 | AC68: 2 | AD68: 2 | AE68: 2 | AF68: 2 | AG68: 2 | AH68: 3 | AI68: 3 | AJ68: 3 | AK68: 3 | AL68: 3 | AM68: 3 | AN68: 3 | AO68: 3 | AP68: 3 | AR68: 0 | AS68: 14 | AT68: 16 | AU68: 0 | AV68: 0 | AW68: 0 | AX68: 0 | AY68: 0 | AZ68: 0 | BA68: 30 | BC68: 384667 | BD68: DESCANSO PENDIENTE POR CIERRE LABORAL AL 30-04-2026 | CI68: 473333
A69: 68 | B69: 16518571-4 | C69: 16518571 | D69: ORTEGA | E69: VALDERRAMA | F69: MARCELO ALEJANDRO | G69: RIGGER | H69: 46054 | I69: D | J69: M | K69: 14X14 B | L69: 1790000090 | M69: 3 | N69: 3 | O69: 3 | P69: 3 | Q69: 3 | R69: 3 | S69: 3 | T69: 2 | U69: 2 | V69: 2 | W69: 2 | X69: 2 | Y69: 2 | Z69: 2 | AA69: 2 | AB69: 2 | AC69: 2 | AD69: 2 | AE69: 2 | AF69: 2 | AG69: 2 | AH69: 3 | AI69: 3 | AJ69: 3 | AK69: 3 | AL69: 3 | AM69: 3 | AN69: 3 | AO69: 3 | AP69: 3 | AR69: 0 | AS69: 14 | AT69: 16 | AU69: 0 | AV69: 0 | AW69: 0 | AX69: 0 | AY69: 0 | AZ69: 0 | BA69: 30 | BC69: 235333 | BD69: DESCANSO PENDIENTE POR CIERRE LABORAL AL 30-04-2026 | BP69: 75000 | CI69: 473333
A70: 69 | B70: 13218666-9 | C70: 13218666 | D70: OYARCE | E70: CARVAJAL | F70: LUIS RICARDO | G70: TECNICO CONTROL CALIDAD | H70: 46092 | I70: D | J70: M | K70: 14X14 A | L70: 1790000090 | M70: 2 | N70: 2 | O70: 8 | P70: 8 | Q70: 2 | R70: 2 | S70: 2 | T70: 3 | U70: 3 | V70: 3 | W70: 3 | X70: 3 | Y70: 3 | Z70: 3 | AA70: 3 | AB70: 3 | AC70: 3 | AD70: 3 | AE70: 3 | AF70: 3 | AG70: 3 | AR70: 0 | AS70: 5 | AT70: 14 | AU70: 0 | AV70: 0 | AW70: 0 | AX70: 0 | AY70: 2 | AZ70: 0 | BA70: 21 | BM70: 2 | BN70: 282400 | BP70: 52500 | CI70: 0
A71: 70 | B71: 18217453-K | C71: 18217453 | D71: PASTEN | E71: GUZMAN | F71: JAIRO BRAYAN | G71: AYUDANTE GEOSINTETICOS | H71: 45992 | I71: D | J71: M | K71: 14x14 A | L71: 1790000090 | M71: 6 | N71: 6 | O71: 6 | P71: 6 | Q71: 6 | R71: 6 | S71: 6 | T71: 3 | U71: 3 | V71: 3 | W71: 3 | X71: 3 | Y71: 3 | Z71: 3 | AA71: 3 | AB71: 3 | AC71: 3 | AD71: 3 | AE71: 3 | AF71: 3 | AG71: 3 | AR71: 0 | AS71: 0 | AT71: 14 | AU71: 0 | AV71: 0 | AW71: 7 | AX71: 0 | AY71: 0 | AZ71: 0 | BA71: 14 | CI71: 315555
A72: 71 | B72: 15043166-2 | C72: 15043166 | D72: PEREIRA | E72: CORTES | F72: HUGO SALATIER | G72: AYUDANTE GEOSINTETICOS | H72: 45997 | I72: D | J72: M | K72: 14x14 B | L72: 1790000090 | M72: 3 | N72: 3 | O72: 3 | P72: 3 | Q72: 3 | R72: 3 | S72: 3 | T72: 2 | U72: 2 | V72: 2 | W72: 2 | X72: 2 | Y72: 2 | Z72: 2 | AA72: 2 | AB72: 2 | AC72: 2 | AD72: 2 | AE72: 2 | AF72: 2 | AG72: 2 | AH72: 3 | AI72: 3 | AJ72: 3 | AK72: 3 | AL72: 3 | AM72: 3 | AN72: 3 | AO72: 3 | AP72: 3 | AR72: 0 | AS72: 14 | AT72: 16 | AU72: 0 | AV72: 0 | AW72: 0 | AX72: 0 | AY72: 0 | AZ72: 0 | BA72: 30 | BC72: 130833 | BD72: DESCANSO PENDIENTE POR CIERRE LABORAL AL 30-04-2026 | BP72: 75000 | CI72: 473333 | CJ72: 213354
A73: 72 | B73: 12572374-8 | C73: 12572374 | D73: PEREZ | E73: CARVAJAL | F73: ALBERTO HERNAN | G73: CONDUCTOR SERVICIO | H73: 46082 | I73: I | J73: M | K73: 14X14 A | L73: 1790000090 | M73: 2 | N73: 2 | O73: 8 | P73: 8 | Q73: 2 | R73: 2 | S73: 2 | T73: 3 | U73: 3 | V73: 3 | W73: 3 | X73: 3 | Y73: 3 | Z73: 3 | AA73: 3 | AB73: 3 | AC73: 3 | AD73: 3 | AE73: 3 | AF73: 3 | AG73: 3 | AR73: 0 | AS73: 5 | AT73: 14 | AU73: 0 | AV73: 0 | AW73: 0 | AX73: 0 | AY73: 2 | AZ73: 0 | BA73: 21 | BM73: 2 | BN73: 258000 | BP73: 52500 | CI73: 157778
A74: 73 | B74: 16687732-6 | C74: 16687732 | D74: PEREZ | E74: CALLEJAS | F74: HERMAN ENRIQUE | G74: MAESTRO SEGUNDA GEOSINTETICOS | H74: 46041 | I74: D | J74: M | K74: 14X14 B | L74: 1790000090 | M74: 3 | N74: 3 | O74: 3 | P74: 3 | Q74: 3 | R74: 3 | S74: 3 | T74: 2 | U74: 2 | V74: 2 | W74: 2 | X74: 2 | Y74: 2 | Z74: 2 | AA74: 2 | AB74: 2 | AC74: 2 | AD74: 2 | AE74: 2 | AF74: 2 | AG74: 2 | AH74: 3 | AI74: 3 | AJ74: 3 | AK74: 3 | AL74: 3 | AM74: 3 | AN74: 3 | AO74: 3 | AP74: 3 | AR74: 0 | AS74: 14 | AT74: 16 | AU74: 0 | AV74: 0 | AW74: 0 | AX74: 0 | AY74: 0 | AZ74: 0 | BA74: 30 | BC74: 150000 | BD74: DESCANSO PENDIENTE POR CIERRE LABORAL AL 30-04-2026 | BP74: 75000 | CI74: 473333
A75: 74 | B75: 20501895-6 | C75: 20501895 | D75: PEREZ | E75: REBOLLEDO | F75: SEBASTIÁN ISRAEL | G75: AYUDANTE GEOSINTETICOS/VIENTERO | H75: 45981 | I75: D | J75: M | K75: 14x14 A | L75: 1790000090 | M75: 2 | N75: 2 | O75: 8 | P75: 8 | Q75: 2 | R75: 2 | S75: 2 | T75: 3 | U75: 3 | V75: 3 | W75: 3 | X75: 3 | Y75: 3 | Z75: 3 | AA75: 3 | AB75: 3 | AC75: 3 | AD75: 3 | AE75: 3 | AF75: 3 | AG75: 3 | AR75: 0 | AS75: 5 | AT75: 14 | AU75: 0 | AV75: 0 | AW75: 0 | AX75: 0 | AY75: 2 | AZ75: 0 | BA75: 21 | BE75: 43750 | BF75: Labores de Vientero | BM75: 2 | BN75: 169500 | BP75: 52500 | CI75: 315555
A76: 75 | B76: 12397806-4 | C76: 12397806 | D76: RAMIREZ | E76: ORTEGA | F76: JUAN SIMON | G76: MAESTRO SEGUNDA GEOSINTETICOS | H76: 46064 | I76: D | J76: M | K76: 14X14 A | L76: 1790000090 | M76: 2 | N76: 2 | O76: 8 | P76: 8 | Q76: 2 | R76: 2 | S76: 2 | T76: 3 | U76: 3 | V76: 3 | W76: 3 | X76: 3 | Y76: 3 | Z76: 3 | AA76: 3 | AB76: 3 | AC76: 3 | AD76: 3 | AE76: 3 | AF76: 3 | AG76: 3 | AR76: 0 | AS76: 5 | AT76: 14 | AU76: 0 | AV76: 0 | AW76: 0 | AX76: 0 | AY76: 2 | AZ76: 0 | BA76: 21 | BM76: 2 | BN76: 180000 | BP76: 52500 | CI76: 157778
A77: 76 | B77: 20999190-k | C77: 20999190 | D77: RAMIREZ | E77: CARVAJAL | F77: MARIO ANGEL | G77: AYUDANTE GEOSINTETICOS/VIENTERO | H77: 46003 | I77: D | J77: M | K77: 14X14 B | L77: 1790000090 | M77: 3 | N77: 3 | O77: 3 | P77: 3 | Q77: 3 | R77: 3 | S77: 3 | T77: 2 | U77: 2 | V77: 2 | W77: 2 | X77: 2 | Y77: 2 | Z77: 2 | AA77: 2 | AB77: 2 | AC77: 2 | AD77: 2 | AE77: 2 | AF77: 2 | AG77: 2 | AH77: 3 | AI77: 3 | AJ77: 3 | AK77: 3 | AL77: 3 | AM77: 3 | AN77: 3 | AO77: 3 | AP77: 3 | AR77: 0 | AS77: 14 | AT77: 16 | AU77: 0 | AV77: 0 | AW77: 0 | AX77: 0 | AY77: 0 | AZ77: 0 | BA77: 30 | BC77: 141250 | BD77: DESCANSO PENDIENTE POR CIERRE LABORAL AL 30-04-2026 | BE77: 62500 | BF77: Labores de Vientero | BP77: 75000 | CI77: 473333 | CJ77: 213354
A78: 77 | B78: 20229876-1 | C78: 20229876 | D78: REVECO | E78: VALENZUELA | F78: OMAR FRANCISCO | G78: AYUDANTE GEOSINTETICOS | H78: 45987 | I78: D | J78: M | K78: 14x14 A | L78: 1790000090 | M78: 2 | N78: 2 | O78: 8 | P78: 8 | Q78: 2 | R78: 2 | S78: 2 | T78: 3 | U78: 3 | V78: 3 | W78: 3 | X78: 3 | Y78: 3 | Z78: 3 | AA78: 3 | AB78: 3 | AC78: 3 | AD78: 3 | AE78: 3 | AF78: 3 | AG78: 3 | AR78: 0 | AS78: 5 | AT78: 14 | AU78: 0 | AV78: 0 | AW78: 0 | AX78: 0 | AY78: 2 | AZ78: 0 | BA78: 21 | BM78: 2 | BN78: 157000 | BP78: 52500 | CI78: 315555
A79: 78 | B79: 18968220-4 | C79: 18968220 | D79: RIVERA | E79: JULIO | F79: FRANCISCO ALEJANDRO | G79: AYUDANTE GEOSINTETICOS | H79: 45992 | I79: D | J79: M | K79: 14x14 A | L79: 1790000090 | M79: 2 | N79: 2 | O79: 8 | P79: 8 | Q79: 2 | R79: 2 | S79: 2 | T79: 3 | U79: 3 | V79: 3 | W79: 3 | X79: 3 | Y79: 3 | Z79: 3 | AA79: 3 | AB79: 3 | AC79: 3 | AD79: 3 | AE79: 3 | AF79: 3 | AG79: 3 | AH79: 2 | AI79: 2 | AJ79: 2 | AK79: 2 | AL79: 2 | AM79: 2 | AN79: 2 | AO79: 2 | AP79: 2 | AR79: 0 | AS79: 14 | AT79: 14 | AU79: 0 | AV79: 0 | AW79: 0 | AX79: 0 | AY79: 2 | AZ79: 0 | BA79: 30 | BM79: 2 | BN79: 157000 | BP79: 75000 | CI79: 473333
A80: 79 | B80: 17362561-8 | C80: 17362561 | D80: ROJAS | E80: ACUÑA | F80: SEBASTIAN ALEJANDRO | G80: AYUDANTE GEOSINTETICOS/VIENTERO | H80: 45992 | I80: D | J80: M | K80: 14x14 A | L80: 1790000090 | M80: 2 | N80: 2 | O80: 8 | P80: 8 | Q80: 2 | R80: 2 | S80: 2 | T80: 3 | U80: 3 | V80: 3 | W80: 3 | X80: 3 | Y80: 3 | Z80: 3 | AA80: 3 | AB80: 3 | AC80: 3 | AD80: 3 | AE80: 3 | AF80: 3 | AG80: 3 | AH80: 2 | AI80: 2 | AJ80: 2 | AK80: 2 | AL80: 2 | AM80: 2 | AN80: 2 | AO80: 2 | AP80: 2 | AR80: 0 | AS80: 14 | AT80: 14 | AU80: 0 | AV80: 0 | AW80: 0 | AX80: 0 | AY80: 2 | AZ80: 0 | BA80: 30 | BE80: 62500 | BF80: Labores de Vientero | BM80: 2 | BN80: 169500 | BP80: 75000 | CI80: 473333
A81: 80 | B81: 21624367-6 | C81: 21624367 | D81: ROJAS | E81: ARAYA | F81: CARLOS HELENBER | G81: AYUDANTE GEOSINTETICOS/VIENTERO | H81: 46003 | I81: D | J81: M | K81: 14X14 B | L81: 1790000090 | M81: 3 | N81: 3 | O81: 3 | P81: 3 | Q81: 3 | R81: 3 | S81: 3 | T81: 2 | U81: 2 | V81: 2 | W81: 2 | X81: 2 | Y81: 2 | Z81: 2 | AA81: 2 | AB81: 2 | AC81: 2 | AD81: 2 | AE81: 2 | AF81: 2 | AG81: 2 | AH81: 3 | AI81: 3 | AJ81: 3 | AK81: 3 | AL81: 3 | AM81: 3 | AN81: 3 | AO81: 3 | AP81: 3 | AR81: 0 | AS81: 14 | AT81: 16 | AU81: 0 | AV81: 0 | AW81: 0 | AX81: 0 | AY81: 0 | AZ81: 0 | BA81: 30 | BC81: 141250 | BD81: DESCANSO PENDIENTE POR CIERRE LABORAL AL 30-04-2026 | BE81: 62500 | BF81: Labores de Vientero | BP81: 75000 | CI81: 473333 | CJ81: 213354
A82: 81 | B82: 20517481-8 | C82: 20517481 | D82: ROJAS | E82: ROJAS | F82: EMILIO ESTEBAN | G82: AYUDANTE GEOSINTETICOS | H82: 46003 | I82: D | J82: M | K82: 14X14 B | L82: 1790000090 | M82: 3 | N82: 3 | O82: 3 | P82: 3 | Q82: 3 | R82: 3 | S82: 3 | T82: 6 | U82: 2 | V82: 2 | W82: 2 | X82: 2 | Y82: 2 | Z82: 2 | AA82: 2 | AB82: 2 | AC82: 2 | AD82: 2 | AE82: 2 | AF82: 2 | AG82: 2 | AH82: 3 | AI82: 3 | AJ82: 3 | AK82: 3 | AL82: 3 | AM82: 3 | AN82: 3 | AO82: 3 | AP82: 3 | AR82: 0 | AS82: 13 | AT82: 16 | AU82: 0 | AV82: 0 | AW82: 1 | AX82: 0 | AY82: 0 | AZ82: 0 | BA82: 29 | BC82: 130833 | BD82: DESCANSO PENDIENTE POR CIERRE LABORAL AL 30-04-2026 | CI82: 473333 | CJ82: 213354
A83: 82 | B83: 28087199-0 | C83: 28087199 | D83: SANCHEZ | E83: CACERES | F83: JHURGEN ADRIAN | G83: OPERADOR RETROEXCAVADORA | H83: 46357 | I83: D | J83: M | K83: 14x14 A | L83: 1790000090 | M83: 2 | N83: 2 | O83: 8 | P83: 8 | Q83: 2 | R83: 2 | S83: 2 | T83: 3 | U83: 3 | V83: 3 | W83: 3 | X83: 3 | Y83: 3 | Z83: 3 | AA83: 3 | AB83: 3 | AC83: 3 | AD83: 3 | AE83: 3 | AF83: 3 | AG83: 3 | AR83: 0 | AS83: 5 | AT83: 14 | AU83: 0 | AV83: 0 | AW83: 0 | AX83: 0 | AY83: 2 | AZ83: 0 | BA83: 21 | BM83: 2 | BN83: 310000 | BP83: 52500 | CI83: 315555
A84: 83 | B84: 23983246-6 | C84: 23983246 | D84: SANTOS | E84: HERAS | F84: KEVIN LEONEL | G84: MAESTRO SEGUNDA GEOSINTETICOS | H84: 46082 | I84: D | J84: M | K84: 14X14 A | L84: 1790000090 | M84: 2 | N84: 2 | O84: 8 | P84: 8 | Q84: 2 | R84: 2 | S84: 2 | T84: 3 | U84: 3 | V84: 3 | W84: 3 | X84: 3 | Y84: 3 | Z84: 3 | AA84: 3 | AB84: 3 | AC84: 3 | AD84: 3 | AE84: 3 | AF84: 3 | AG84: 3 | AR84: 0 | AS84: 5 | AT84: 14 | AU84: 0 | AV84: 0 | AW84: 0 | AX84: 0 | AY84: 2 | AZ84: 0 | BA84: 21 | BM84: 2 | BN84: 180000 | BP84: 52500 | CI84: 157778
A85: 84 | B85: 10147391-0 | C85: 10147391 | D85: SEGOVIA | E85: GUERRA | F85: PEDRO ENRIQUE | G85: AYUDANTE GEOSINTETICOS | H85: 45992 | I85: D | J85: M | K85: 14X14 B | L85: 1790000090 | M85: 3 | N85: 3 | O85: 3 | P85: 3 | Q85: 3 | R85: 3 | S85: 3 | T85: 2 | U85: 2 | V85: 2 | W85: 2 | X85: 2 | Y85: 2 | Z85: 2 | AA85: 2 | AB85: 2 | AC85: 2 | AD85: 2 | AE85: 2 | AF85: 2 | AG85: 2 | AH85: 3 | AI85: 3 | AJ85: 3 | AK85: 3 | AL85: 3 | AM85: 3 | AN85: 3 | AO85: 3 | AP85: 3 | AR85: 0 | AS85: 14 | AT85: 16 | AU85: 0 | AV85: 0 | AW85: 0 | AX85: 0 | AY85: 0 | AZ85: 0 | BA85: 30 | BC85: 130833 | BD85: DESCANSO PENDIENTE POR CIERRE LABORAL AL 30-04-2026 | BP85: 75000 | CI85: 473333 | CJ85: 213354
A86: 85 | B86: 18353315-0 | C86: 18353315 | D86: SEGOVIA | E86: ALFARO | F86: FABIAN EDGARDO | G86: MAESTRO SEGUNDA GEOSINTETICOS | H86: 46023 | I86: D | J86: M | K86: 14x14 A | L86: 1790000090 | M86: 2 | N86: 2 | O86: 8 | P86: 8 | Q86: 2 | R86: 2 | S86: 2 | T86: 3 | U86: 3 | V86: 3 | W86: 3 | X86: 3 | Y86: 3 | Z86: 3 | AA86: 3 | AB86: 3 | AC86: 3 | AD86: 3 | AE86: 3 | AF86: 3 | AG86: 3 | AR86: 0 | AS86: 5 | AT86: 14 | AU86: 0 | AV86: 0 | AW86: 0 | AX86: 0 | AY86: 2 | AZ86: 0 | BA86: 21 | BM86: 2 | BN86: 180000 | BP86: 52500 | CI86: 315555
A87: 86 | B87: 15982591-4 | C87: 15982591 | D87: SIARES | E87: GUZMÁN | F87: RICHARD ALEXANDER | G87: ADMINISTRADOR DE CONTRATOS | H87: 45962 | I87: I | J87: M | K87: 4X3 | L87: 1790000090 | M87: 2 | N87: 2 | O87: 3 | P87: 3 | Q87: 3 | R87: 2 | S87: 2 | T87: 2 | U87: 2 | V87: 3 | W87: 3 | X87: 3 | Y87: 2 | Z87: 2 | AA87: 2 | AB87: 2 | AC87: 3 | AD87: 3 | AE87: 3 | AF87: 2 | AG87: 2 | AH87: 2 | AI87: 2 | AJ87: 3 | AK87: 3 | AL87: 3 | AM87: 2 | AN87: 2 | AO87: 2 | AP87: 2 | AR87: 0 | AS87: 18 | AT87: 12 | AU87: 0 | AV87: 0 | AW87: 0 | AX87: 0 | AY87: 0 | AZ87: 0 | BA87: 30 | BE87: 940000 | BF87: Bono acuerdo salarial | CI87: 473333
A88: 87 | B88: 27900677-1 | C88: 27900677 | D88: SORUCO | E88: CANDIA | F88: CARLOS DAVID | G88: AYUDANTE GEOSINTETICOS | H88: 46082 | I88: D | J88: M | K88: 14X14 A | L88: 1790000090 | M88: 2 | N88: 2 | O88: 8 | P88: 8 | Q88: 2 | R88: 2 | S88: 2 | T88: 3 | U88: 3 | V88: 3 | W88: 3 | X88: 3 | Y88: 3 | Z88: 3 | AA88: 3 | AB88: 3 | AC88: 3 | AD88: 3 | AE88: 3 | AF88: 3 | AG88: 3 | AR88: 0 | AS88: 5 | AT88: 14 | AU88: 0 | AV88: 0 | AW88: 0 | AX88: 0 | AY88: 2 | AZ88: 0 | BA88: 21 | BM88: 2 | BN88: 157000 | BP88: 52500 | CI88: 157778
A89: 88 | B89: 15876024-k | C89: 15876024 | D89: STUARDO | E89: SEPULVEDA | F89: MANUEL ANTONIO | G89: MAESTRO SEGUNDA CONTROL CALIDAD | H89: 46069 | I89: D | J89: M | K89: 14X14 B | L89: 1790000090 | M89: 3 | N89: 3 | O89: 3 | P89: 3 | Q89: 3 | R89: 3 | S89: 3 | T89: 2 | U89: 2 | V89: 2 | W89: 2 | X89: 2 | Y89: 2 | Z89: 2 | AA89: 2 | AB89: 2 | AC89: 2 | AD89: 2 | AE89: 2 | AF89: 2 | AG89: 2 | AH89: 3 | AI89: 3 | AJ89: 3 | AK89: 3 | AL89: 3 | AM89: 3 | AN89: 3 | AO89: 3 | AP89: 3 | AR89: 0 | AS89: 14 | AT89: 16 | AU89: 0 | AV89: 0 | AW89: 0 | AX89: 0 | AY89: 0 | AZ89: 0 | BA89: 30 | BC89: 150000 | BD89: DESCANSO PENDIENTE POR CIERRE LABORAL AL 30-04-2026 | BP89: 75000 | CI89: 315556
A90: 89 | B90: 18444978-1 | C90: 18444978 | D90: TALAMILLA | E90: TALAMILLA | F90: FRANCISCO JAVIER | G90: MAESTRO PRIMERA GEOSINTETICOS | H90: 45987 | I90: D | J90: M | K90: 14x14 A | L90: 1790000090 | M90: 2 | N90: 2 | O90: 8 | P90: 8 | Q90: 2 | R90: 2 | S90: 2 | T90: 3 | U90: 3 | V90: 3 | W90: 3 | X90: 3 | Y90: 3 | Z90: 3 | AA90: 3 | AB90: 3 | AC90: 3 | AD90: 3 | AE90: 3 | AF90: 3 | AG90: 3 | AR90: 0 | AS90: 5 | AT90: 14 | AU90: 0 | AV90: 0 | AW90: 0 | AX90: 0 | AY90: 2 | AZ90: 0 | BA90: 21 | BM90: 2 | BN90: 282400 | BP90: 52500 | CI90: 315555
A91: 90 | B91: 19046867-4 | C91: 19046867 | D91: TAPIA | E91: AGUILERA | F91: SEBASTIAN ALEJANDRO | G91: AYUDANTE GEOSINTETICOS | H91: 45987 | I91: D | J91: M | K91: 14x14 A | L91: 1790000090 | M91: 2 | N91: 2 | O91: 8 | P91: 8 | Q91: 2 | R91: 2 | S91: 2 | T91: 3 | U91: 3 | V91: 3 | W91: 3 | X91: 3 | Y91: 3 | Z91: 3 | AA91: 3 | AB91: 3 | AC91: 3 | AD91: 3 | AE91: 3 | AF91: 3 | AG91: 3 | AR91: 0 | AS91: 5 | AT91: 14 | AU91: 0 | AV91: 0 | AW91: 0 | AX91: 0 | AY91: 2 | AZ91: 0 | BA91: 21 | BM91: 2 | BN91: 157000 | BP91: 52500 | CI91: 315555
A92: 91 | B92: 13534540-7 | C92: 13534540 | D92: TORO | E92: VARAS | F92: JORGE ARMANDO | G92: AYUDANTE GEOSINTETICOS | H92: 45992 | I92: D | J92: M | K92: 14x14 B | L92: 1790000090 | M92: 3 | N92: 3 | O92: 3 | P92: 3 | Q92: 3 | R92: 3 | S92: 3 | T92: 2 | U92: 2 | V92: 2 | W92: 2 | X92: 2 | Y92: 2 | Z92: 2 | AA92: 2 | AB92: 2 | AC92: 2 | AD92: 2 | AE92: 2 | AF92: 2 | AG92: 2 | AH92: 3 | AI92: 3 | AJ92: 3 | AK92: 3 | AL92: 3 | AM92: 3 | AN92: 3 | AO92: 3 | AP92: 3 | AR92: 0 | AS92: 14 | AT92: 16 | AU92: 0 | AV92: 0 | AW92: 0 | AX92: 0 | AY92: 0 | AZ92: 0 | BA92: 30 | BC92: 130833 | BD92: DESCANSO PENDIENTE POR CIERRE LABORAL AL 30-04-2026 | BP92: 75000 | CI92: 473333 | CJ92: 213354
A93: 92 | B93: 13976044-1 | C93: 13976044 | D93: VALENZUELA | E93: SEGOVIA | F93: RODRIGO ANTONIO | G93: MAESTRO PRIMERA GEOSINTETICOS | H93: 45997 | I93: D | J93: M | K93: 14x14 B | L93: 1790000090 | M93: 3 | N93: 3 | O93: 3 | P93: 3 | Q93: 3 | R93: 3 | S93: 3 | T93: 2 | U93: 2 | V93: 2 | W93: 2 | X93: 2 | Y93: 2 | Z93: 2 | AA93: 2 | AB93: 2 | AC93: 2 | AD93: 2 | AE93: 2 | AF93: 2 | AG93: 2 | AH93: 3 | AI93: 3 | AJ93: 3 | AK93: 3 | AL93: 3 | AM93: 3 | AN93: 3 | AO93: 3 | AP93: 3 | AR93: 0 | AS93: 14 | AT93: 16 | AU93: 0 | AV93: 0 | AW93: 0 | AX93: 0 | AY93: 0 | AZ93: 0 | BA93: 30 | BC93: 235333 | BD93: DESCANSO PENDIENTE POR CIERRE LABORAL AL 30-04-2026 | BP93: 75000 | CI93: 473333
A94: 93 | B94: 16538795-3 | C94: 16538795 | D94: VASQUEZ | E94: BRAVO | F94: LUIS ALEXIS FERNANDO | G94: CAPATAZ GEOSINTETICOS | H94: 45992 | I94: D | J94: M | K94: 14x14 A | L94: 1790000090 | M94: 2 | N94: 2 | O94: 8 | P94: 8 | Q94: 2 | R94: 2 | S94: 2 | T94: 3 | U94: 3 | V94: 3 | W94: 3 | X94: 3 | Y94: 3 | Z94: 3 | AA94: 3 | AB94: 3 | AC94: 3 | AD94: 3 | AE94: 3 | AF94: 3 | AG94: 3 | AH94: 2 | AI94: 2 | AJ94: 2 | AK94: 2 | AL94: 2 | AM94: 2 | AN94: 2 | AO94: 2 | AP94: 2 | AR94: 0 | AS94: 14 | AT94: 14 | AU94: 0 | AV94: 0 | AW94: 0 | AX94: 0 | AY94: 2 | AZ94: 0 | BA94: 30 | BM94: 2 | BN94: 320000 | BP94: 75000 | CI94: 473333
A95: 94 | B95: 19863925-7 | C95: 19863925 | D95: VEGA | E95: CONTRERAS | F95: DANISSA ALEJANDRA | G95: ADMINISTRATIVO PREVENCION DE RIESGOS | H95: 45957 | I95: I | J95: F | K95: 14x14 D | L95: 1790000090 | M95: 3 | N95: 3 | O95: 3 | P95: 3 | Q95: 3 | R95: 3 | S95: 3 | T95: 3 | U95: 3 | V95: 3 | W95: 3 | X95: 3 | Y95: 3 | Z95: 3 | AA95: 4 | AB95: 4 | AC95: 4 | AD95: 4 | AE95: 4 | AF95: 4 | AG95: 4 | AH95: 4 | AI95: 4 | AJ95: 4 | AK95: 4 | AL95: 4 | AM95: 4 | AN95: 4 | AO95: 3 | AP95: 3 | AR95: 0 | AS95: 0 | AT95: 16 | AU95: 14 | AV95: 0 | AW95: 0 | AX95: 0 | AY95: 0 | AZ95: 0 | BA95: 16 | CI95: 473333
A96: 95 | B96: 13330676-5 | C96: 13330676 | D96: VEGA | E96: JIMENEZ | F96: JUAN CARLOS | G96: CAPATAZ GEOSINTETICOS | H96: 46054 | I96: D | J96: M | K96: 14X14 A | L96: 1790000090 | M96: 2 | N96: 2 | O96: 8 | P96: 8 | Q96: 2 | R96: 2 | S96: 2 | T96: 3 | U96: 3 | V96: 3 | W96: 3 | X96: 3 | Y96: 3 | Z96: 3 | AA96: 3 | AB96: 3 | AC96: 3 | AD96: 3 | AE96: 3 | AF96: 3 | AG96: 3 | AR96: 0 | AS96: 5 | AT96: 14 | AU96: 0 | AV96: 0 | AW96: 0 | AX96: 0 | AY96: 2 | AZ96: 0 | BA96: 21 | BM96: 2 | BN96: 320000 | BP96: 52500 | CI96: 315555
A97: 96 | B97: 20406991-3 | C97: 20406991 | D97: VELIZ | E97: CASTILLO | F97: FELIPE ANDRES | G97: ELECTROMECANICO MANTENCION | H97: 45992 | I97: I | J97: M | K97: 14x14 B | L97: 1790000090 | M97: 3 | N97: 3 | O97: 3 | P97: 3 | Q97: 3 | R97: 3 | S97: 3 | T97: 2 | U97: 2 | V97: 2 | W97: 2 | X97: 2 | Y97: 2 | Z97: 2 | AA97: 2 | AB97: 2 | AC97: 2 | AD97: 2 | AE97: 2 | AF97: 2 | AG97: 2 | AH97: 3 | AI97: 3 | AJ97: 3 | AK97: 3 | AL97: 3 | AM97: 3 | AN97: 3 | AO97: 3 | AP97: 3 | AR97: 0 | AS97: 14 | AT97: 16 | AU97: 0 | AV97: 0 | AW97: 0 | AX97: 0 | AY97: 0 | AZ97: 0 | BA97: 30 | BC97: 235333 | BD97: DESCANSO PENDIENTE POR CIERRE LABORAL AL 30-04-2026 | BP97: 75000 | CI97: 473333
A98: 97 | B98: 26128372-7 | C98: 26128372 | D98: VILNORD | F98: MACELICE | G98: AYUDANTE GEOSINTETICOS | H98: 46054 | I98: D | J98: M | K98: 14X14 B | L98: 1790000090 | M98: 3 | N98: 3 | O98: 3 | P98: 3 | Q98: 3 | R98: 3 | S98: 3 | T98: 2 | U98: 2 | V98: 2 | W98: 2 | X98: 2 | Y98: 2 | Z98: 2 | AA98: 2 | AB98: 2 | AC98: 2 | AD98: 2 | AE98: 2 | AF98: 2 | AG98: 2 | AH98: 3 | AI98: 3 | AJ98: 3 | AK98: 3 | AL98: 3 | AM98: 3 | AN98: 3 | AO98: 3 | AP98: 3 | AR98: 0 | AS98: 14 | AT98: 16 | AU98: 0 | AV98: 0 | AW98: 0 | AX98: 0 | AY98: 0 | AZ98: 0 | BA98: 30 | BC98: 130833 | BD98: DESCANSO PENDIENTE POR CIERRE LABORAL AL 30-04-2026 | BP98: 75000 | CI98: 473333 | CJ98: 213354
A99: 98 | B99: 17296868-6 | C99: 17296868 | D99: YAEGER | E99: GONZALEZ | F99: BORIS CAMILO | G99: OPERADOR RETROEXCAVADORA | H99: 45992 | I99: D | J99: M | K99: 14x14 B | L99: 1790000090 | M99: 3 | N99: 3 | O99: 3 | P99: 3 | Q99: 3 | R99: 3 | S99: 3 | T99: 2 | U99: 2 | V99: 2 | W99: 2 | X99: 2 | Y99: 2 | Z99: 2 | AA99: 3 | AB99: 3 | AC99: 3 | AD99: 3 | AE99: 3 | AF99: 3 | AG99: 3 | AH99: 3 | AI99: 3 | AJ99: 3 | AK99: 3 | AL99: 3 | AM99: 3 | AN99: 3 | AO99: 3 | AP99: 3 | AR99: 0 | AS99: 7 | AT99: 23 | AU99: 0 | AV99: 0 | AW99: 0 | AX99: 0 | AY99: 0 | AZ99: 0 | BA99: 30 | BP99: 75000 | CI99: 315555
A100: 99 | B100: 15012307-0 | C100: 15012307 | D100: YAÑEZ | E100: VELIZ | F100: JORGE ANDRES | G100: MAESTRO SEGUNDA GEOSINTETICOS | H100: 46041 | I100: D | J100: M | K100: 14X14 B | L100: 1790000090 | M100: 3 | N100: 3 | O100: 3 | P100: 3 | Q100: 3 | R100: 3 | S100: 3 | T100: 4 | U100: 4 | V100: 4 | W100: 4 | X100: 4 | Y100: 4 | Z100: 4 | AA100: 4 | AB100: 4 | AC100: 4 | AD100: 4 | AE100: 4 | AF100: 4 | AG100: 4 | AH100: 4 | AI100: 3 | AR100: 0 | AS100: 0 | AT100: 8 | AU100: 15 | AV100: 0 | AW100: 0 | AX100: 0 | AY100: 0 | AZ100: 0 | BA100: 8 | CI100: 473333
...

Sheet Hoja1
